Workbook

Sheet 00 Read me
A1: Project V-Drop — D2C unit economics, subscription economics and price architecture
A2: Built by pricing-economist, 2026-09-22. British English, £ sterling. All prices UK.
A5: STATUS | B5: ILLUSTRATIVE. No manufacturer quote exists for any COGS line in this model. Every COGS figure is an ESTIMATE or an ASSUMPTION with a low/base/high range. Do not quote a margin from this workbook as a fact.
A7: WHAT THIS MODELS | B7: The current concept per notes/decisions.md (2026-09-22), NOT docs/master-brief.md:
B8: 1. D2C only. No retail, no retailer margin, no cannibalisation problem. CAC is the entire growth model.
B9: 2. A single 'super morning drink' — one effervescent tablet daily: a tasty drink, a full essential daily multivitamin load, plus caffeine and L-theanine. Multivitamin sense of 'everything you need', not an AG1-style greens stack.
B10: 3. Three products maximum.
B11: 4. The differentiator is taste and ease of use — explicitly not potency, not claims, not ingredients. Taste is therefore costed as a COGS line, not a rounding error (see Inputs I-23).
B12: 5. Formulation excludes cordyceps (A-041 stop-sale), Alpha-GPC (A-010 unauthorised), lion's mane 20:1 (A-042 probably novel) and zinc bisglycinate (A-043 source form unconfirmed). Vitamins and minerals in permitted source forms only.
A14: NON-NEGOTIABLES APPLIED | B14: VAT (A-007): every UK consumer price includes 20% VAT. Net price = RRP / 1.2. No margin in this workbook is computed on a VAT-inclusive price. £29.99 = £24.99 net; £19.99 = £16.66 net.
B15: Both margins shown: GROSS MARGIN = net revenue minus COGS. CONTRIBUTION = gross margin minus fulfilment, postage, payment fees, breakage and returns (and retailer/distributor margin where relevant).
B16: Payment fees are charged on the amount actually billed (VAT-inclusive), not on net revenue. Modelled that way.
A18: CONTROLS (Inputs sheet, cells B3:B5) | B18: B3 Scenario switch: 1 = Downside, 2 = Base, 3 = Upside. Drives the 'Selected' column and sheet 03.
B19: B4 Tablet format switch: 1 = 3.5 g tablet, 2 = 4.5 g tablet. Drives tablet mass, tablet COGS and shipped weight (A-019 / A-032 / decision of 2026-09-22 that the payload race is off).
B20: B5 Case included in the headline starter kit: 1 = yes, 0 = no. Sheet 03 shows both variants side by side regardless (A-025).
A22: COLOUR CONVENTION | B22: Blue font = an input you may change. Black = a formula. Do not overwrite a black cell.
A24: SOURCING HEALTH WARNING | B24: This session's egress policy refuses CONNECT to retailer and brand domains (403 at the proxy); three previous runs confirmed it is environment policy. Every competitor price in sheet 02 is inherited from a search-engine summary, not a direct read of the page. Treat the competitor ladder as MEDIUM confidence at best. Royal Mail tariffs in Inputs I-41..I-45 were re-checked this session via search summaries only and CONTRADICT the figures previously recorded in A-006 — see the note on those rows.
A26: SHEETS | B26: 01 Inputs · 02 Competitor ladder · 03 Unit economics · 04 Subscription economics · 05 Channel consistency · 06 Scenarios & sensitivity · 07 Price architectures
A28: THE THREE THINGS THAT DECIDE THIS BUSINESS | B28: 1. CAC (A-028). The brief contains no CAC line at all. Health & wellness carries the highest median Meta CPM of any vertical. With no retail discovery route, CAC payback is the model.
B29: 2. Churn (single-product supplement subscriptions run 8-15%/month). It compounds against CAC.
B30: 3. Taste-led COGS. A taste-led strategy costed like a commodity one produces a false margin. I-23 is the line to argue about.

Sheet 01 Inputs
A1: 01 INPUTS — every driver, with label, method and source
A2: Blue = input. Low / Base / High are genuine ranges, not decoration. 'Selected' follows the scenario switch in B3.
A3: CTRL | B3: SCENARIO SWITCH (1 = Downside, 2 = Base, 3 = Upside) | C3: 2
B4: TABLET FORMAT SWITCH (1 = 3.5 g tablet, 2 = 4.5 g tablet) | C4: 1
B5: CASE IN HEADLINE STARTER KIT (1 = yes, 0 = no) | C5: 1
B6: ACTIVES GRADE (1 = commodity USP source forms, 2 = branded / patented bioavailable forms) | C6: 1
B7: CAFFEINE (1 = contains caffeine, 0 = caffeine-free) << set to 0 by the decision of 2026-09-22 | C7: 0
A9: Ref | B9: Input | C9: Unit | D9: Low | E9: Base | F9: High | G9: Selected | H9: Label | I9: Method / reasoning | J9: Source URL | K9: Checked | L9: Conf. | M9: Assumption
B10: A. TAX AND GENERAL
A11: VAT | B11: VAT rate on the product (standard-rated) | C11: % | D11: 0.2 | E11: 0.2 | F11: 0.2 | G11: =CHOOSE($C$3,D11,E11,F11) | H11: FACT | I11: HMRC VAT Notice 701/14: vitamin and mineral supplements, and preparations for making beverages, are standard-rated. Net price = RRP / 1.2. Confirm with an accountant before filing. | J11: https://www.gov.uk/government/publications/vat-notice-70114-food | K11: 2026-09-22 | L11: high | M11: A-007
A12: FX | B12: GBP per USD (for US-sourced ad benchmarks) | C12: GBP/USD | D12: 1.27 | E12: 1.27 | F12: 1.27 | G12: =CHOOSE($C$3,D12,E12,F12) | H12: ASSUMPTION | I12: Working rate. Used only to translate the US-quoted Meta CPA benchmark into a sanity check; the CAC inputs below are set in £ directly. | K12: 2026-09-22 | L12: low
B13: B. PACK ARCHITECTURE AND USAGE (A-014 — repaired by the daily-ritual decision)
A14: TABG | B14: Tablet mass | C14: g | D14: =CHOOSE($C$4,3.5,4.5) | E14: =CHOOSE($C$4,3.5,4.5) | F14: =CHOOSE($C$4,3.5,4.5) | G14: =CHOOSE($C$3,D14,E14,F14) | H14: ASSUMPTION | I14: Driven by the tablet format switch (C4). The 4.5 g / 33% active load existed to win a price-to-potency argument the user has declined to have (decision 2026-09-22). 3.5 g is cheaper per unit, lighter to post, eases A-032 density and A-004 case geometry. Both modelled as scenarios. | K14: 2026-09-22 | L14: n/a | M14: A-019, A-032
A15: PACK | B15: Servings per monthly pack | C15: tablets | D15: 30 | E15: 30 | F15: 30 | G15: =CHOOSE($C$3,D15,E15,F15) | H15: ASSUMPTION | I15: Follows the usage, not the brief. A morning ritual is genuinely daily, so the pack should be a calendar month of servings. The brief's 24 was sized against the OLD occasion set (office/gym days) and over-shipped by ~45% at those occasions — that finding is now superseded. | K15: 2026-09-22 | L15: n/a | M15: A-014
A16: USE | B16: Servings actually consumed per month | C16: servings/mo | D16: 24 | E16: 29 | F16: 31 | G16: =CHOOSE($C$3,D16,E16,F16) | H16: ESTIMATE | I16: Daily ritual with realistic slippage. Low = drifts to weekdays only (~5.5/wk). Base = 29 (misses ~1 day/month). High = 31 (occasional second tablet). Supersedes the 8/16/26 range in customer-segments.md §3.3, which was measured against occasion-based use, not a morning ritual. NEEDS SURVEY VALIDATION. | K16: 2026-09-22 | L16: low-med | M16: A-014
A17: QPACK | B17: Servings per quarterly prepay pack | C17: tablets | D17: 90 | E17: 90 | F17: 90 | G17: =CHOOSE($C$3,D17,E17,F17) | H17: ASSUMPTION | I17: Three monthly packs shipped together. Tests whether cadence, not price, is the lever on CAC payback. | K17: 2026-09-22 | L17: n/a
B18: C. COGS BUILD-UP PER TABLET (illustrative until manufacturers quote — A-002)
A19: C_BASE | B19: Effervescent base and excipients (citric acid, sodium/potassium carbonates, bulking, lubricant) | C19: £/tablet | D19: 0.008 | E19: 0.012 | F19: 0.018 | G19: =CHOOSE($C$3,D19,E19,F19) | H19: ESTIMATE | I19: An effervescent tablet is ~50-75% acid/carbonate couple by mass. Commodity food-grade inputs at £2.50-4.00/kg applied to ~2.4-3.1 g of base. Arithmetic is mine; prices are not quoted. | K19: 2026-09-22 | L19: low | M19: A-019
A20: C_VIT | B20: Vitamin and mineral premix — full essential daily panel, permitted GB source forms | C20: £/tablet | D20: 0.02 | E20: 0.035 | F20: 0.055 | G20: =CHOOSE($C$3,D20,E20,F20) | H20: ESTIMATE | I20: A full-NRV multivitamin panel is only a few hundred mg (A-038). Premix, not individual dosing. EXCLUDES zinc bisglycinate (A-043 — source form unconfirmed); assumes zinc citrate/gluconate. Magnesium is the mass driver and is assumed partial-NRV: a full 375 mg NRV as citrate would not fit and would push this line up. | K20: 2026-09-22 | L20: low | M20: A-038, A-043
A21: C_ACT | B21: Caffeine + L-theanine — REMOVED BY DECISION (caffeine-free, 2026-09-22) | C21: £/tablet | D21: =0.015*$C$7 | E21: =0.028*$C$7 | F21: =0.045*$C$7 | G21: =CHOOSE($C$3,D21,E21,F21) | H21: ESTIMATE | I21: ZERO under the caffeine-free decision; switch C7 to 1 to see what caffeine would have cost. The money is small (caffeine is near-free; L-theanine bulk grades £120-250/kg drove the old figure). WHAT IS NOT SMALL IS THE COMPLIANCE SAVING. Going caffeine-free removes the whole A-024 workstream: no >150 mg/L test, no age verification at the D2C checkout (see input AV), no FIC Annex III 4.1/4.2 warning statements competing for space on a 23 mm tablet's pack, no EGCG exposure (A-044) and no L-theanine novel-food question (A-037). It also removes the only ingredient in the formulation with a live regulatory clock on it. | K21: 2026-09-22 | L21: low | M21: A-024, A-037, A-044
A22: C_TASTE | B22: PREMIUM FLAVOUR SYSTEM — natural flavour, Reb-M steviol glycosides (E960), spray-dried fruit powders | C22: £/tablet | D22: 0.015 | E22: 0.035 | F22: 0.07 | G22: =CHOOSE($C$3,D22,E22,F22) | H22: ESTIMATE | I22: THE DIFFERENTIATOR LINE. The user's decision makes taste the product, so this is hero spend, not overhead. Range spans a competent commodity flavour (low) to a genuinely premium sensory matrix with real fruit powder and top-grade Reb-M (high). Monk fruit DELETED — not an authorised GB sweetener (A-018), so the brief's two-option sensory matrix has one option. A taste-led strategy costed like a commodity one is the fastest route to a false margin: at the high end this line alone is 23% of tablet COGS. | K22: 2026-09-22 | L22: low | M22: A-018
A23: C_CONV | B23: Tableting and effervescent-line conversion (low-RH suite, tooling time, line rate) | C23: £/tablet | D23: 0.035 | E23: 0.055 | F23: 0.09 | G23: =CHOOSE($C$3,D23,E23,F23) | H23: ESTIMATE | I23: Effervescent blends must be made below 20% RH and sealed immediately (A-005), and building an effervescent line is quoted at 30-60% more expensive than a standard tablet line. This is the structural COGS premium the format carries regardless of what is in it. | J23: https://www.jinlupacking.com/blogs/effervescent-tablets-guide/ ; https://selvita.com/our-science/resources/blog-articles/effervescent-tablets-a-lasting-trend | K23: 2026-09-22 | L23: low | M23: A-005
A24: C_QC | B24: QC, stability testing amortisation, yield loss and overage | C24: £/tablet | D24: 0.005 | E24: 0.01 | F24: 0.02 | G24: =CHOOSE($C$3,D24,E24,F24) | H24: ESTIMATE | I24: Accelerated and real-time stability programmes amortised across the first runs, plus scrap. | K24: 2026-09-22 | L24: low
A25: C_PAT | B25: BRANDED / PATENTED SOURCE-FORM UPLIFT (applies only when switch C6 = 2) | C25: £/tablet | D25: 0.035 | E25: 0.08 | F25: 0.16 | G25: =CHOOSE($C$3,D25,E25,F25) | H25: ASSUMPTION | I25: THE 'CLINICAL BUT TASTY' LINE, added 2026-09-22 on CSO direction. vitamin-category-map.md §9 and A-049 say the minimum condition for a survivable premium is carrying something own-label cannot — a branded active at its trialled dose, in the LYMA pattern — because the authorised claims (A-045) are equally available to a £0.06/serving Tesco effervescent. Branded chelates and bioavailable forms (e.g. amino-acid chelated minerals, a branded folate, a branded K2, a branded ascorbate) typically run 3-10x the price of commodity oxides, sulfates and carbonates, and several carry a per-kilo licence or logo fee on top. Applied across a full daily panel this is the largest single swing in the COGS build-up. RANGE IS WIDE ON PURPOSE: no quote exists. RISK, NOT BLOCKER (A-043): GB permitted source forms were frozen by Schedule 2 of the Nutrition (Amendment etc.) (EU Exit) Regs 2019 at end-2020 and have taken ONE amendment since (SI 2023/28, which added only nicotinamide riboside chloride and magnesium citrate malate). A branded form that is freely available in the EU or US may simply not be a permitted GB source form. Every branded form must be checked against Schedule 2 as currently amended BEFORE it is designed into a premium story, because the story does not survive substituting it out. | J25: https://www.legislation.gov.uk/uksi/2023/28 | K25: 2026-09-22 | L25: low | M25: A-043, A-045, A-049
A26: C_UPL | B26: Uplift factor applied if the 4.5 g tablet is chosen | C26: x | D26: =CHOOSE($C$4,1,1.15) | E26: =CHOOSE($C$4,1,1.20) | F26: =CHOOSE($C$4,1,1.28) | G26: =CHOOSE($C$3,D26,E26,F26) | H26: ESTIMATE | I26: More base mass, more compression time, more active headroom. Applies automatically when switch C4 = 2. NOTE: the payload pressure is now low — potency is not the differentiator and the product is caffeine-free — so the 3.5 g tablet (C4 = 1) is the default and the burden of proof sits on anyone arguing for 4.5 g. | K26: 2026-09-22 | L26: low | M26: A-019
A27: C_TAB_C | B27: TABLET COGS — COMMODITY source forms | C27: £/tablet | D27: =SUM(D19:D24)*D26 | E27: =SUM(E19:E24)*E26 | F27: =SUM(F19:F24)*F26 | G27: =CHOOSE($C$3,D27,E27,F27) | H27: ESTIMATE | I27: Cross-check: format-options.md §8 estimated £0.06-0.10 for a commodity 3.5 g tablet. This model sits above that even on commodity forms, deliberately — because the premium taste system and a full daily panel are not commodity inputs. The brief's £2.20 refill COGS for 24 tablets implies £0.092/tablet (A-002, DISPUTED). | K27: 2026-09-22 | L27: low | M27: A-002
A28: C_TAB_P | B28: TABLET COGS — BRANDED / PATENTED source forms | C28: £/tablet | D28: =D27+D25*D26 | E28: =E27+E25*E26 | F28: =F27+F25*F26 | G28: =CHOOSE($C$3,D28,E28,F28) | H28: ESTIMATE | I28: The 'clinical' formulation. Sheet 07 shows what it does to the price floor. | K28: 2026-09-22 | L28: low | M28: A-049
A29: C_TAB | B29: TOTAL TABLET COGS (follows switch C6) | C29: £/tablet | D29: =CHOOSE($C$6,D27,D28) | E29: =CHOOSE($C$6,E27,E28) | F29: =CHOOSE($C$6,F27,F28) | G29: =CHOOSE($C$3,D29,E29,F29) | H29: ESTIMATE | I29: This is the figure every other sheet uses. | K29: 2026-09-22 | L29: low | M29: A-002
B30: D. PACKAGING AND HARDWARE COGS
A31: C_BLI | B31: Blister per tablet (alu/alu sealed strip — required by A-005) | C31: £/tablet | D31: 0.008 | E31: 0.015 | F31: 0.028 | G31: =CHOOSE($C$3,D31,E31,F31) | H31: ESTIMATE | I31: Loose tablets in a repeatedly-opened case do not meet the moisture specification (A-005, near-disproved). Individually sealed blisters are the fix and they add COGS. Includes materials plus blistering conversion. | J31: https://prosafenutra.com/effervescent-tablet-manufacturer-mastering-stability-moisture-control/ | K31: 2026-09-22 | L31: low | M31: A-005
A32: C_CAR | B32: Refill carton and letterbox mailer, per order | C32: £/order | D32: 0.18 | E32: 0.3 | F32: 0.55 | G32: =CHOOSE($C$3,D32,E32,F32) | H32: ESTIMATE | I32: Printed carton plus a rigid flat mailer that holds the <=25 mm depth. Depth compliance is not free: it needs a board spec that does not bulge. | K32: 2026-09-22 | L32: low | M32: A-006
A33: C_INS | B33: Insert, leaflet and label, per order | C33: £/order | D33: 0.05 | E33: 0.1 | F33: 0.2 | G33: =CHOOSE($C$3,D33,E33,F33) | H33: ESTIMATE | I33: A food supplement carries a long mandatory-particulars set (claims-library §8.1), so the leaflet is not optional. | K33: 2026-09-22 | L33: low
A34: C_CASE | B34: Aluminium pocket case — unit cost at launch volumes | C34: £/unit | D34: 6 | E34: 9.5 | F34: 15 | G34: =CHOOSE($C$3,D34,E34,F34) | H34: ASSUMPTION | I34: CNC-milled and anodised at 1,500-5,000 units. No quote obtained; this is my judgement of the shape of the cost, not a price. The brief's £5.50 covered the case AND 24 tablets, which is not credible at launch volumes (A-001). Deep-drawn stamping is far cheaper per unit but needs hard tooling and a much larger first run. | K34: 2026-09-22 | L34: low | M34: A-001, A-025
A35: C_TOOL | B35: Case tooling, fixtures, programming and first-article — one-off | C35: £ | D35: 1500 | E35: 4000 | F35: 9000 | G35: =CHOOSE($C$3,D35,E35,F35) | H35: ASSUMPTION | I35: CNC route. A stamped route is £8,000-£25,000 of hard tooling instead. | K35: 2026-09-22 | L35: low | M35: A-025
A36: C_TAMO | B36: Units over which case tooling is amortised | C36: units | D36: 5000 | E36: 3000 | F36: 1500 | G36: =CHOOSE($C$3,D36,E36,F36) | H36: ASSUMPTION | I36: Deliberately pessimistic at the High end: if the case is unproven (A-025) the first run is small and the amortisation is brutal. | K36: 2026-09-22 | L36: low | M36: A-025
A37: C_CASE_T | B37: CASE COST INCLUDING TOOLING AMORTISATION | C37: £/unit | D37: =D34+D35/D36 | E37: =E34+E35/E36 | F37: =F34+F35/F36 | G37: =CHOOSE($C$3,D37,E37,F37) | H37: ESTIMATE | I37: This is the number that decides whether the case belongs in the starter kit. Sheet 03 shows the starter kit with and without it. | K37: 2026-09-22 | L37: low | M37: A-025
B38: E. FULFILMENT, WEIGHT AND POSTAGE (A-006 — re-checked this session)
A39: FUL | B39: Fulfilment: 3PL pick, pack and handling, per order | C39: £/order | D39: 0.85 | E39: 1.3 | F39: 2.1 | G39: =CHOOSE($C$3,D39,E39,F39) | H39: ESTIMATE | I39: UK 3PL letterbox pick-and-pack at low volume, including receipt and storage recharge. No quote obtained. | K39: 2026-09-22 | L39: low
A40: W_BLI | B40: Blister carrier mass per tablet | C40: g | D40: 0.8 | E40: 1.2 | F40: 1.8 | G40: =CHOOSE($C$3,D40,E40,F40) | H40: ESTIMATE | I40: Alu/alu foil and lidding. | K40: 2026-09-22 | L40: low
A41: W_TARE | B41: Mailer, carton and insert tare mass | C41: g | D41: 28 | E41: 38 | F41: 55 | G41: =CHOOSE($C$3,D41,E41,F41) | H41: ESTIMATE | I41: Flat rigid mailer plus carton plus leaflet. | K41: 2026-09-22 | L41: low
A42: W_CASE | B42: Aluminium case mass | C42: g | D42: 55 | E42: 70 | F42: 90 | G42: =CHOOSE($C$3,D42,E42,F42) | H42: ESTIMATE | I42: 110 x 62 x 11 mm anodised aluminium shell (geometry itself is INCORRECT per A-004 — a redesign changes this). | K42: 2026-09-22 | L42: low | M42: A-004
A43: P100 | B43: Royal Mail 2nd Class Large Letter, 0-100 g | C43: £ | D43: 1.55 | E43: 1.55 | F43: 1.55 | G43: =CHOOSE($C$3,D43,E43,F43) | H43: ESTIMATE | I43: RE-CHECKED 2026-09-22 via search summaries and it CONTRADICTS A-006, which recorded £1.77 (1st) / £1.80. The figures now returned are: 2nd class Large Letter 0-100 g £1.55, unchanged at the 7 April 2026 revision; 1st class Large Letter 0-100 g returned as £3.30. A-006 appears to have conflated the 1st class LETTER price (£1.80) with the Large Letter price. NOT A DIRECT READ — royalmail.com and mailcoms.co.uk are both blocked by the egress proxy. Must be read from the tariff PDF before anyone commits. | J43: https://www.royalmail.com/prices2026 ; https://www.mailcoms.co.uk/current-royal-mail-postage-rates/ ; https://www.mymailingroom.com/rm-prices | K43: 2026-09-22 | L43: med | M43: A-006
A44: P250 | B44: Royal Mail 2nd Class Large Letter, 101-250 g << THE BASE CASE BAND | C44: £ | D44: 2.2 | E44: 2.2 | F44: 2.2 | G44: =CHOOSE($C$3,D44,E44,F44) | H44: ESTIMATE | I44: THIS IS THE BAND V-DROP LIVES IN AND IT IS STRUCTURAL. 30 x 3.5 g = 105 g of tablets alone, so the sub-100 g band is unreachable at a daily pack in either tablet size. The brief's 'under £1.60' is not achievable on any plausible pack. | J44: https://www.royalmail.com/prices2026 ; https://www.mailcoms.co.uk/current-royal-mail-postage-rates/ | K44: 2026-09-22 | L44: med | M44: A-006
A45: P500 | B45: Royal Mail 2nd Class Large Letter, 251-500 g | C45: £ | D45: 2.85 | E45: 2.85 | F45: 2.85 | G45: =CHOOSE($C$3,D45,E45,F45) | H45: ESTIMATE | I45: The band a 90-tablet quarterly pack falls into. 90 x 3.5 g = 315 g of tablets alone. | J45: https://www.royalmail.com/prices2026 | K45: 2026-09-22 | L45: med | M45: A-006
A46: P750 | B46: Royal Mail 2nd Class Large Letter, 501-750 g | C46: £ | D46: 3.75 | E46: 3.75 | F46: 3.75 | G46: =CHOOSE($C$3,D46,E46,F46) | H46: ESTIMATE | I46: 750 g and 25 mm depth are the hard Large Letter maxima. | J46: https://www.royalmail.com/prices2026 | K46: 2026-09-22 | L46: med | M46: A-006
A47: PPAR | B47: Royal Mail 2nd Class Small Parcel — what a TUBE competitor must pay | C47: £ | D47: 3.29 | E47: 3.69 | F47: 4.19 | G47: =CHOOSE($C$3,D47,E47,F47) | H47: ASSUMPTION | I47: THE ONE QUANTIFIED D2C COST ADVANTAGE THE FORMAT HAS. Large Letter depth is capped at 25 mm; a standard effervescent tube for a 23-27 mm tablet is ~28-30 mm in diameter, so every tube-based competitor must ship a parcel and V-Drop's flat blister architecture need not. I could not source the exact 2026 small-parcel tariff (proxy blocked), so this is a ranged assumption — but the BAND STRUCTURE and the 25 mm depth limit are not in doubt. | J47: https://www.royalmail.com/prices2026 ; research/format-options.md §7 | K47: 2026-09-22 | L47: low | M47: A-006, A-030
A48: PDIS | B48: Business / Mailmark discount multiplier on the stamp tariff | C48: x | D48: 0.55 | E48: 0.78 | F48: 1 | G48: =CHOOSE($C$3,D48,E48,F48) | H48: ASSUMPTION | I48: A real D2C subscription would post on a business account or via a consolidator, not on stamps. No rate card obtained. Base assumes a modest 22% discount; High (1.00) assumes stamp prices, i.e. no account at all. | K48: 2026-09-22 | L48: low | M48: A-006
B49: F. PAYMENT, BREAKAGE AND RETURNS
A50: PAY_R | B50: Payment processing rate | C50: % of billed amount | D50: 0.015 | E50: 0.019 | F50: 0.026 | G50: =CHOOSE($C$3,D50,E50,F50) | H50: ESTIMATE | I50: Stripe UK standard is 1.5% + 20p for UK cards, higher for EEA and international. Base blends in a realistic non-UK card mix. CHARGED ON THE VAT-INCLUSIVE AMOUNT — so the fee is levied on money that is partly HMRC's, which the brief ignores. | K50: 2026-09-22 | L50: med
A51: PAY_F | B51: Payment fixed fee per transaction | C51: £ | D51: 0.2 | E51: 0.2 | F51: 0.25 | G51: =CHOOSE($C$3,D51,E51,F51) | H51: ESTIMATE | I51: Per successful charge. | K51: 2026-09-22 | L51: med
A52: BRK | B52: Breakage / damage in transit — orders replaced | C52: % of orders | D52: 0.005 | E52: 0.015 | F52: 0.04 | G52: =CHOOSE($C$3,D52,E52,F52) | H52: ASSUMPTION | I52: Effervescent tablets are friable and moisture-sensitive; a letterbox mailer takes a beating. Cost of a replacement = COGS + fulfilment + postage, with no revenue against it. | K52: 2026-09-22 | L52: low
A53: AV | B53: Age verification at the D2C checkout — AVOIDED by going caffeine-free | C53: £/order | D53: =0.12*$C$7 | E53: =0.25*$C$7 | F53: =0.45*$C$7 | G53: =CHOOSE($C$3,D53,E53,F53) | H53: ASSUMPTION | I53: ZERO under the caffeine-free decision (switch C7 = 0). At 80 mg per 500 ml the Energy SKU was 160 mg/L, above the >150 mg/L threshold of the England under-16 restriction taking effect 6 April 2027, whose scope expressly covers products reconstituted as drinks — so an online sale would have needed age verification (A-024, exit C). A third-party AV check is a per-transaction cost AND a conversion cost at the single most fragile step in a D2C funnel. This row prices the per-order part only; the one-off part (legal review, pack warning copy, checkout build) is in the launch-capital block and is the larger number. | J53: https://www.gov.uk/government/news/childrens-health-further-protected-with-energy-drinks-ban | K53: 2026-09-22 | L53: low | M53: A-024
A54: RET | B54: Returns, refunds and goodwill credits | C54: % of orders | D54: 0.01 | E54: 0.025 | F54: 0.06 | G54: =CHOOSE($C$3,D54,E54,F54) | H54: ASSUMPTION | I54: A taste-led proposition invites 'I didn't like the flavour' refunds. The DMCC subscription regime (autumn 2026 earliest) mandates two cooling-off periods, which raises this line, not lowers it. | J54: https://www.hsfkramer.com/notes/crt/2026-04/time-to-start-preparing-for-the-new-uk-subscription-contracts-regime | K54: 2026-09-22 | L54: low | M54: A-013
B55: G. CHANNEL MARGINS — OUT OF PHASE 1 SCOPE (D2C-only decision, 2026-09-21). Retained for reference only.
A56: RM | B56: UK pharmacy / grocery retailer margin, % of sell price | C56: 0.3 | D56: 0.3 | E56: 0.4 | F56: 0.5 | G56: =CHOOSE($C$3,D56,E56,F56) | H56: ASSUMPTION | I56: NOT SOURCED. 40% is the conventional health-and-beauty figure but every retailer domain is blocked by the egress proxy, so it remains my working assumption, unchanged from A-029. Set to zero in every live D2C calculation on sheet 03; shown only in the greyed reference column. | K56: 2026-09-22 | L56: low | M56: A-029
A57: DM | B57: Distributor / wholesaler margin, % of trade price | C57: % | D57: 0.1 | E57: 0.15 | F57: 0.22 | G57: =CHOOSE($C$3,D57,E57,F57) | H57: ASSUMPTION | I57: NOT SOURCED. Applies only if a wholesaler sits between V-Drop and the retailer. Zero under D2C-only. | K57: 2026-09-22 | L57: low | M57: A-029
B58: H. CUSTOMER ACQUISITION COST (A-028 — the single biggest gap in the brief, which contains NO CAC line at all)
A59: CAC_M | B59: CAC — Meta paid social | C59: £/customer | D59: 32 | E59: 55 | F59: 95 | G59: =CHOOSE($C$3,D59,E59,F59) | H59: ASSUMPTION | I59: DELIBERATELY PESSIMISTIC. Health & wellness carries the HIGHEST median CPM of any Meta vertical, ~$21.80 (up ~19% YoY), with a median CPA of ~$38.55 (= £30.4 at 1.27), because Meta restricts the health advertiser pool. That CPA is a median across established accounts; a cold-start UK brand selling a £20-30 first order in a category with no shelf discovery should expect to sit above it, not at it. Third-party aggregator data, directional only. | J59: https://influee.co/gb/blog/facebook-ads-benchmarks ; https://www.triplewhale.com/blog/facebook-ads-benchmarks | K59: 2026-09-22 | L59: low | M59: A-028
A60: CAC_G | B60: CAC — Google paid search (brand + non-brand) | C60: £/customer | D60: 18 | E60: 30 | F60: 50 | G60: =CHOOSE($C$3,D60,E60,F60) | H60: ASSUMPTION | I60: Cheaper per conversion but volume-capped: nobody searches for a product category that does not yet exist. Non-brand terms ('effervescent multivitamin', 'morning vitamin drink') are thin; 'multivitamin' itself is contested by Vitabiotics, H&B and Amazon. | K60: 2026-09-22 | L60: low | M60: A-028
A61: CAC_I | B61: CAC — influencer and affiliate | C61: £/customer | D61: 28 | E61: 48 | F61: 80 | G61: =CHOOSE($C$3,D61,E61,F61) | H61: ASSUMPTION | I61: Taste-led product demos well on video, which argues this channel should be over-weighted. But ASA actively monitors supplement influencer content and every creative is a claims exposure (A-047). | K61: 2026-09-22 | L61: low | M61: A-028, A-047
A62: CAC_O | B62: CAC — organic, referral and earned | C62: £/customer | D62: 4 | E62: 9 | F62: 18 | G62: =CHOOSE($C$3,D62,E62,F62) | H62: ASSUMPTION | I62: Content, SEO and referral cost real money even when the media is free. Not zero. | K62: 2026-09-22 | L62: low | M62: A-028
A63: MIX_M | B63: Channel mix — Meta | C63: % | D63: 0.55 | E63: 0.55 | F63: 0.55 | G63: =CHOOSE($C$3,D63,E63,F63) | H63: ASSUMPTION | I63: Paid social must carry a D2C launch with no retail discovery route. | K63: 2026-09-22 | L63: low
A64: MIX_G | B64: Channel mix — Google | C64: % | D64: 0.2 | E64: 0.2 | F64: 0.2 | G64: =CHOOSE($C$3,D64,E64,F64) | H64: ASSUMPTION | K64: 2026-09-22 | L64: low
A65: MIX_I | B65: Channel mix — influencer / affiliate | C65: % | D65: 0.15 | E65: 0.15 | F65: 0.15 | G65: =CHOOSE($C$3,D65,E65,F65) | H65: ASSUMPTION | K65: 2026-09-22 | L65: low
A66: MIX_O | B66: Channel mix — organic / referral | C66: % | D66: 0.1 | E66: 0.1 | F66: 0.1 | G66: =CHOOSE($C$3,D66,E66,F66) | H66: ASSUMPTION | K66: 2026-09-22 | L66: low
A67: CAC | B67: BLENDED CAC | C67: £/customer | D67: =D59*D63+D60*D64+D61*D65+D62*D66 | E67: =E59*E63+E60*E64+E61*E65+E62*E66 | F67: =F59*F63+F60*F64+F61*F65+F62*F66 | G67: =CHOOSE($C$3,D67,E67,F67) | H67: ESTIMATE | I67: Mix-weighted. CAC is a net-of-VAT cost (ad spend VAT is recoverable once registered), so it is correctly compared against net contribution, which is what sheet 04 does. | K67: 2026-09-22 | L67: low | M67: A-028
B68: I. RETENTION
A69: CHURN | B69: Monthly churn, steady state | C69: %/month | D69: 0.06 | E69: 0.1 | F69: 0.15 | G69: =CHOOSE($C$3,D69,E69,F69) | H69: ESTIMATE | I69: Benchmarks put typical DTC supplement subscription churn at 5-8%/month and SINGLE-PRODUCT subscriptions at 8-15%/month. V-Drop is by design a single-product subscription (three products maximum, one ritual), so the 8-15% band is the right one and the base case sits inside it. | J69: https://eightx.co/blog/supplement-subscription-churn-rate-benchmark ; https://blog.jericommerce.com/resources/supplement-vitamin-brands-retention-statistics | K69: 2026-09-22 | L69: low-med | M69: A-014
A70: DROP1 | B70: Extra drop-off before the FIRST refill | C70: % of starters | D70: 0.1 | E70: 0.18 | F70: 0.28 | G70: =CHOOSE($C$3,D70,E70,F70) | H70: ASSUMPTION | I70: Most supplement subscription churn happens in months 1-3, and subscribers who perceive no benefit churn at 2-3x the later-tenure rate. A taste-led product should do BETTER than the benchmark here if the taste delivers — and far worse if it does not. This cell is where the whole strategy is tested. | K70: 2026-09-22 | L70: low | M70: A-014
A71: INVOL | B71: Involuntary churn (failed cards), added to monthly churn | C71: pp/month | D71: 0.005 | E71: 0.01 | F71: 0.02 | G71: =CHOOSE($C$3,D71,E71,F71) | H71: ASSUMPTION | I71: Card expiry and insufficient funds. Dunning recovers some of it; this is the residual. | K71: 2026-09-22 | L71: low
A72: CHURN_T | B72: TOTAL MONTHLY CHURN | C72: %/month | D72: =D69+D71 | E72: =E69+E71 | F72: =F69+F71 | G72: =CHOOSE($C$3,D72,E72,F72) | H72: ESTIMATE | I72: Voluntary plus involuntary. | K72: 2026-09-22 | L72: low
B73: J. PRICES — base architecture A1 ('the brief, corrected'). Other architectures are priced on sheet 07.
A74: PR_SK | B74: Starter kit including case — list RRP inc VAT | C74: £ | D74: 29.99 | E74: 29.99 | F74: 29.99 | G74: =CHOOSE($C$3,D74,E74,F74) | H74: ASSUMPTION | I74: The brief's price, retained for architecture A1. Net of VAT it is £24.99, not £29.99 (A-001). The brief's '80-82% gross margin' was computed on the VAT-inclusive price. | K74: 2026-09-22 | L74: n/a | M74: A-001
A75: PR_SKN | B75: Starter kit WITHOUT case — list RRP inc VAT | C75: £ | D75: 19.99 | E75: 19.99 | F75: 19.99 | G75: =CHOOSE($C$3,D75,E75,F75) | H75: ASSUMPTION | I75: The same 30 blistered tablets with no hardware. Lets the user see exactly what including the case costs at the moment of first purchase (A-025). | K75: 2026-09-22 | L75: n/a | M75: A-025
A76: PR_SUB | B76: Monthly subscription refill (30 tablets) — list RRP inc VAT | C76: £ | D76: 19.99 | E76: 19.99 | F76: 19.99 | G76: =CHOOSE($C$3,D76,E76,F76) | H76: ASSUMPTION | I76: The brief's price. Net of VAT it is £16.66 (A-002). NOTE A-027: half of UK consumers spend under £40/month on subscriptions IN TOTAL, so £19.99 is roughly 30-50% of the median subscriber's entire subscription budget. That is a real constraint from above and it is stronger evidence than the brief's invented '£20 bank audit threshold' (A-013 limb 2, DISPROVED — do not use). | J76: https://www.aquacard.co.uk/building-better-credit/subscription-spending-in-2025 | K76: 2026-09-22 | L76: n/a | M76: A-002, A-027, A-013
A77: PR_ONE | B77: One-off refill (30 tablets), non-subscriber — list RRP inc VAT | C77: £ | D77: 24.99 | E77: 24.99 | F77: 24.99 | G77: =CHOOSE($C$3,D77,E77,F77) | H77: ASSUMPTION | I77: Must sit ABOVE the subscription per serving or there is no reason to subscribe. 25% premium. The brief had the opposite structure (retail undercut subscription by 44% — A-003). | K77: 2026-09-22 | L77: n/a | M77: A-003
A78: PR_QTR | B78: Quarterly prepay (90 tablets) — list RRP inc VAT | C78: £ | D78: 54.99 | E78: 54.99 | F78: 54.99 | G78: =CHOOSE($C$3,D78,E78,F78) | H78: ASSUMPTION | I78: £18.33/month effective, a 8.3% saving on monthly. Pulls three months of cash forward, removes two fulfilment events, two postage charges and two payment fees, and removes two cancellation decision points. | K78: 2026-09-22 | L78: n/a
A79: PR_RET | B79: Retail tube (15 tablets) — RRP inc VAT. OUT OF SCOPE, reference only | C79: £ | D79: 6.99 | E79: 6.99 | F79: 6.99 | G79: =CHOOSE($C$3,D79,E79,F79) | H79: ASSUMPTION | I79: The brief's retail price. Retained solely so sheet 05 can show what the abandoned architecture did: £6.99/15 = £0.466/serving against a £0.833/serving subscription, a 44.1% inversion. Under D2C-only this is moot (A-003 superseded for Phase 1). | K79: 2026-09-22 | L79: n/a | M79: A-003
A80: PR_RETN | B80: Retail tube servings per pack | C80: tablets | D80: 15 | E80: 15 | F80: 15 | G80: =CHOOSE($C$3,D80,E80,F80) | H80: ASSUMPTION | K80: 2026-09-22 | L80: n/a | M80: A-003
B81: K. LAUNCH CAPITAL AND THE SHARED-BASE ARCHITECTURE (three products, one vitamin and mineral base)
A82: NPD_BASE | B82: Formulation, sensory development and stability — the SHARED base blend | C82: £ | D82: 8000 | E82: 16000 | F82: 32000 | G82: =CHOOSE($C$3,D82,E82,F82) | H82: ASSUMPTION | I82: One vitamin and mineral base carrying the premium flavour system, developed once. Taste iteration is the expensive part and it is where the money SHOULD go under the differentiator decision. No quote obtained. | K82: 2026-09-22 | L82: low
A83: NPD_LAYER | B83: Formulation and stability — each differentiating layer on top of the base | C83: £ | D83: 2500 | E83: 5000 | F83: 10000 | G83: =CHOOSE($C$3,D83,E83,F83) | H83: ASSUMPTION | I83: A layer is a small delta on a proven base: new actives, a flavour variant, a fresh stability run. Costed at roughly 30% of a full formulation. | K83: 2026-09-22 | L83: low
A84: NSKU | B84: Number of products at launch | C84: SKUs | D84: 3 | E84: 3 | F84: 3 | G84: =CHOOSE($C$3,D84,E84,F84) | H84: ASSUMPTION | I84: Range capped at three by the decision of 2026-09-22. All three share one vitamin and mineral base. | K84: 2026-09-22 | L84: n/a
A85: NPD_TOT | B85: TOTAL FORMULATION COST — shared-base architecture | C85: £ | D85: =D82+D83*D84 | E85: =E82+E83*E84 | F85: =F82+F83*F84 | G85: =CHOOSE($C$3,D85,E85,F85) | H85: ESTIMATE | I85: Shared base plus three layers. | K85: 2026-09-22 | L85: low
A86: NPD_TRIP | B86: Memo: TOTAL FORMULATION COST if the three SKUs were formulated independently | C86: £ | D86: =D82*D84 | E86: =E82*E84 | F86: =F82*F84 | G86: =CHOOSE($C$3,D86,E86,F86) | H86: ESTIMATE | I86: The counterfactual. The gap between this row and the one above is what the shared-base architecture is worth in NPD alone — before the MOQ effect below, which is larger. | K86: 2026-09-22 | L86: low
A87: MOQ | B87: Manufacturer MOQ per distinct blend | C87: tablets | D87: 60000 | E87: 100000 | F87: 150000 | G87: =CHOOSE($C$3,D87,E87,F87) | H87: ESTIMATE | I87: Effervescent MOQs of ~100,000 tablets are quoted by contract manufacturers. THIS IS THE REAL PRIZE IN THE SHARED-BASE ARCHITECTURE: one MOQ on the base blend instead of three, because the differentiating layer is a smaller sub-run, not a separate product. | J87: https://prosafenutra.com/tablet-manufacturing/ ; https://www.lebenformulation.com/blog/effervescent-tablet-formulation-contract-manufacturing | K87: 2026-09-22 | L87: low
A88: MOQ_LAYER | B88: Additional MOQ per differentiating layer | C88: tablets | D88: 15000 | E88: 25000 | F88: 40000 | G88: =CHOOSE($C$3,D88,E88,F88) | H88: ASSUMPTION | I88: A short run off the shared base. If the manufacturer will not do this, the shared-base saving evaporates and the answer is to launch ONE product, not three. ASK THIS QUESTION IN THE FIRST MANUFACTURER CALL. | K88: 2026-09-22 | L88: low
A89: CAFF_ONEOFF | B89: Memo: one-off compliance cost AVOIDED by going caffeine-free | C89: £ | D89: =3000*$C$7 | E89: =7500*$C$7 | F89: =15000*$C$7 | G89: =CHOOSE($C$3,D89,E89,F89) | H89: ASSUMPTION | I89: Regulatory review of the >150 mg/L position, FIC Annex III warning copy through artwork, an age-gate at the checkout, and the standing risk of a £2,500-per-breach enforcement regime from April 2027. Zero under the caffeine-free decision. Not a unit cost — a workstream that no longer exists. | K89: 2026-09-22 | L89: low | M89: A-024
A90: REALF | B90: Realised revenue factor (promotions, intro discounts, mix) | C90: x | D90: 0.85 | E90: 0.93 | F90: 0.99 | G90: =CHOOSE($C$3,D90,E90,F90) | H90: ESTIMATE | I90: Nobody realises list price. Welcome offers, win-back discounts, referral credits and loyalty tiers all leak. Vitabiotics runs 20% off orders 1-2 rising to 30% from order 6 — a deepening tenure discount is the category norm and it is a permanent revenue leak, not a promotion. Base 0.93 is optimistic against that benchmark. | J90: https://www.vitabiotics.com/pages/subscribe | K90: 2026-09-22 | L90: low | M90: A-036

Sheet 02 Competitor ladder
A1: 02 COMPETITOR PRICE LADDER — and the question of WHICH ladder
A2: Pulled from research/competitors.csv (77 rows; those with a parseable RRP and servings count are shown). Price per serving computed live, inc VAT and net of VAT (÷1.2). EVERY PRICE HERE IS A SEARCH-ENGINE SUMMARY, NOT A DIRECT READ OF THE PAGE — the egress proxy refuses retailer and brand domains. Medium confidence at best.
A4: THE STRATEGIC POINT. V-Drop can be judged on two different ladders and they give opposite answers. On the EFFERVESCENT ladder (Tesco £0.060 -> Boots £0.088 -> Berocca Immuno £0.500 -> Berocca Mind £0.666 -> Applied Nutrition Creatine £0.744) £0.833/serving would be the dearest effervescent tablet of any kind in the dataset, at 9.5-13.9x own-label. On the VITAMIN CATEGORY ladder it ranks 30th of 41, BELOW Wild Nutrition (£0.950-1.013 — the user's own named reference), Heights, AG1 and LYMA, and within 4% of Wellwoman Max (£0.804). Columns I and J compute both ranks live. My view is in drafts/pricing-recommendation.md: a taste-and-ritual proposition sold D2C is judged on the ladder the customer is standing on, and under D2C-only there is no shelf, so the comparison happens in search and paid social against DAILY MORNING SUPPLEMENTS, not against a Boots effervescent fixture. But the effervescent anchor does not disappear just because we would rather it did — it is one Google search away, and it is the single most commoditised price point in UK vitamins.
A6: Brand | B6: Product | C6: Format | D6: Category | E6: Servings/pack | F6: RRP inc VAT | G6: £/serving inc VAT | H6: £/serving NET (÷1.2) | I6: Eff? | J6: Vit? | K6: Rank: eff. ladder | L6: Rank: vitamin ladder | M6: Source URL(s) | N6: Checked | O6: Confidence
A8: V-DROP (proposed) | B8: Subscription refill — architecture A1 | C8: effervescent tablet | D8: vitamin (morning multi) | E8: ='01 Inputs'!$E$15 | F8: ='01 Inputs'!$E$76 | G8: =IF(E8=0,"",F8/E8) | H8: =IF(E8=0,"",G8/(1+'01 Inputs'!$G$11)) | I8: Y | J8: Y | K8: =IF(I8="Y",COUNTIFS($I$8:$I$58,"Y",$G$8:$G$58,"<"&G8)+1,"") | L8: =IF(J8="Y",COUNTIFS($J$8:$J$58,"Y",$G$8:$G$58,"<"&G8)+1,"") | M8: This workbook, architecture A1 (sheet 07) | N8: 2026-09-22 | O8: n/a
A9: V-DROP (proposed) | B9: Subscription refill — architecture A2 | C9: effervescent tablet | D9: vitamin (morning multi) | E9: 30 | F9: 22.99 | G9: =IF(E9=0,"",F9/E9) | H9: =IF(E9=0,"",G9/(1+'01 Inputs'!$G$11)) | I9: Y | J9: Y | K9: =IF(I9="Y",COUNTIFS($I$8:$I$58,"Y",$G$8:$G$58,"<"&G9)+1,"") | L9: =IF(J9="Y",COUNTIFS($J$8:$J$58,"Y",$G$8:$G$58,"<"&G9)+1,"") | M9: This workbook, architecture A2 (sheet 07) | N9: 2026-09-22 | O9: n/a
A10: V-DROP (proposed) | B10: Quarterly prepay per serving — architecture A3 | C10: effervescent tablet | D10: vitamin (morning multi) | E10: ='01 Inputs'!$E$17 | F10: ='01 Inputs'!$E$78 | G10: =IF(E10=0,"",F10/E10) | H10: =IF(E10=0,"",G10/(1+'01 Inputs'!$G$11)) | I10: Y | J10: Y | K10: =IF(I10="Y",COUNTIFS($I$8:$I$58,"Y",$G$8:$G$58,"<"&G10)+1,"") | L10: =IF(J10="Y",COUNTIFS($J$8:$J$58,"Y",$G$8:$G$58,"<"&G10)+1,"") | M10: This workbook, architecture A3 (sheet 07) | N10: 2026-09-22 | O10: n/a
A11: V-DROP (proposed) | B11: Starter kit month 1 (with case) — A1 | C11: effervescent tablet + case | D11: vitamin (morning multi) | E11: ='01 Inputs'!$E$15 | F11: ='01 Inputs'!$E$74 | G11: =IF(E11=0,"",F11/E11) | H11: =IF(E11=0,"",G11/(1+'01 Inputs'!$G$11)) | I11: Y | J11: Y | K11: =IF(I11="Y",COUNTIFS($I$8:$I$58,"Y",$G$8:$G$58,"<"&G11)+1,"") | L11: =IF(J11="Y",COUNTIFS($J$8:$J$58,"Y",$G$8:$G$58,"<"&G11)+1,"") | M11: This workbook | N11: 2026-09-22 | O11: n/a
A12: Waterdrop | B12: Microdrink | C12: effervescent cube | D12: vitamin | E12: 12 | F12: 8.99 | G12: =IF(E12=0,"",F12/E12) | H12: =IF(E12=0,"",G12/(1+'01 Inputs'!$G$11)) | I12: Y | J12: Y | K12: =IF(I12="Y",COUNTIFS($I$8:$I$58,"Y",$G$8:$G$58,"<"&G12)+1,"") | L12: =IF(J12="Y",COUNTIFS($J$8:$J$58,"Y",$G$8:$G$58,"<"&G12)+1,"") | M12: https://en.waterdrop.com/products/microdrink-blackcurrant | https://en.waterdrop.com/collections/subscription | https://en.waterdrop.com/blogs/magazine/drink-more-water-get-vitamins | N12: 2026-09-21 | O12: med (price and vitamin figures from search summaries of wate
A13: Phizz | B13: Daily 3-in-1 Hydration, Electrolytes & Vitamins | C13: effervescent tablet in tube | D13: mixed | E13: 20 | F13: 7.99 | G13: =IF(E13=0,"",F13/E13) | H13: =IF(E13=0,"",G13/(1+'01 Inputs'!$G$11)) | I13: Y | J13: Y | K13: =IF(I13="Y",COUNTIFS($I$8:$I$58,"Y",$G$8:$G$58,"<"&G13)+1,"") | L13: =IF(J13="Y",COUNTIFS($J$8:$J$58,"Y",$G$8:$G$58,"<"&G13)+1,"") | M13: https://www.phizz.co/products/3-in-1-hydration-electrolytes-vitamins-20 | https://www.tesco.com/groceries/en-GB/products/312575988 | https://www.boots.com/phizz-orange-3-in-1-hydration-electrolytes-and-vitamins-effervescent-tablets-20-tablets-10285064 | https://www.stirlinghealthfoodstore.co.uk/products/14937/hydration-electrolytes-vitamins.htm | N13: 2026-09-21 | O13: med (price £7.99 corroborated by two independent UK sources
A14: Berocca (Bayer) | B14: Berocca Mind | C14: effervescent tablet in tube | D14: focus | E14: 15 | F14: 9.99 | G14: =IF(E14=0,"",F14/E14) | H14: =IF(E14=0,"",G14/(1+'01 Inputs'!$G$11)) | I14: Y | J14: Y | K14: =IF(I14="Y",COUNTIFS($I$8:$I$58,"Y",$G$8:$G$58,"<"&G14)+1,"") | L14: =IF(J14="Y",COUNTIFS($J$8:$J$58,"Y",$G$8:$G$58,"<"&G14)+1,"") | M14: https://www.boots.com/berocca-mind-berry-tablets-15s-10358306 | https://www.bayer.com/sites/default/files/berocca-mind-pil.pdf | https://www.berocca.com.au/products/mind/berocca-mind-film-coated-tablets | N14: 2026-09-21 | O14: med (Boots price from search summary; formulation described
A15: Berocca (Bayer) | B15: Berocca Immuno | C15: effervescent tablet in tube | D15: vitamin | E15: 30 | F15: 15 | G15: =IF(E15=0,"",F15/E15) | H15: =IF(E15=0,"",G15/(1+'01 Inputs'!$G$11)) | I15: Y | J15: Y | K15: =IF(I15="Y",COUNTIFS($I$8:$I$58,"Y",$G$8:$G$58,"<"&G15)+1,"") | L15: =IF(J15="Y",COUNTIFS($J$8:$J$58,"Y",$G$8:$G$58,"<"&G15)+1,"") | M15: https://www.boots.com/berocca-immuno-orange-effervescent-tablets-30s-10372054 | N15: 2026-09-21 | O15: med (price from search summary of the Boots page; doses UNVE
A16: Tonic Health | B16: High Dose Immunity drink sachets | C16: effervescent powder sachet | D16: vitamin | E16: 10 | F16: 9 | G16: =IF(E16=0,"",F16/E16) | H16: =IF(E16=0,"",G16/(1+'01 Inputs'!$G$11)) | I16: Y | J16: Y | K16: =IF(I16="Y",COUNTIFS($I$8:$I$58,"Y",$G$8:$G$58,"<"&G16)+1,"") | L16: =IF(J16="Y",COUNTIFS($J$8:$J$58,"Y",$G$8:$G$58,"<"&G16)+1,"") | M16: https://www.trolley.co.uk/product/tonic-lemon-cold-immunity-drink-10-sachet/TIX573 | N16: 2026-09-21 | O16: low (price is a range from an aggregator, not a single retai
A17: Boots | B17: High Strength Vitamin C 1000 mg effervescent | C17: effervescent tablet in tube | D17: vitamin | E17: 20 | F17: 1.75 | G17: =IF(E17=0,"",F17/E17) | H17: =IF(E17=0,"",G17/(1+'01 Inputs'!$G$11)) | I17: Y | J17: Y | K17: =IF(I17="Y",COUNTIFS($I$8:$I$58,"Y",$G$8:$G$58,"<"&G17)+1,"") | L17: =IF(J17="Y",COUNTIFS($J$8:$J$58,"Y",$G$8:$G$58,"<"&G17)+1,"") | M17: https://www.boots.com/boots-blackcurrant-flavour-effervescent-vitamin-c-1000-mg-20-tablets-10275001 | https://www.trolley.co.uk/product/boots-high-strength-blackcurrant-flavour-effervescent-vitamin-c-1000-mg-20-tablets/YSM896 | N17: 2026-09-21 | O17: med (price from search summary; 'from' pricing may not be th
A18: Tesco | B18: Health High Strength Vitamin C effervescent | C18: effervescent tablet in tube | D18: vitamin | E18: 20 | F18: 1.19 | G18: =IF(E18=0,"",F18/E18) | H18: =IF(E18=0,"",G18/(1+'01 Inputs'!$G$11)) | I18: Y | J18: Y | K18: =IF(I18="Y",COUNTIFS($I$8:$I$58,"Y",$G$8:$G$58,"<"&G18)+1,"") | L18: =IF(J18="Y",COUNTIFS($J$8:$J$58,"Y",$G$8:$G$58,"<"&G18)+1,"") | M18: https://www.grocefully.com/uk/product/tesco/tesco-health-high-strength-vitamin-c-effervescent-tablets-252479807 | https://www.tesco.com/shop/en-GB/products/252479807 | N18: 2026-09-21 | O18: med (two prices seen for the same line: £1.19 and £1.50)
A19: Science in Sport (SiS) | B19: GO Hydro | C19: effervescent tablet in tube | D19: hydration | E19: 20 | F19: 6.99 | G19: =IF(E19=0,"",F19/E19) | H19: =IF(E19=0,"",G19/(1+'01 Inputs'!$G$11)) | I19: Y | J19: N | K19: =IF(I19="Y",COUNTIFS($I$8:$I$58,"Y",$G$8:$G$58,"<"&G19)+1,"") | L19: =IF(J19="Y",COUNTIFS($J$8:$J$58,"Y",$G$8:$G$58,"<"&G19)+1,"") | M19: https://www.scienceinsport.com/sis-hydro-tablets-pack | https://www.tesco.com/groceries/en-GB/products/274761998 | https://startfitness.co.uk/products/sis-go-hydro-20-tablet-tube | N19: 2026-09-21 | O19: med (several UK prices seen: £6.50, £6.99, £7.60; £6.99 take
A20: HIGH5 | B20: ZERO electrolyte tablets | C20: effervescent tablet in tube | D20: hydration | E20: 20 | F20: 8 | G20: =IF(E20=0,"",F20/E20) | H20: =IF(E20=0,"",G20/(1+'01 Inputs'!$G$11)) | I20: Y | J20: N | K20: =IF(I20="Y",COUNTIFS($I$8:$I$58,"Y",$G$8:$G$58,"<"&G20)+1,"") | L20: =IF(J20="Y",COUNTIFS($J$8:$J$58,"Y",$G$8:$G$58,"<"&G20)+1,"") | M20: https://www.tesco.com/groceries/en-GB/products/317875026 | https://pricespy.co.uk/product.php?p=3330836 | https://highfive.co.uk/products/zero | https://www.boots.com/high5-zero-orange-and-cherry-electrolyte-hydration-tabs-20-tabs-10345397 | N20: 2026-09-21 | O20: med (price spread £3.99-£8.00; Tesco standard used for the l
A21: Liquid I.V. (Unilever) | B21: Hydration Multiplier | C21: powder stick sachet | D21: hydration | E21: 15 | F21: 16 | G21: =IF(E21=0,"",F21/E21) | H21: =IF(E21=0,"",G21/(1+'01 Inputs'!$G$11)) | I21: N | J21: N | K21: =IF(I21="Y",COUNTIFS($I$8:$I$58,"Y",$G$8:$G$58,"<"&G21)+1,"") | L21: =IF(J21="Y",COUNTIFS($J$8:$J$58,"Y",$G$8:$G$58,"<"&G21)+1,"") | M21: https://www.latestdeals.co.uk/deals/liquid-iv-hydration-multiplier-electrolyte-powder-mix-strawberry-15-sachets-boots | https://www.boots.com/liquid-iv-hydration-multiplier-electrolyte-powder-mix-strawberry-15-sachets-10342019 | https://www.liquid-iv.co.uk/products/hydration-multiplier | N21: 2026-09-21 | O21: med (price corroborated by a deals aggregator citing Boots;
A22: Dioralyte (Sanofi) | B22: Oral rehydration salts | C22: powder sachet | D22: hydration | E22: 6 | F22: 4.9 | G22: =IF(E22=0,"",F22/E22) | H22: =IF(E22=0,"",G22/(1+'01 Inputs'!$G$11)) | I22: N | J22: N | K22: =IF(I22="Y",COUNTIFS($I$8:$I$58,"Y",$G$8:$G$58,"<"&G22)+1,"") | L22: =IF(J22="Y",COUNTIFS($J$8:$J$58,"Y",$G$8:$G$58,"<"&G22)+1,"") | M22: https://www.boots.com/dioralyte-blackcurrent-6-sachets-10020148 | https://cache.trolley.co.uk/product/dioralyte-blackcurrant-6-sachets/RIS484 | N22: 2026-09-21 | O22: med (Boots price from search summary; price spread noted)
A23: Applied Nutrition | B23: Electrolyte Hydration effervescent | C23: effervescent tablet in tube | D23: hydration | E23: 20 | F23: 5 | G23: =IF(E23=0,"",F23/E23) | H23: =IF(E23=0,"",G23/(1+'01 Inputs'!$G$11)) | I23: Y | J23: N | K23: =IF(I23="Y",COUNTIFS($I$8:$I$58,"Y",$G$8:$G$58,"<"&G23)+1,"") | L23: =IF(J23="Y",COUNTIFS($J$8:$J$58,"Y",$G$8:$G$58,"<"&G23)+1,"") | M23: https://www.hollandandbarrett.com/shop/product/electrolyte-hydration-tablets-vimto-20-x-4g-6100006019 | https://www.hollandandbarrett.com/shop/product/applied-nutrition-electrolyte-hydration-lemon-lime-20-tablets-6100002242 | N23: 2026-09-21 | O23: med (RRP and promo price both stated in the search summary o
... A58: Ankhway (ATC MN LTD) | B58: 10-in-1 Mushroom Gummies | C58: gummy | D58: adaptogen | E58: 30 | F58: 29.99 | G58: =IF(E58=0,"",F58/E58) | H58: =IF(E58=0,"",G58/(1+'01 Inputs'!$G$11)) | I58: N | J58: Y | K58: =IF(I58="Y",COUNTIFS($I$8:$I$58,"Y",$G$8:$G$58,"<"&G58)+1,"") | L58: =IF(J58="Y",COUNTIFS($J$8:$J$58,"Y",$G$8:$G$58,"<"&G58)+1,"") | M58: https://ankhway.com/products/mushroom-gummies | https://ankhway.com/ | https://www.amazon.co.uk/Ankhway-10-Mushroom-Gummies-Supplement/dp/B0CMWRQ4GT | https://topshelfmushrooms.com/ankhway-mushroom-gummies-review-2026-formula-verified/ | https://ankhway.com/pages/lions-mane-mushroom | N58: 2026-09-22 | O58: low-med (brand and product existence CONFIRMED across the br
A60: LADDER SUMMARY (live)
A61: Cheapest in the effervescent set (set INCLUDES V-Drop's own proposed rows) | B61: =INDEX($G$8:$G$58,MATCH(1,$K$8:$K$58,0))
A62: Dearest in the effervescent set (set INCLUDES V-Drop's own proposed rows) | B62: =INDEX($G$8:$G$58,MATCH(MAX($K$8:$K$58),$K$8:$K$58,0))
A63: Mean effervescent £/serving | B63: =SUMPRODUCT(($I$8:$I$58="Y")*$G$8:$G$58)/COUNTIF($I$8:$I$58,"Y")
A64: Count of effervescent rows | B64: =COUNTIF($I$8:$I$58,"Y")
A65: V-Drop A1 rank within the effervescent ladder (1 = cheapest) | B65: =K8
A66: V-Drop A1 rank within the vitamin-category ladder (1 = cheapest) | B66: =L8
A67: Rows in the vitamin-category ladder | B67: =COUNTIF($J$8:$J$58,"Y")
A68: V-Drop A1 sub £/serving inc VAT | B68: =G8
A69: V-Drop A1 sub £/serving NET | B69: =H8
A70: V-Drop A1 vs Tesco own-label effervescent vitamin C (£0.060) | B70: =G8/0.06
A71: V-Drop A1 vs Berocca Mind (£0.666) | B71: =G8/0.666
A72: V-Drop A1 vs Waterdrop (£0.749) | B72: =G8/0.749
A73: V-Drop A1 vs Wild Nutrition 45+ (£1.013) | B73: =G8/1.013
A74: V-Drop A1 vs AG1 subscription (£2.633) | B74: =G8/2.633

Sheet 03 Unit economics
A1: 03 UNIT ECONOMICS BY SKU — waterfall from RRP inc VAT to contribution per serving
A2: D2C only (decision, 2026-09-21). Driven by the scenario switch at '01 Inputs'!C3 and the tablet switch at C4. The retail column is OUT OF SCOPE and shown greyed, for continuity only.
B4: Line | C4: D2C starter kit (WITH case) | D4: D2C starter kit (NO case) | E4: D2C subscription refill (monthly, 30) | F4: D2C one-off refill (30) | G4: D2C quarterly prepay (90) | H4: Retail tube (15) OUT OF SCOPE — reference | I4: Note
B5: Pack size (servings) | C5: ='01 Inputs'!$G$15 | D5: ='01 Inputs'!$G$15 | E5: ='01 Inputs'!$G$15 | F5: ='01 Inputs'!$G$15 | G5: ='01 Inputs'!$G$17 | H5: ='01 Inputs'!$G$80
B6: List RRP inc VAT | C6: ='01 Inputs'!$G$74 | D6: ='01 Inputs'!$G$75 | E6: ='01 Inputs'!$G$76 | F6: ='01 Inputs'!$G$77 | G6: ='01 Inputs'!$G$78 | H6: ='01 Inputs'!$G$79 | I6: Brief's headline prices. VAT correction applied immediately below.
B7: Realised revenue factor | C7: ='01 Inputs'!$G$90 | D7: ='01 Inputs'!$G$90 | E7: ='01 Inputs'!$G$90 | F7: ='01 Inputs'!$G$90 | G7: ='01 Inputs'!$G$90 | H7: ='01 Inputs'!$G$90
B8: Realised price billed inc VAT | C8: =C6*C7 | D8: =D6*D7 | E8: =E6*E7 | F8: =F6*F7 | G8: =G6*G7 | H8: =H6*H7
B9: less VAT at 20% | C9: =C8*'01 Inputs'!$G$11/(1+'01 Inputs'!$G$11) | D9: =D8*'01 Inputs'!$G$11/(1+'01 Inputs'!$G$11) | E9: =E8*'01 Inputs'!$G$11/(1+'01 Inputs'!$G$11) | F9: =F8*'01 Inputs'!$G$11/(1+'01 Inputs'!$G$11) | G9: =G8*'01 Inputs'!$G$11/(1+'01 Inputs'!$G$11) | H9: =H8*'01 Inputs'!$G$11/(1+'01 Inputs'!$G$11) | I9: A-007. The brief computed its 80-82% and 88-89% margins on the row above this one. That is the whole error.
B10: NET PRICE (ex VAT) | C10: =C8/(1+'01 Inputs'!$G$11) | D10: =D8/(1+'01 Inputs'!$G$11) | E10: =E8/(1+'01 Inputs'!$G$11) | F10: =F8/(1+'01 Inputs'!$G$11) | G10: =G8/(1+'01 Inputs'!$G$11) | H10: =H8/(1+'01 Inputs'!$G$11) | I10: £29.99 -> £24.99 net; £19.99 -> £16.66 net.
B11: less retailer margin | C11: =C10*0 | D11: =D10*0 | E11: =E10*0 | F11: =F10*0 | G11: =G10*0 | H11: =H10*'01 Inputs'!$G$56 | I11: Zero under D2C-only. Retail column applies the A-029 assumption (40%, NOT SOURCED).
B12: less distributor margin | C12: =(C10-C11)*0 | D12: =(D10-D11)*0 | E12: =(E10-E11)*0 | F12: =(F10-F11)*0 | G12: =(G10-G11)*0 | H12: =(H10-H11)*'01 Inputs'!$G$57
B13: NET REVENUE REALISED BY V-DROP | C13: =C10-C11-C12 | D13: =D10-D11-D12 | E13: =E10-E11-E12 | F13: =F10-F11-F12 | G13: =G10-G11-G12 | H13: =H10-H11-H12
B14: COGS — tablets | C14: =C5*'01 Inputs'!$G$29 | D14: =D5*'01 Inputs'!$G$29 | E14: =E5*'01 Inputs'!$G$29 | F14: =F5*'01 Inputs'!$G$29 | G14: =G5*'01 Inputs'!$G$29 | H14: =H5*'01 Inputs'!$G$29
B15: COGS — blisters | C15: =C5*'01 Inputs'!$G$31 | D15: =D5*'01 Inputs'!$G$31 | E15: =E5*'01 Inputs'!$G$31 | F15: =F5*'01 Inputs'!$G$31 | G15: =G5*'01 Inputs'!$G$31 | H15: =H5*'01 Inputs'!$G$31
B16: COGS — carton and mailer | C16: ='01 Inputs'!$G$32 | D16: ='01 Inputs'!$G$32 | E16: ='01 Inputs'!$G$32 | F16: ='01 Inputs'!$G$32 | G16: ='01 Inputs'!$G$32 | H16: =0
B17: COGS — insert and label | C17: ='01 Inputs'!$G$33 | D17: ='01 Inputs'!$G$33 | E17: ='01 Inputs'!$G$33 | F17: ='01 Inputs'!$G$33 | G17: ='01 Inputs'!$G$33 | H17: ='01 Inputs'!$G$33
B18: COGS — aluminium case (incl. tooling amortisation) | C18: =1*'01 Inputs'!$G$37 | D18: =0*'01 Inputs'!$G$37 | E18: =0*'01 Inputs'!$G$37 | F18: =0*'01 Inputs'!$G$37 | G18: =0*'01 Inputs'!$G$37 | H18: =0*'01 Inputs'!$G$37 | I18: A-025. Compare column C with column D: the difference is exactly what the case costs you at the moment of first purchase.
B19: TOTAL COGS | C19: =SUM(C14:C18) | D19: =SUM(D14:D18) | E19: =SUM(E14:E18) | F19: =SUM(F14:F18) | G19: =SUM(G14:G18) | H19: =SUM(H14:H18)
B20: GROSS MARGIN £ | C20: =C13-C19 | D20: =D13-D19 | E20: =E13-E19 | F20: =F13-F19 | G20: =G13-G19 | H20: =H13-H19 | I20: GROSS MARGIN. This is the number the brief quoted — and it quoted it on the wrong revenue base.
B21: GROSS MARGIN % of net revenue | C21: =IF(C13=0,"",C20/C13) | D21: =IF(D13=0,"",D20/D13) | E21: =IF(E13=0,"",E20/E13) | F21: =IF(F13=0,"",F20/F13) | G21: =IF(G13=0,"",G20/G13) | H21: =IF(H13=0,"",H20/H13)
B22: Shipped weight (g) | C22: =C5*'01 Inputs'!$G$14+C5*'01 Inputs'!$G$40+'01 Inputs'!$G$41+1*'01 Inputs'!$G$42 | D22: =D5*'01 Inputs'!$G$14+D5*'01 Inputs'!$G$40+'01 Inputs'!$G$41+0*'01 Inputs'!$G$42 | E22: =E5*'01 Inputs'!$G$14+E5*'01 Inputs'!$G$40+'01 Inputs'!$G$41+0*'01 Inputs'!$G$42 | F22: =F5*'01 Inputs'!$G$14+F5*'01 Inputs'!$G$40+'01 Inputs'!$G$41+0*'01 Inputs'!$G$42 | G22: =G5*'01 Inputs'!$G$14+G5*'01 Inputs'!$G$40+'01 Inputs'!$G$41+0*'01 Inputs'!$G$42 | H22: =H5*'01 Inputs'!$G$14+H5*'01 Inputs'!$G$40+'01 Inputs'!$G$41+0*'01 Inputs'!$G$42 | I22: 30 x 3.5 g = 105 g of tablets alone, so the 0-100 g band is unreachable. See A-006.
B23: Fulfilment (3PL pick and pack) | C23: ='01 Inputs'!$G$39 | D23: ='01 Inputs'!$G$39 | E23: ='01 Inputs'!$G$39 | F23: ='01 Inputs'!$G$39 | G23: ='01 Inputs'!$G$39 | H23: =0
B24: Postage (Royal Mail band, after business discount) | C24: =IF(C22<=100,'01 Inputs'!$G$43,IF(C22<=250,'01 Inputs'!$G$44,IF(C22<=500,'01 Inputs'!$G$45,IF(C22<=750,'01 Inputs'!$G$46,'01 Inputs'!$G$47))))*'01 Inputs'!$G$48 | D24: =IF(D22<=100,'01 Inputs'!$G$43,IF(D22<=250,'01 Inputs'!$G$44,IF(D22<=500,'01 Inputs'!$G$45,IF(D22<=750,'01 Inputs'!$G$46,'01 Inputs'!$G$47))))*'01 Inputs'!$G$48 | E24: =IF(E22<=100,'01 Inputs'!$G$43,IF(E22<=250,'01 Inputs'!$G$44,IF(E22<=500,'01 Inputs'!$G$45,IF(E22<=750,'01 Inputs'!$G$46,'01 Inputs'!$G$47))))*'01 Inputs'!$G$48 | F24: =IF(F22<=100,'01 Inputs'!$G$43,IF(F22<=250,'01 Inputs'!$G$44,IF(F22<=500,'01 Inputs'!$G$45,IF(F22<=750,'01 Inputs'!$G$46,'01 Inputs'!$G$47))))*'01 Inputs'!$G$48 | G24: =IF(G22<=100,'01 Inputs'!$G$43,IF(G22<=250,'01 Inputs'!$G$44,IF(G22<=500,'01 Inputs'!$G$45,IF(G22<=750,'01 Inputs'!$G$46,'01 Inputs'!$G$47))))*'01 Inputs'!$G$48 | H24: =0 | I24: Royal Mail 2nd class Large Letter, 101-250 g band at base. Re-checked 2026-09-22 and it contradicts A-006 — see Inputs I-41.
B25: Payment fees (on the VAT-inclusive billed amount) | C25: =C8*'01 Inputs'!$G$50+'01 Inputs'!$G$51 | D25: =D8*'01 Inputs'!$G$50+'01 Inputs'!$G$51 | E25: =E8*'01 Inputs'!$G$50+'01 Inputs'!$G$51 | F25: =F8*'01 Inputs'!$G$50+'01 Inputs'!$G$51 | G25: =G8*'01 Inputs'!$G$50+'01 Inputs'!$G$51 | H25: =H8*'01 Inputs'!$G$50+'01 Inputs'!$G$51 | I25: Charged on the VAT-inclusive amount. The brief ignores payment fees entirely.
B26: Age verification at checkout (nil — caffeine-free) | C26: ='01 Inputs'!$G$53 | D26: ='01 Inputs'!$G$53 | E26: ='01 Inputs'!$G$53 | F26: ='01 Inputs'!$G$53 | G26: ='01 Inputs'!$G$53 | H26: ='01 Inputs'!$G$53 | I26: Nil under the caffeine-free decision of 2026-09-22. Set '01 Inputs'!C7 to 1 to see the cost of the architecture we have just walked away from (A-024).
B27: Breakage / damage replacement | C27: ='01 Inputs'!$G$52*(C19+C23+C24) | D27: ='01 Inputs'!$G$52*(D19+D23+D24) | E27: ='01 Inputs'!$G$52*(E19+E23+E24) | F27: ='01 Inputs'!$G$52*(F19+F23+F24) | G27: ='01 Inputs'!$G$52*(G19+G23+G24) | H27: ='01 Inputs'!$G$52*(H19+H23+H24)
B28: Returns and refunds | C28: ='01 Inputs'!$G$54*(C13+C19+C24) | D28: ='01 Inputs'!$G$54*(D13+D19+D24) | E28: ='01 Inputs'!$G$54*(E13+E19+E24) | F28: ='01 Inputs'!$G$54*(F13+F19+F24) | G28: ='01 Inputs'!$G$54*(G13+G19+G24) | H28: ='01 Inputs'!$G$54*(H13+H19+H24)
B29: TOTAL VARIABLE COSTS | C29: =SUM(C23:C28) | D29: =SUM(D23:D28) | E29: =SUM(E23:E28) | F29: =SUM(F23:F28) | G29: =SUM(G23:G28) | H29: =SUM(H23:H28)
B30: CONTRIBUTION £ | C30: =C20-C29 | D30: =D20-D29 | E30: =E20-E29 | F30: =F20-F29 | G30: =G20-G29 | H30: =H20-H29 | I30: CONTRIBUTION. This is the only number that can be compared against CAC.
B31: CONTRIBUTION MARGIN % of net revenue | C31: =IF(C13=0,"",C30/C13) | D31: =IF(D13=0,"",D30/D13) | E31: =IF(E13=0,"",E30/E13) | F31: =IF(F13=0,"",F30/F13) | G31: =IF(G13=0,"",G30/G13) | H31: =IF(H13=0,"",H30/H13)
B32: CONTRIBUTION PER SERVING £ | C32: =C30/C5 | D32: =D30/D5 | E32: =E30/E5 | F32: =F30/F5 | G32: =G30/G5 | H32: =H30/H5 | I32: The number to put on the competitor ladder — after costs, not before.
B33: List price per serving, inc VAT | C33: =C6/C5 | D33: =D6/D5 | E33: =E6/E5 | F33: =F6/F5 | G33: =G6/G5 | H33: =H6/H5
B34: List price per serving, NET | C34: =C33/(1+'01 Inputs'!$G$11) | D34: =D33/(1+'01 Inputs'!$G$11) | E34: =E33/(1+'01 Inputs'!$G$11) | F34: =F33/(1+'01 Inputs'!$G$11) | G34: =G33/(1+'01 Inputs'!$G$11) | H34: =H33/(1+'01 Inputs'!$G$11)
B35: Memo: parcel postage a TUBE competitor must pay | C35: ='01 Inputs'!$G$47*'01 Inputs'!$G$48 | D35: ='01 Inputs'!$G$47*'01 Inputs'!$G$48 | E35: ='01 Inputs'!$G$47*'01 Inputs'!$G$48 | F35: ='01 Inputs'!$G$47*'01 Inputs'!$G$48 | G35: ='01 Inputs'!$G$47*'01 Inputs'!$G$48 | H35: ='01 Inputs'!$G$47*'01 Inputs'!$G$48
B36: Memo: LETTERBOX ADVANTAGE per order (A-006) | C36: =C35-C24 | D36: =D35-D24 | E36: =E35-E24 | F36: =F35-F24 | G36: =G35-G24 | H36: =0 | I36: THE FORMAT'S ONLY QUANTIFIED D2C COST ADVANTAGE. A tube competitor fails the 25 mm Large Letter depth limit and must ship a parcel. This row is the size of the edge, per order.
B39: WATERFALL CHECK — subscription refill, base case
B40: RRP inc VAT | C40: =E6
B41: less VAT | C41: =-E9
B42: -> Net price | C42: =E10
B43: less retailer / distributor margin (nil under D2C) | C43: =-E11-E12
B44: less COGS | C44: =-E19
B45: -> GROSS MARGIN | C45: =E20
B46: less fulfilment | C46: =-E23
B47: less postage | C47: =-E24
B48: less payment fees | C48: =-E25
B49: less age verification (nil — caffeine-free) | C49: =-E26
B50: less breakage | C50: =-E27
B51: less returns | C51: =-E28
B52: -> CONTRIBUTION PER UNIT | C52: =E30
B53: -> CONTRIBUTION PER SERVING | C53: =E32
B55: Note: the realised revenue factor (Inputs I-REALF) is applied before VAT is stripped, so the 'RRP inc VAT' row above is list price and the VAT line is computed on the amount actually billed. At a factor below 1.00 the two do not reconcile exactly — that gap IS the promotional leakage.
B57: ACTIVES GRADE — what 'clinical' costs (subscription refill, base inputs)
C58: Commodity USP forms | D58: Branded / patented forms | E58: Difference
B59: Tablet COGS £/tablet | C59: ='01 Inputs'!$E$27 | D59: ='01 Inputs'!$E$28 | E59: =D59-C59
B60: Pack COGS (30 tablets, all components) | C60: =('01 Inputs'!$E$15*'01 Inputs'!$E$27+'01 Inputs'!$E$15*'01 Inputs'!$E$31+'01 Inputs'!$E$32+'01 Inputs'!$E$33) | D60: =('01 Inputs'!$E$15*'01 Inputs'!$E$28+'01 Inputs'!$E$15*'01 Inputs'!$E$31+'01 Inputs'!$E$32+'01 Inputs'!$E$33) | E60: =D60-C60
B61: Net revenue (ex VAT, after realised factor) | C61: =(('01 Inputs'!$E$76*'01 Inputs'!$E$90)/(1+'01 Inputs'!$E$11)) | D61: =(('01 Inputs'!$E$76*'01 Inputs'!$E$90)/(1+'01 Inputs'!$E$11)) | E61: =D61-C61
B62: GROSS MARGIN £ | C62: =(('01 Inputs'!$E$76*'01 Inputs'!$E$90)/(1+'01 Inputs'!$E$11))-('01 Inputs'!$E$15*'01 Inputs'!$E$27+'01 Inputs'!$E$15*'01 Inputs'!$E$31+'01 Inputs'!$E$32+'01 Inputs'!$E$33) | D62: =(('01 Inputs'!$E$76*'01 Inputs'!$E$90)/(1+'01 Inputs'!$E$11))-('01 Inputs'!$E$15*'01 Inputs'!$E$28+'01 Inputs'!$E$15*'01 Inputs'!$E$31+'01 Inputs'!$E$32+'01 Inputs'!$E$33) | E62: =D62-C62
B63: Gross margin % | C63: =C62/C61 | D63: =D62/D61 | E63: =D63-C63
B64: CONTRIBUTION £ | C64: =(('01 Inputs'!$E$76*'01 Inputs'!$E$90)/(1+'01 Inputs'!$E$11))-('01 Inputs'!$E$15*'01 Inputs'!$E$27+'01 Inputs'!$E$15*'01 Inputs'!$E$31+'01 Inputs'!$E$32+'01 Inputs'!$E$33)-('01 Inputs'!$E$39+(IF(('01 Inputs'!$E$15*'01 Inputs'!$E$14+'01 Inputs'!$E$15*'01 Inputs'!$E$40+'01 Inputs'!$E$41)<=100,'01 Inputs'!$E$43,IF(('01 Inputs'!$E$15*'01 Inputs'!$E$14+'01 Inputs'!$E$15*'01 Inputs'!$E$40+'01 Inputs'!$E$41)<=250,'01 Inputs'!$E$44,IF(('01 Inputs'!$E$15*'01 Inputs'!$E$14+'01 Inputs'!$E$15*'01 Inputs'!$E$40+'01 Inputs'!$E$41)<=500,'01 Inputs'!$E$45,IF(('01 Inputs'!$E$15*'01 Inputs'!$E$14+'01 Inputs'!$E$15*'01 Inputs'!$E$40+'01 Inputs'!$E$41)<=750,'01 Inputs'!$E$46,'01 Inputs'!$E$47))))*'01 Inputs'!$E$48)+(('01 Inputs'!$E$76*'01 Inputs'!$E$90)*'01 Inputs'!$E$50+'01 Inputs'!$E$51)+'01 Inputs'!$E$53+('01 Inputs'!$E$52*(('01 Inputs'!$E$15*'01 Inputs'!$E$27+'01 Inputs'!$E$15*'01 Inputs'!$E$31+'01 Inputs'!$E$32+'01 Inputs'!$E$33)+'01 Inputs'!$E$39+(IF(('01 Inputs'!$E$15*'01 Inputs'!$E$14+'01 Inputs'!$E$15*'01 Inputs'!$E$40+'01 Inputs'!$E$41)<=100,'01 Inputs'!$E$43,IF(('01 Inputs'!$E$15*'01 Inputs'!$E$14+'01 Inputs'!$E$15*'01 Inputs'!$E$40+'01 Inputs'!$E$41)<=250,'01 Inputs'!$E$44,IF(('01 Inputs'!$E$15*'01 Inputs'!$E$14+'01 Inputs'!$E$15*'01 Inputs'!$E$40+'01 Inputs'!$E$41)<=500,'01 Inputs'!$E$45,IF(('01 Inputs'!$E$15*'01 Inputs'!$E$14+'01 Inputs'!$E$15*'01 Inputs'!$E$40+'01 Inputs'!$E$41)<=750,'01 Inputs'!$E$46,'01 Inputs'!$E$47))))*'01 Inputs'!$E$48)))+('01 Inputs'!$E$54*((('01 Inputs'!$E$76*'01 Inputs'!$E$90)/(1+'01 Inputs'!$E$11))+('01 Inputs'!$E$15*'01 Inputs'!$E$27+'01 Inputs'!$E$15*'01 Inputs'!$E$31+'01 Inputs'!$E$32+'01 Inputs'!$E$33)+(IF(('01 Inputs'!$E$15*'01 Inputs'!$E$14+'01 Inputs'!$E$15*'01 Inputs'!$E$40+'01 Inputs'!$E$41)<=100,'01 Inputs'!$E$43,IF(('01 Inputs'!$E$15*'01 Inputs'!$E$14+'01 Inputs'!$E$15*'01 Inputs'!$E$40+'01 Inputs'!$E$41)<=250,'01 Inputs'!$E$44,IF(('01 Inputs'!$E$15*'01 Inputs'!$E$14+'01 Inputs'!$E$15*'01 Inputs'!$E$40+'01 Inputs'!$E$41)<=500,'01 Inputs'!$E$45,IF(('01 Inputs'!$E$15*'01 Inputs'!$E$14+'01 Inputs'!$E$15*'01 Inputs'!$E$40+'01 Inputs'!$E$41)<=750,'01 Inputs'!$E$46,'01 Inputs'!$E$47))))*'01 Inputs'!$E$48)))) | D64: =(('01 Inputs'!$E$76*'01 Inputs'!$E$90)/(1+'01 Inputs'!$E$11))-('01 Inputs'!$E$15*'01 Inputs'!$E$28+'01 Inputs'!$E$15*'01 Inputs'!$E$31+'01 Inputs'!$E$32+'01 Inputs'!$E$33)-('01 Inputs'!$E$39+(IF(('01 Inputs'!$E$15*'01 Inputs'!$E$14+'01 Inputs'!$E$15*'01 Inputs'!$E$40+'01 Inputs'!$E$41)<=100,'01 Inputs'!$E$43,IF(('01 Inputs'!$E$15*'01 Inputs'!$E$14+'01 Inputs'!$E$15*'01 Inputs'!$E$40+'01 Inputs'!$E$41)<=250,'01 Inputs'!$E$44,IF(('01 Inputs'!$E$15*'01 Inputs'!$E$14+'01 Inputs'!$E$15*'01 Inputs'!$E$40+'01 Inputs'!$E$41)<=500,'01 Inputs'!$E$45,IF(('01 Inputs'!$E$15*'01 Inputs'!$E$14+'01 Inputs'!$E$15*'01 Inputs'!$E$40+'01 Inputs'!$E$41)<=750,'01 Inputs'!$E$46,'01 Inputs'!$E$47))))*'01 Inputs'!$E$48)+(('01 Inputs'!$E$76*'01 Inputs'!$E$90)*'01 Inputs'!$E$50+'01 Inputs'!$E$51)+'01 Inputs'!$E$53+('01 Inputs'!$E$52*(('01 Inputs'!$E$15*'01 Inputs'!$E$28+'01 Inputs'!$E$15*'01 Inputs'!$E$31+'01 Inputs'!$E$32+'01 Inputs'!$E$33)+'01 Inputs'!$E$39+(IF(('01 Inputs'!$E$15*'01 Inputs'!$E$14+'01 Inputs'!$E$15*'01 Inputs'!$E$40+'01 Inputs'!$E$41)<=100,'01 Inputs'!$E$43,IF(('01 Inputs'!$E$15*'01 Inputs'!$E$14+'01 Inputs'!$E$15*'01 Inputs'!$E$40+'01 Inputs'!$E$41)<=250,'01 Inputs'!$E$44,IF(('01 Inputs'!$E$15*'01 Inputs'!$E$14+'01 Inputs'!$E$15*'01 Inputs'!$E$40+'01 Inputs'!$E$41)<=500,'01 Inputs'!$E$45,IF(('01 Inputs'!$E$15*'01 Inputs'!$E$14+'01 Inputs'!$E$15*'01 Inputs'!$E$40+'01 Inputs'!$E$41)<=750,'01 Inputs'!$E$46,'01 Inputs'!$E$47))))*'01 Inputs'!$E$48)))+('01 Inputs'!$E$54*((('01 Inputs'!$E$76*'01 Inputs'!$E$90)/(1+'01 Inputs'!$E$11))+('01 Inputs'!$E$15*'01 Inputs'!$E$28+'01 Inputs'!$E$15*'01 Inputs'!$E$31+'01 Inputs'!$E$32+'01 Inputs'!$E$33)+(IF(('01 Inputs'!$E$15*'01 Inputs'!$E$14+'01 Inputs'!$E$15*'01 Inputs'!$E$40+'01 Inputs'!$E$41)<=100,'01 Inputs'!$E$43,IF(('01 Inputs'!$E$15*'01 Inputs'!$E$14+'01 Inputs'!$E$15*'01 Inputs'!$E$40+'01 Inputs'!$E$41)<=250,'01 Inputs'!$E$44,IF(('01 Inputs'!$E$15*'01 Inputs'!$E$14+'01 Inputs'!$E$15*'01 Inputs'!$E$40+'01 Inputs'!$E$41)<=500,'01 Inputs'!$E$45,IF(('01 Inputs'!$E$15*'01 Inputs'!$E$14+'01 Inputs'!$E$15*'01 Inputs'!$E$40+'01 Inputs'!$E$41)<=750,'01 Inputs'!$E$46,'01 Inputs'!$E$47))))*'01 Inputs'!$E$48)))) | E64: =D64-C64
B65: Contribution % | C65: =C64/C61 | D65: =D64/D61 | E65: =D65-C65
B66: Contribution per serving | C66: =C64/'01 Inputs'!$E$15 | D66: =D64/'01 Inputs'!$E$15 | E66: =D66-C66
B67: READ THIS. Branded source forms are the only lever in this model that buys a reason to charge more than a £0.06/serving Tesco effervescent, because the authorised CLAIMS are identical at both prices (A-045). They are also the only COGS line that can move the contribution margin by double digits. If the 'clinical' positioning is real, this cost is the price of it and it must be in the plan. A-043 RISK: GB permitted source forms are frozen by Schedule 2 at end-2020 with one amendment since; check every branded form against Schedule 2 BEFORE building a story on it.
B69: LAUNCH CAPITAL AND THE SHARED-BASE ARCHITECTURE (three products, one base)
B70: Formulation cost — shared base + 3 layers | C70: ='01 Inputs'!$G$85
B71: Formulation cost — if the 3 SKUs were formulated independently | C71: ='01 Inputs'!$G$86
B72: NPD saving from the shared base | C72: =C71-C70
B73: First-run tablets — shared base MOQ + 3 layer runs | C73: ='01 Inputs'!$G$87+'01 Inputs'!$G$88*'01 Inputs'!$G$84
B74: First-run tablets — if each SKU carried a full MOQ | C74: ='01 Inputs'!$G$87*'01 Inputs'!$G$84
B75: First-run STOCK VALUE — shared base | C75: =C73*'01 Inputs'!$G$29
B76: First-run STOCK VALUE — independent SKUs | C76: =C74*'01 Inputs'!$G$29
B77: Working-capital saving from the shared base | C77: =C76-C75
B78: Subscriber-months of stock in the first run (shared base) | C78: =C73/'01 Inputs'!$G$15
B79: Case tooling and fixtures (one-off, if the case is in the kit) | C79: ='01 Inputs'!$G$35
B80: One-off compliance cost avoided by going caffeine-free | C80: ='01 Inputs'!$G$89
B81: TOTAL CASH TO FIRST SHIPPABLE BATCH (excl. brand, web, artwork and marketing) | C81: =C70+C75+C79
B83: THE QUESTION TO ASK THE FIRST MANUFACTURER. Will you run a shared base blend with three short differentiating sub-runs, and what is the MOQ on each? If the answer is no — if every SKU carries a full MOQ — then three products at launch is roughly three times the working capital and the right answer is one product, not three. This single question moves more cash than any pricing decision in this workbook.

Sheet 04 Subscription economics
A1: 04 SUBSCRIPTION ECONOMICS — retention, LTV on a contribution basis, CAC payback, LTV:CAC
A2: Base architecture A1. CAC is compared against CONTRIBUTION, never against revenue and never against gross margin. LTV is undiscounted; at these horizons discounting changes the ratio by less than the input uncertainty.
B4: A. USAGE AND CADENCE (A-014, repaired by the daily-ritual decision)
B5: Servings per monthly pack | C5: ='01 Inputs'!$G$15 | J5: Pack size follows daily usage, not the brief's 24.
B6: Servings consumed per month | C6: ='01 Inputs'!$G$16 | J6: 28-30 at base. A morning ritual is genuinely daily — this is what repairs A-014.
B7: MONTHS OF SUPPLY per monthly pack | C7: =C5/C6 | J7: 1.00 = perfectly matched cadence. Above 1.00 the subscriber accumulates stock, which is the classic mechanical cause of supplement cancellation ('I've got four boxes I haven't opened').
B8: Over-shipping per month | C8: =C7-1 | J8: At the brief's 24-pack against the OLD occasion set this was ~45%. At a 30-pack against daily use it is near zero at base, and only bites in the downside usage case.
B9: Months of supply per QUARTERLY pack | C9: ='01 Inputs'!$G$17/C6
B11: B. UNIT CONTRIBUTIONS CARRIED FORWARD FROM SHEET 03
B12: Starter kit contribution — WITH case | C12: ='03 Unit economics'!C30
B13: Starter kit contribution — NO case | C13: ='03 Unit economics'!D30
B14: Monthly refill contribution | C14: ='03 Unit economics'!E30
B15: Quarterly prepay contribution | C15: ='03 Unit economics'!G30
B16: Blended CAC | C16: ='01 Inputs'!$G$67 | J16: A-028. The brief contains no CAC line at all. With no retail discovery route this is the entire growth model.
B17: Total monthly churn | C17: ='01 Inputs'!$G$72
B18: Extra drop-off before first refill | C18: ='01 Inputs'!$G$70
B20: C. RETENTION CURVE BY CHURN SCENARIO (% of starters still subscribing at each refill)
B21: Refill month | C21: Monthly churn used | D21: Optimistic (Inputs Low) | E21: Base (Inputs Base) | F21: Pessimistic (Inputs High)
B22: churn p.m. | D22: ='01 Inputs'!$D$72 | E22: ='01 Inputs'!$E$72 | F22: ='01 Inputs'!$F$72
B23: first-refill drop | D23: ='01 Inputs'!$D$70 | E23: ='01 Inputs'!$E$70 | F23: ='01 Inputs'!$F$70 | J23: Retention = (1 - first-refill drop) x (1 - monthly churn)^(m-1). The first-refill drop is separate because supplement churn is front-loaded: most cancellation happens in months 1-3.
B24: 1 | D24: =(1-D$23)*(1-D$22)^(1-1) | E24: =(1-E$23)*(1-E$22)^(1-1) | F24: =(1-F$23)*(1-F$22)^(1-1)
B25: 2 | D25: =(1-D$23)*(1-D$22)^(2-1) | E25: =(1-E$23)*(1-E$22)^(2-1) | F25: =(1-F$23)*(1-F$22)^(2-1)
B26: 3 | D26: =(1-D$23)*(1-D$22)^(3-1) | E26: =(1-E$23)*(1-E$22)^(3-1) | F26: =(1-F$23)*(1-F$22)^(3-1)
B27: 4 | D27: =(1-D$23)*(1-D$22)^(4-1) | E27: =(1-E$23)*(1-E$22)^(4-1) | F27: =(1-F$23)*(1-F$22)^(4-1)
B28: 5 | D28: =(1-D$23)*(1-D$22)^(5-1) | E28: =(1-E$23)*(1-E$22)^(5-1) | F28: =(1-F$23)*(1-F$22)^(5-1)
B29: 6 | D29: =(1-D$23)*(1-D$22)^(6-1) | E29: =(1-E$23)*(1-E$22)^(6-1) | F29: =(1-F$23)*(1-F$22)^(6-1)
B30: 7 | D30: =(1-D$23)*(1-D$22)^(7-1) | E30: =(1-E$23)*(1-E$22)^(7-1) | F30: =(1-F$23)*(1-F$22)^(7-1)
B31: 8 | D31: =(1-D$23)*(1-D$22)^(8-1) | E31: =(1-E$23)*(1-E$22)^(8-1) | F31: =(1-F$23)*(1-F$22)^(8-1)
B32: 9 | D32: =(1-D$23)*(1-D$22)^(9-1) | E32: =(1-E$23)*(1-E$22)^(9-1) | F32: =(1-F$23)*(1-F$22)^(9-1)
B33: 10 | D33: =(1-D$23)*(1-D$22)^(10-1) | E33: =(1-E$23)*(1-E$22)^(10-1) | F33: =(1-F$23)*(1-F$22)^(10-1)
B34: 11 | D34: =(1-D$23)*(1-D$22)^(11-1) | E34: =(1-E$23)*(1-E$22)^(11-1) | F34: =(1-F$23)*(1-F$22)^(11-1)
B35: 12 | D35: =(1-D$23)*(1-D$22)^(12-1) | E35: =(1-E$23)*(1-E$22)^(12-1) | F35: =(1-F$23)*(1-F$22)^(12-1)
B36: 13 | D36: =(1-D$23)*(1-D$22)^(13-1) | E36: =(1-E$23)*(1-E$22)^(13-1) | F36: =(1-F$23)*(1-F$22)^(13-1)
B37: 14 | D37: =(1-D$23)*(1-D$22)^(14-1) | E37: =(1-E$23)*(1-E$22)^(14-1) | F37: =(1-F$23)*(1-F$22)^(14-1)
B38: 15 | D38: =(1-D$23)*(1-D$22)^(15-1) | E38: =(1-E$23)*(1-E$22)^(15-1) | F38: =(1-F$23)*(1-F$22)^(15-1)
B39: 16 | D39: =(1-D$23)*(1-D$22)^(16-1) | E39: =(1-E$23)*(1-E$22)^(16-1) | F39: =(1-F$23)*(1-F$22)^(16-1)
B40: 17 | D40: =(1-D$23)*(1-D$22)^(17-1) | E40: =(1-E$23)*(1-E$22)^(17-1) | F40: =(1-F$23)*(1-F$22)^(17-1)
B41: 18 | D41: =(1-D$23)*(1-D$22)^(18-1) | E41: =(1-E$23)*(1-E$22)^(18-1) | F41: =(1-F$23)*(1-F$22)^(18-1)
B42: 19 | D42: =(1-D$23)*(1-D$22)^(19-1) | E42: =(1-E$23)*(1-E$22)^(19-1) | F42: =(1-F$23)*(1-F$22)^(19-1)
B43: 20 | D43: =(1-D$23)*(1-D$22)^(20-1) | E43: =(1-E$23)*(1-E$22)^(20-1) | F43: =(1-F$23)*(1-F$22)^(20-1)
B44: 21 | D44: =(1-D$23)*(1-D$22)^(21-1) | E44: =(1-E$23)*(1-E$22)^(21-1) | F44: =(1-F$23)*(1-F$22)^(21-1)
B45: 22 | D45: =(1-D$23)*(1-D$22)^(22-1) | E45: =(1-E$23)*(1-E$22)^(22-1) | F45: =(1-F$23)*(1-F$22)^(22-1)
B46: 23 | D46: =(1-D$23)*(1-D$22)^(23-1) | E46: =(1-E$23)*(1-E$22)^(23-1) | F46: =(1-F$23)*(1-F$22)^(23-1)
B47: 24 | D47: =(1-D$23)*(1-D$22)^(24-1) | E47: =(1-E$23)*(1-E$22)^(24-1) | F47: =(1-F$23)*(1-F$22)^(24-1)
B49: D. LTV, PAYBACK AND LTV:CAC (contribution basis, starter kit WITH case)
B50: Metric | D50: Optimistic churn | E50: Base churn | F50: Pessimistic churn
B51: Months 1-12 retained subscriber-months | D51: =SUM(D24:D35) | E51: =SUM(E24:E35) | F51: =SUM(F24:F35)
B52: Months 1-24 retained subscriber-months | D52: =SUM(D24:D47) | E52: =SUM(E24:E47) | F52: =SUM(F24:F47)
B53: Starter contribution (month 0) | D53: =$C12 | E53: =$C12 | F53: =$C12
B54: Refill contribution x retained months, 12m | D54: =D51*$C14 | E54: =E51*$C14 | F54: =F51*$C14
B55: LTV 12 months (contribution) | D55: =D53+D54 | E55: =E53+E54 | F55: =F53+F54
B56: LTV 24 months (contribution) | D56: =$C12+D52*$C14 | E56: =$C12+E52*$C14 | F56: =$C12+F52*$C14
B57: CAC | D57: =$C16 | E57: =$C16 | F57: =$C16
B58: LTV:CAC — 12 months | D58: =D55/D57 | E58: =E55/E57 | F58: =F55/F57
B59: LTV:CAC — 24 months | D59: =D56/D57 | E59: =E56/E57 | F59: =F56/F57
B60: CAC payback (months of refills after the starter) | D60: =IF($C12>=$C16,0,IF($C12+$C14*(1-D$23)/D$22<=$C16,"never",LN(1-($C16-$C12)*D$22/($C14*(1-D$23)))/LN(1-D$22))) | E60: =IF($C12>=$C16,0,IF($C12+$C14*(1-E$23)/E$22<=$C16,"never",LN(1-($C16-$C12)*E$22/($C14*(1-E$23)))/LN(1-E$22))) | F60: =IF($C12>=$C16,0,IF($C12+$C14*(1-F$23)/F$22<=$C16,"never",LN(1-($C16-$C12)*F$22/($C14*(1-F$23)))/LN(1-F$22)))
B61: Cumulative contribution at month 12 minus CAC | D61: =D55-D57 | E61: =E55-E57 | F61: =F55-F57
B62: MAXIMUM LIFETIME CONTRIBUTION (infinite horizon — the ceiling) | D62: =$C12+$C14*(1-D$23)/D$22 | E62: =$C12+$C14*(1-E$23)/E$22 | F62: =$C12+$C14*(1-F$23)/F$22
B63: MAX LTV:CAC (infinite horizon) | D63: =D62/D57 | E63: =E62/E57 | F63: =F62/F57
B64: Expected subscriber lifetime (months) | D64: =(1-D$23)/D$22 | E64: =(1-E$23)/E$22 | F64: =(1-F$23)/F$22
B66: E. THE SAME THING WITHOUT THE CASE, AND ON QUARTERLY CADENCE (base churn)
B67: LTV 12m — starter WITHOUT case | C67: =$C13+E51*$C14
B68: LTV:CAC 12m — starter WITHOUT case | C68: =C67/$C16
B69: CAC payback — starter WITHOUT case (months) | C69: =IF($C13>=$C16,0,IF($C13+$C14*(1-E$23)/E$22<=$C16,"never",LN(1-($C16-$C13)*E$22/($C14*(1-E$23)))/LN(1-E$22)))
B70: Case cost to include in the starter kit (COGS incl. tooling) | C70: ='01 Inputs'!$G$37
B71: Extra price the case must earn to be contribution-neutral (inc VAT) | C71: ='01 Inputs'!$G$37*(1+'01 Inputs'!$G$11)/'01 Inputs'!$G$90
B72: LTV 12m — QUARTERLY cadence (4 shipments/yr incl. the starter quarter) | C72: =$C15+(C15*3)
B73: Quarterly: contribution per serving | C73: ='03 Unit economics'!G32
B74: Quarterly: annual contribution per retained customer at base churn | C74: =$C15*(1+(1-E$23)*((1-(1-E$22)^3)/E$22/3)*3)
B76: READ THIS. The quarterly line is approximate — it assumes churn is only expressed at renewal points, which is the POINT of quarterly cadence: four decision moments a year instead of twelve. If quarterly cadence cuts the number of cancellation opportunities by two thirds, it is worth more than any price change available to us.
B77: F. CADENCE — THE CHEAPEST LEVER IN THE MODEL (price per serving held constant at architecture A1's £0.666 inc VAT)
B78: Shipment cadence | C78: Tablets per shipment | D78: Price inc VAT | E78: Shipped weight (g) | F78: Postage | G78: Contribution per shipment | H78: Contribution per CALENDAR MONTH | I78: Max lifetime contribution | J78: Max LTV:CAC
B79: 1 month | C79: =1*'01 Inputs'!$G$15 | D79: =C79*'01 Inputs'!$G$76/'01 Inputs'!$G$15 | E79: =C79*'01 Inputs'!$G$14+C79*'01 Inputs'!$G$40+'01 Inputs'!$G$41 | F79: =IF(E79<=100,'01 Inputs'!$G$43,IF(E79<=250,'01 Inputs'!$G$44,IF(E79<=500,'01 Inputs'!$G$45,IF(E79<=750,'01 Inputs'!$G$46,'01 Inputs'!$G$47))))*'01 Inputs'!$G$48 | G79: =((D79*'01 Inputs'!$G$90)/(1+'01 Inputs'!$G$11))-(C79*'01 Inputs'!$G$29+C79*'01 Inputs'!$G$31+'01 Inputs'!$G$32+'01 Inputs'!$G$33)-('01 Inputs'!$G$39+F79+((D79*'01 Inputs'!$G$90)*'01 Inputs'!$G$50+'01 Inputs'!$G$51)+'01 Inputs'!$G$53+('01 Inputs'!$G$52*((C79*'01 Inputs'!$G$29+C79*'01 Inputs'!$G$31+'01 Inputs'!$G$32+'01 Inputs'!$G$33)+'01 Inputs'!$G$39+F79))+('01 Inputs'!$G$54*(((D79*'01 Inputs'!$G$90)/(1+'01 Inputs'!$G$11))+(C79*'01 Inputs'!$G$29+C79*'01 Inputs'!$G$31+'01 Inputs'!$G$32+'01 Inputs'!$G$33)+F79))) | H79: =G79/1 | I79: =$C12+H79*(1-'01 Inputs'!$G$70)/'01 Inputs'!$G$72 | J79: =I79/$C16
B80: 2 months | C80: =2*'01 Inputs'!$G$15 | D80: =C80*'01 Inputs'!$G$76/'01 Inputs'!$G$15 | E80: =C80*'01 Inputs'!$G$14+C80*'01 Inputs'!$G$40+'01 Inputs'!$G$41 | F80: =IF(E80<=100,'01 Inputs'!$G$43,IF(E80<=250,'01 Inputs'!$G$44,IF(E80<=500,'01 Inputs'!$G$45,IF(E80<=750,'01 Inputs'!$G$46,'01 Inputs'!$G$47))))*'01 Inputs'!$G$48 | G80: =((D80*'01 Inputs'!$G$90)/(1+'01 Inputs'!$G$11))-(C80*'01 Inputs'!$G$29+C80*'01 Inputs'!$G$31+'01 Inputs'!$G$32+'01 Inputs'!$G$33)-('01 Inputs'!$G$39+F80+((D80*'01 Inputs'!$G$90)*'01 Inputs'!$G$50+'01 Inputs'!$G$51)+'01 Inputs'!$G$53+('01 Inputs'!$G$52*((C80*'01 Inputs'!$G$29+C80*'01 Inputs'!$G$31+'01 Inputs'!$G$32+'01 Inputs'!$G$33)+'01 Inputs'!$G$39+F80))+('01 Inputs'!$G$54*(((D80*'01 Inputs'!$G$90)/(1+'01 Inputs'!$G$11))+(C80*'01 Inputs'!$G$29+C80*'01 Inputs'!$G$31+'01 Inputs'!$G$32+'01 Inputs'!$G$33)+F80))) | H80: =G80/2 | I80: =$C12+H80*(1-'01 Inputs'!$G$70)/'01 Inputs'!$G$72 | J80: =I80/$C16
B81: 3 months | C81: =3*'01 Inputs'!$G$15 | D81: =C81*'01 Inputs'!$G$76/'01 Inputs'!$G$15 | E81: =C81*'01 Inputs'!$G$14+C81*'01 Inputs'!$G$40+'01 Inputs'!$G$41 | F81: =IF(E81<=100,'01 Inputs'!$G$43,IF(E81<=250,'01 Inputs'!$G$44,IF(E81<=500,'01 Inputs'!$G$45,IF(E81<=750,'01 Inputs'!$G$46,'01 Inputs'!$G$47))))*'01 Inputs'!$G$48 | G81: =((D81*'01 Inputs'!$G$90)/(1+'01 Inputs'!$G$11))-(C81*'01 Inputs'!$G$29+C81*'01 Inputs'!$G$31+'01 Inputs'!$G$32+'01 Inputs'!$G$33)-('01 Inputs'!$G$39+F81+((D81*'01 Inputs'!$G$90)*'01 Inputs'!$G$50+'01 Inputs'!$G$51)+'01 Inputs'!$G$53+('01 Inputs'!$G$52*((C81*'01 Inputs'!$G$29+C81*'01 Inputs'!$G$31+'01 Inputs'!$G$32+'01 Inputs'!$G$33)+'01 Inputs'!$G$39+F81))+('01 Inputs'!$G$54*(((D81*'01 Inputs'!$G$90)/(1+'01 Inputs'!$G$11))+(C81*'01 Inputs'!$G$29+C81*'01 Inputs'!$G$31+'01 Inputs'!$G$32+'01 Inputs'!$G$33)+F81))) | H81: =G81/3 | I81: =$C12+H81*(1-'01 Inputs'!$G$70)/'01 Inputs'!$G$72 | J81: =I81/$C16
B82: 6 months | C82: =6*'01 Inputs'!$G$15 | D82: =C82*'01 Inputs'!$G$76/'01 Inputs'!$G$15 | E82: =C82*'01 Inputs'!$G$14+C82*'01 Inputs'!$G$40+'01 Inputs'!$G$41 | F82: =IF(E82<=100,'01 Inputs'!$G$43,IF(E82<=250,'01 Inputs'!$G$44,IF(E82<=500,'01 Inputs'!$G$45,IF(E82<=750,'01 Inputs'!$G$46,'01 Inputs'!$G$47))))*'01 Inputs'!$G$48 | G82: =((D82*'01 Inputs'!$G$90)/(1+'01 Inputs'!$G$11))-(C82*'01 Inputs'!$G$29+C82*'01 Inputs'!$G$31+'01 Inputs'!$G$32+'01 Inputs'!$G$33)-('01 Inputs'!$G$39+F82+((D82*'01 Inputs'!$G$90)*'01 Inputs'!$G$50+'01 Inputs'!$G$51)+'01 Inputs'!$G$53+('01 Inputs'!$G$52*((C82*'01 Inputs'!$G$29+C82*'01 Inputs'!$G$31+'01 Inputs'!$G$32+'01 Inputs'!$G$33)+'01 Inputs'!$G$39+F82))+('01 Inputs'!$G$54*(((D82*'01 Inputs'!$G$90)/(1+'01 Inputs'!$G$11))+(C82*'01 Inputs'!$G$29+C82*'01 Inputs'!$G$31+'01 Inputs'!$G$32+'01 Inputs'!$G$33)+F82))) | H82: =G82/6 | I82: =$C12+H82*(1-'01 Inputs'!$G$70)/'01 Inputs'!$G$72 | J82: =I82/$C16
B83: WHY THIS TABLE MATTERS MORE THAN THE PRICE TABLE. Fulfilment, postage and the fixed part of the payment fee are charged PER ORDER, not per serving. At a monthly cadence they consume roughly a fifth of net revenue; at a quarterly cadence, a third of that. Lengthening the cadence raises the contribution per calendar month at an UNCHANGED price per serving — it is the only lever in this workbook that improves the economics without asking the customer to pay more or the manufacturer to charge less. Watch the six-month row: it breaches the 750 g Royal Mail Large Letter ceiling, becomes a parcel, and the gain stops. That is where the format's postal advantage runs out.

Sheet 05 Channel consistency
A1: 05 CHANNEL AND PACK CONSISTENCY — price per serving everywhere, with cannibalisation flags
A2: Under the D2C-only decision the retail half of A-003 is moot for Phase 1. The internal ladder still has to be coherent, and the retail row is kept so the user can see what was abandoned.
B4: Channel / pack | C4: List price inc VAT | D4: Servings | E4: £/serving inc VAT | F4: £/serving NET | G4: Contribution / serving | H4: Cannibalisation check
B5: D2C starter kit, month 1 (WITH case) | C5: ='01 Inputs'!$G$74 | D5: ='01 Inputs'!$G$15 | E5: =C5/D5 | F5: =E5/(1+'01 Inputs'!$G$11) | G5: ='03 Unit economics'!C32 | H5: Entry price carries the hardware. Highest £/serving in month 1 — acceptable only if the case is genuinely wanted (A-025, UNPROVEN).
B6: D2C starter kit, month 1 (NO case) | C6: ='01 Inputs'!$G$75 | D6: ='01 Inputs'!$G$15 | E6: =C6/D6 | F6: =E6/(1+'01 Inputs'!$G$11) | G6: ='03 Unit economics'!D32 | H6: Same tablets, no hardware. If this converts materially better, the case is a tax on acquisition, not a feature.
B7: D2C subscription refill (monthly) | C7: ='01 Inputs'!$G$76 | D7: ='01 Inputs'!$G$15 | E7: =C7/D7 | F7: =E7/(1+'01 Inputs'!$G$11) | G7: ='03 Unit economics'!E32 | H7: The reference price. Everything else must be coherent against it.
B8: D2C one-off refill (non-subscriber) | C8: ='01 Inputs'!$G$77 | D8: ='01 Inputs'!$G$15 | E8: =C8/D8 | F8: =E8/(1+'01 Inputs'!$G$11) | G8: ='03 Unit economics'!F32 | H8: MUST be above the subscription per serving. Flag below.
B9: D2C quarterly prepay | C9: ='01 Inputs'!$G$78 | D9: ='01 Inputs'!$G$17 | E9: =C9/D9 | F9: =E9/(1+'01 Inputs'!$G$11) | G9: ='03 Unit economics'!G32 | H9: Must be below monthly (rewards commitment) but not so far below that it simply discounts the monthly base. Flag below.
B10: Retail tube (15) — OUT OF SCOPE, reference | C10: ='01 Inputs'!$G$79 | D10: ='01 Inputs'!$G$80 | E10: =C10/D10 | F10: =E10/(1+'01 Inputs'!$G$11) | G10: ='03 Unit economics'!H32 | H10: The abandoned architecture. A-003: retail undercut the subscription by 44.1% per serving, handing every subscriber a cancellation argument.
B12: CANNIBALISATION FLAGS (live)
B13: One-off refill priced ABOVE subscription per serving? | C13: =IF(E8>E7,"OK — premium of "&TEXT((E8-E7)/E7,"0.0%")&" gives a real reason to subscribe","FAIL — no reason to subscribe")
B14: Quarterly priced BELOW monthly per serving? | C14: =IF(E9<E7,"OK — saving of "&TEXT((E7-E9)/E7,"0.0%"),"FAIL — quarterly must reward commitment")
B15: Quarterly discount within a sane 5-20% band? | C15: =IF(AND((E7-E9)/E7>=0.05,(E7-E9)/E7<=0.2),"OK","REVIEW — a discount outside 5-20% either fails to motivate or simply reprices the base")
B16: Starter kit (with case) month-1 £/serving vs ongoing | C16: =IF(E5>E7,"Entry is "&TEXT(E5/E7-1,"0.0%")&" dearer per serving than ongoing — the case is an acquisition tax","Entry is discounted — check it does not train discount-seeking")
B17: Starter kit (no case) vs ongoing | C17: =IF(E6>E7,"Entry dearer than ongoing — unusual for D2C","Entry at or below ongoing — conventional; watch the payback on sheet 04")
B18: RETAIL (out of scope) vs subscription per serving | C18: =IF(E10<E7,"THE A-003 INVERSION: retail undercuts subscription by "&TEXT((E7-E10)/E7,"0.0%")&". Moot under D2C-only, but it is why retail was dropped.","No inversion")
B19: Own-label effervescent vitamin C anchor (£0.060/serving) | C19: =TEXT(E7/0.06,"0.0")&"x the cheapest effervescent vitamin in the dataset. This anchor is one Google search away and does not disappear under D2C."

Sheet 06 Scenarios & sensitivity
A1: 06 SCENARIOS AND SENSITIVITY
A2: Part A builds Downside / Base / Upside independently of the scenario switch, by pointing each driver at the right Inputs column. Part B is a one-variable-at-a-time sensitivity on the base case.
B4: PART A — SCENARIO DRIVERS (each cell points at the Low, Base or High column of sheet 01)
B5: Driver | C5: DOWNSIDE | D5: BASE | E5: UPSIDE | I5: Which Inputs column each case uses
B6: VAT rate on the product (standard-rated) | C6: ='01 Inputs'!$D$11 | D6: ='01 Inputs'!$E$11 | E6: ='01 Inputs'!$D$11 | I6: Downside uses column D, Upside uses column D
B7: Tablet mass | C7: ='01 Inputs'!$D$14 | D7: ='01 Inputs'!$E$14 | E7: ='01 Inputs'!$D$14 | I7: Downside uses column D, Upside uses column D
B8: Servings per monthly pack | C8: ='01 Inputs'!$D$15 | D8: ='01 Inputs'!$E$15 | E8: ='01 Inputs'!$D$15 | I8: Downside uses column D, Upside uses column D
B9: Servings actually consumed per month | C9: ='01 Inputs'!$D$16 | D9: ='01 Inputs'!$E$16 | E9: ='01 Inputs'!$F$16 | I9: Downside uses column D, Upside uses column F
B10: Servings per quarterly prepay pack | C10: ='01 Inputs'!$D$17 | D10: ='01 Inputs'!$E$17 | E10: ='01 Inputs'!$D$17 | I10: Downside uses column D, Upside uses column D
B11: TOTAL TABLET COGS (follows switch C6) | C11: ='01 Inputs'!$F$29 | D11: ='01 Inputs'!$E$29 | E11: ='01 Inputs'!$D$29 | I11: Downside uses column F, Upside uses column D
B12: Blister per tablet (alu/alu sealed strip — required by A-005) | C12: ='01 Inputs'!$F$31 | D12: ='01 Inputs'!$E$31 | E12: ='01 Inputs'!$D$31 | I12: Downside uses column F, Upside uses column D
B13: Refill carton and letterbox mailer, per order | C13: ='01 Inputs'!$F$32 | D13: ='01 Inputs'!$E$32 | E13: ='01 Inputs'!$D$32 | I13: Downside uses column F, Upside uses column D
B14: Insert, leaflet and label, per order | C14: ='01 Inputs'!$F$33 | D14: ='01 Inputs'!$E$33 | E14: ='01 Inputs'!$D$33 | I14: Downside uses column F, Upside uses column D
B15: CASE COST INCLUDING TOOLING AMORTISATION | C15: ='01 Inputs'!$F$37 | D15: ='01 Inputs'!$E$37 | E15: ='01 Inputs'!$D$37 | I15: Downside uses column F, Upside uses column D
B16: Fulfilment: 3PL pick, pack and handling, per order | C16: ='01 Inputs'!$F$39 | D16: ='01 Inputs'!$E$39 | E16: ='01 Inputs'!$D$39 | I16: Downside uses column F, Upside uses column D
B17: Blister carrier mass per tablet | C17: ='01 Inputs'!$F$40 | D17: ='01 Inputs'!$E$40 | E17: ='01 Inputs'!$D$40 | I17: Downside uses column F, Upside uses column D
B18: Mailer, carton and insert tare mass | C18: ='01 Inputs'!$F$41 | D18: ='01 Inputs'!$E$41 | E18: ='01 Inputs'!$D$41 | I18: Downside uses column F, Upside uses column D
B19: Aluminium case mass | C19: ='01 Inputs'!$F$42 | D19: ='01 Inputs'!$E$42 | E19: ='01 Inputs'!$D$42 | I19: Downside uses column F, Upside uses column D
B20: Royal Mail 2nd Class Large Letter, 0-100 g | C20: ='01 Inputs'!$E$43 | D20: ='01 Inputs'!$E$43 | E20: ='01 Inputs'!$E$43 | I20: Downside uses column E, Upside uses column E
B21: Royal Mail 2nd Class Large Letter, 101-250 g << THE BASE CASE BAND | C21: ='01 Inputs'!$E$44 | D21: ='01 Inputs'!$E$44 | E21: ='01 Inputs'!$E$44 | I21: Downside uses column E, Upside uses column E
B22: Royal Mail 2nd Class Large Letter, 251-500 g | C22: ='01 Inputs'!$E$45 | D22: ='01 Inputs'!$E$45 | E22: ='01 Inputs'!$E$45 | I22: Downside uses column E, Upside uses column E
B23: Royal Mail 2nd Class Large Letter, 501-750 g | C23: ='01 Inputs'!$E$46 | D23: ='01 Inputs'!$E$46 | E23: ='01 Inputs'!$E$46 | I23: Downside uses column E, Upside uses column E
B24: Royal Mail 2nd Class Small Parcel — what a TUBE competitor must pay | C24: ='01 Inputs'!$E$47 | D24: ='01 Inputs'!$E$47 | E24: ='01 Inputs'!$E$47 | I24: Downside uses column E, Upside uses column E
B25: Business / Mailmark discount multiplier on the stamp tariff | C25: ='01 Inputs'!$F$48 | D25: ='01 Inputs'!$E$48 | E25: ='01 Inputs'!$D$48 | I25: Downside uses column F, Upside uses column D
B26: Payment processing rate | C26: ='01 Inputs'!$F$50 | D26: ='01 Inputs'!$E$50 | E26: ='01 Inputs'!$D$50 | I26: Downside uses column F, Upside uses column D
B27: Payment fixed fee per transaction | C27: ='01 Inputs'!$F$51 | D27: ='01 Inputs'!$E$51 | E27: ='01 Inputs'!$D$51 | I27: Downside uses column F, Upside uses column D
B28: Age verification at the D2C checkout — AVOIDED by going caffeine-free | C28: ='01 Inputs'!$E$53 | D28: ='01 Inputs'!$E$53 | E28: ='01 Inputs'!$E$53 | I28: Downside uses column E, Upside uses column E
B29: Breakage / damage in transit — orders replaced | C29: ='01 Inputs'!$F$52 | D29: ='01 Inputs'!$E$52 | E29: ='01 Inputs'!$D$52 | I29: Downside uses column F, Upside uses column D
B30: Returns, refunds and goodwill credits | C30: ='01 Inputs'!$F$54 | D30: ='01 Inputs'!$E$54 | E30: ='01 Inputs'!$D$54 | I30: Downside uses column F, Upside uses column D
B31: UK pharmacy / grocery retailer margin, % of sell price | C31: ='01 Inputs'!$E$56 | D31: ='01 Inputs'!$E$56 | E31: ='01 Inputs'!$E$56 | I31: Downside uses column E, Upside uses column E
B32: Distributor / wholesaler margin, % of trade price | C32: ='01 Inputs'!$E$57 | D32: ='01 Inputs'!$E$57 | E32: ='01 Inputs'!$E$57 | I32: Downside uses column E, Upside uses column E
B33: BLENDED CAC | C33: ='01 Inputs'!$F$67 | D33: ='01 Inputs'!$E$67 | E33: ='01 Inputs'!$D$67 | I33: Downside uses column F, Upside uses column D
B34: TOTAL MONTHLY CHURN | C34: ='01 Inputs'!$F$72 | D34: ='01 Inputs'!$E$72 | E34: ='01 Inputs'!$D$72 | I34: Downside uses column F, Upside uses column D
B35: Extra drop-off before the FIRST refill | C35: ='01 Inputs'!$F$70 | D35: ='01 Inputs'!$E$70 | E35: ='01 Inputs'!$D$70 | I35: Downside uses column F, Upside uses column D
B36: Starter kit including case — list RRP inc VAT | C36: ='01 Inputs'!$E$74 | D36: ='01 Inputs'!$E$74 | E36: ='01 Inputs'!$E$74 | I36: Downside uses column E, Upside uses column E
B37: Starter kit WITHOUT case — list RRP inc VAT | C37: ='01 Inputs'!$E$75 | D37: ='01 Inputs'!$E$75 | E37: ='01 Inputs'!$E$75 | I37: Downside uses column E, Upside uses column E
B38: Monthly subscription refill (30 tablets) — list RRP inc VAT | C38: ='01 Inputs'!$E$76 | D38: ='01 Inputs'!$E$76 | E38: ='01 Inputs'!$E$76 | I38: Downside uses column E, Upside uses column E
B39: One-off refill (30 tablets), non-subscriber — list RRP inc VAT | C39: ='01 Inputs'!$E$77 | D39: ='01 Inputs'!$E$77 | E39: ='01 Inputs'!$E$77 | I39: Downside uses column E, Upside uses column E
B40: Quarterly prepay (90 tablets) — list RRP inc VAT | C40: ='01 Inputs'!$E$78 | D40: ='01 Inputs'!$E$78 | E40: ='01 Inputs'!$E$78 | I40: Downside uses column E, Upside uses column E
B41: Retail tube (15 tablets) — RRP inc VAT. OUT OF SCOPE, reference only | C41: ='01 Inputs'!$E$79 | D41: ='01 Inputs'!$E$79 | E41: ='01 Inputs'!$E$79 | I41: Downside uses column E, Upside uses column E
B42: Retail tube servings per pack | C42: ='01 Inputs'!$E$80 | D42: ='01 Inputs'!$E$80 | E42: ='01 Inputs'!$E$80 | I42: Downside uses column E, Upside uses column E
B43: Realised revenue factor (promotions, intro discounts, mix) | C43: ='01 Inputs'!$D$90 | D43: ='01 Inputs'!$E$90 | E43: ='01 Inputs'!$F$90 | I43: Downside uses column D, Upside uses column F
B44: Note: prices and Royal Mail tariffs do not move between scenarios — they are decisions and published tariffs, not uncertainties. What moves is COGS, CAC, churn, usage, realised revenue and the operating cost stack.
B46: SCENARIO ECONOMICS — subscription refill (30 tablets)
B47: Line | C47: DOWNSIDE | D47: BASE | E47: UPSIDE
B48: Pack size (servings) | C48: =$C$8 | D48: =$D$8 | E48: =$E$8
B49: List RRP inc VAT | C49: =$C$38 | D49: =$D$38 | E49: =$E$38
B50: Realised revenue factor | C50: =$C$43 | D50: =$D$43 | E50: =$E$43
B51: Realised price billed inc VAT | C51: =C49*C50 | D51: =D49*D50 | E51: =E49*E50
B52: less VAT at 20% | C52: =C51*$C$6/(1+$C$6) | D52: =D51*$D$6/(1+$D$6) | E52: =E51*$E$6/(1+$E$6)
B53: NET PRICE (ex VAT) | C53: =C51/(1+$C$6) | D53: =D51/(1+$D$6) | E53: =E51/(1+$E$6)
B54: less retailer margin | C54: =C53*0 | D54: =D53*0 | E54: =E53*0
B55: less distributor margin | C55: =(C53-C54)*0 | D55: =(D53-D54)*0 | E55: =(E53-E54)*0
B56: NET REVENUE REALISED BY V-DROP | C56: =C53-C54-C55 | D56: =D53-D54-D55 | E56: =E53-E54-E55
B57: COGS — tablets | C57: =C48*$C$11 | D57: =D48*$D$11 | E57: =E48*$E$11
B58: COGS — blisters | C58: =C48*$C$12 | D58: =D48*$D$12 | E58: =E48*$E$12
B59: COGS — carton and mailer | C59: =$C$13 | D59: =$D$13 | E59: =$E$13
B60: COGS — insert and label | C60: =$C$14 | D60: =$D$14 | E60: =$E$14
B61: COGS — aluminium case (incl. tooling amortisation) | C61: =0*$C$15 | D61: =0*$D$15 | E61: =0*$E$15
B62: TOTAL COGS | C62: =SUM(C57:C61) | D62: =SUM(D57:D61) | E62: =SUM(E57:E61)
B63: GROSS MARGIN £ | C63: =C56-C62 | D63: =D56-D62 | E63: =E56-E62
B64: GROSS MARGIN % of net revenue | C64: =IF(C56=0,"",C63/C56) | D64: =IF(D56=0,"",D63/D56) | E64: =IF(E56=0,"",E63/E56)
B65: Shipped weight (g) | C65: =C48*$C$7+C48*$C$17+$C$18+0*$C$19 | D65: =D48*$D$7+D48*$D$17+$D$18+0*$D$19 | E65: =E48*$E$7+E48*$E$17+$E$18+0*$E$19
B66: Fulfilment (3PL pick and pack) | C66: =$C$16 | D66: =$D$16 | E66: =$E$16
B67: Postage (Royal Mail band, after business discount) | C67: =IF(C65<=100,$C$20,IF(C65<=250,$C$21,IF(C65<=500,$C$22,IF(C65<=750,$C$23,$C$24))))*$C$25 | D67: =IF(D65<=100,$D$20,IF(D65<=250,$D$21,IF(D65<=500,$D$22,IF(D65<=750,$D$23,$D$24))))*$D$25 | E67: =IF(E65<=100,$E$20,IF(E65<=250,$E$21,IF(E65<=500,$E$22,IF(E65<=750,$E$23,$E$24))))*$E$25
B68: Payment fees (on the VAT-inclusive billed amount) | C68: =C51*$C$26+$C$27 | D68: =D51*$D$26+$D$27 | E68: =E51*$E$26+$E$27
B69: Age verification at checkout (nil — caffeine-free) | C69: =$C$28 | D69: =$D$28 | E69: =$E$28
B70: Breakage / damage replacement | C70: =$C$29*(C62+C66+C67) | D70: =$D$29*(D62+D66+D67) | E70: =$E$29*(E62+E66+E67)
B71: Returns and refunds | C71: =$C$30*(C56+C62+C67) | D71: =$D$30*(D56+D62+D67) | E71: =$E$30*(E56+E62+E67)
B72: TOTAL VARIABLE COSTS | C72: =SUM(C66:C71) | D72: =SUM(D66:D71) | E72: =SUM(E66:E71)
B73: CONTRIBUTION £ | C73: =C63-C72 | D73: =D63-D72 | E73: =E63-E72
B74: CONTRIBUTION MARGIN % of net revenue | C74: =IF(C56=0,"",C73/C56) | D74: =IF(D56=0,"",D73/D56) | E74: =IF(E56=0,"",E73/E56)
B75: CONTRIBUTION PER SERVING £ | C75: =C73/C48 | D75: =D73/D48 | E75: =E73/E48
B76: List price per serving, inc VAT | C76: =C49/C48 | D76: =D49/D48 | E76: =E49/E48
B77: List price per serving, NET | C77: =C76/(1+$C$6) | D77: =D76/(1+$D$6) | E77: =E76/(1+$E$6)
B78: Memo: parcel postage a TUBE competitor must pay | C78: =$C$24*$C$25 | D78: =$D$24*$D$25 | E78: =$E$24*$E$25
B79: Memo: LETTERBOX ADVANTAGE per order (A-006) | C79: =C78-C67 | D79: =D78-D67 | E79: =E78-E67
B81: SCENARIO ECONOMICS — starter kit WITH case
B82: Line | C82: DOWNSIDE | D82: BASE | E82: UPSIDE
B83: Pack size (servings) | C83: =$C$8 | D83: =$D$8 | E83: =$E$8
B84: List RRP inc VAT | C84: =$C$36 | D84: =$D$36 | E84: =$E$36
B85: Realised revenue factor | C85: =$C$43 | D85: =$D$43 | E85: =$E$43
B86: Realised price billed inc VAT | C86: =C84*C85 | D86: =D84*D85 | E86: =E84*E85
B87: less VAT at 20% | C87: =C86*$C$6/(1+$C$6) | D87: =D86*$D$6/(1+$D$6) | E87: =E86*$E$6/(1+$E$6)
B88: NET PRICE (ex VAT) | C88: =C86/(1+$C$6) | D88: =D86/(1+$D$6) | E88: =E86/(1+$E$6)
B89: less retailer margin | C89: =C88*0 | D89: =D88*0 | E89: =E88*0
B90: less distributor margin | C90: =(C88-C89)*0 | D90: =(D88-D89)*0 | E90: =(E88-E89)*0
B91: NET REVENUE REALISED BY V-DROP | C91: =C88-C89-C90 | D91: =D88-D89-D90 | E91: =E88-E89-E90
B92: COGS — tablets | C92: =C83*$C$11 | D92: =D83*$D$11 | E92: =E83*$E$11
B93: COGS — blisters | C93: =C83*$C$12 | D93: =D83*$D$12 | E93: =E83*$E$12
B94: COGS — carton and mailer | C94: =$C$13 | D94: =$D$13 | E94: =$E$13
B95: COGS — insert and label | C95: =$C$14 | D95: =$D$14 | E95: =$E$14
B96: COGS — aluminium case (incl. tooling amortisation) | C96: =1*$C$15 | D96: =1*$D$15 | E96: =1*$E$15
B97: TOTAL COGS | C97: =SUM(C92:C96) | D97: =SUM(D92:D96) | E97: =SUM(E92:E96)
B98: GROSS MARGIN £ | C98: =C91-C97 | D98: =D91-D97 | E98: =E91-E97
B99: GROSS MARGIN % of net revenue | C99: =IF(C91=0,"",C98/C91) | D99: =IF(D91=0,"",D98/D91) | E99: =IF(E91=0,"",E98/E91)
B100: Shipped weight (g) | C100: =C83*$C$7+C83*$C$17+$C$18+1*$C$19 | D100: =D83*$D$7+D83*$D$17+$D$18+1*$D$19 | E100: =E83*$E$7+E83*$E$17+$E$18+1*$E$19
B101: Fulfilment (3PL pick and pack) | C101: =$C$16 | D101: =$D$16 | E101: =$E$16
B102: Postage (Royal Mail band, after business discount) | C102: =IF(C100<=100,$C$20,IF(C100<=250,$C$21,IF(C100<=500,$C$22,IF(C100<=750,$C$23,$C$24))))*$C$25 | D102: =IF(D100<=100,$D$20,IF(D100<=250,$D$21,IF(D100<=500,$D$22,IF(D100<=750,$D$23,$D$24))))*$D$25 | E102: =IF(E100<=100,$E$20,IF(E100<=250,$E$21,IF(E100<=500,$E$22,IF(E100<=750,$E$23,$E$24))))*$E$25
B103: Payment fees (on the VAT-inclusive billed amount) | C103: =C86*$C$26+$C$27 | D103: =D86*$D$26+$D$27 | E103: =E86*$E$26+$E$27
...

Sheet 07 Price architectures
A1: 07 PRICE ARCHITECTURE OPTIONS — four coherent architectures, priced end to end
A2: All D2C. All use base-case Inputs. Each is internally coherent: pack size, entry price, ongoing price and cadence hang together.
B4: Line | C4: A1 — THE BRIEF, CORRECTED Case-led starter, monthly refill | D4: A2 — SUBSCRIPTION-FIRST, NO HARDWARE AT ENTRY Intro-priced first month, case an optional accessory | E4: A3 — PREMIUM RITUAL, PREPAID QUARTERLY Case-led starter, then a quarterly shipment | F4: A4 — VALUE-LED VOLUME Low entry, low ongoing, no hardware | G4: A5 — RECOMMENDED HYBRID No hardware at entry, quarterly cadence, branded actives | H4: Comment
B5: Starter: list price inc VAT | C5: 29.99 | D5: 14.99 | E5: 34.99 | F5: 12.99 | G5: 19.99
B6: Starter: tablets | C6: 30 | D6: 30 | E6: 30 | F6: 30 | G6: 30
B7: Starter: includes the aluminium case? (1/0) | C7: 1 | D7: 0 | E7: 1 | F7: 0 | G7: 0 | H7: A-025 is unproven. A2, A4 and A5 sell the case separately as an accessory; A1 and A3 bundle it.
B8: Actives grade (1 = commodity USP forms, 2 = branded / patented forms) | C8: 1 | D8: 1 | E8: 1 | F8: 1 | G8: 2 | H8: A5 is the only architecture priced to carry branded source forms. That is the point of it: vitamin-category-map.md §9 and A-049 say a survivable premium needs something own-label cannot have, and the authorised CLAIMS are not it (A-045). Subject to the A-043 permitted-source-form risk.
B9: Ongoing: list price inc VAT | C9: 19.99 | D9: 22.99 | E9: 54.99 | F9: 15.99 | G9: 74.99
B10: Ongoing: tablets per shipment | C10: 30 | D10: 30 | E10: 90 | F10: 30 | G10: 90
B11: Ongoing: cadence (months per shipment) | C11: 1 | D11: 1 | E11: 3 | F11: 1 | G11: 3
B12: One-off (non-subscriber) price inc VAT | C12: 24.99 | D12: 27.99 | E12: 64.99 | F12: 18.99 | G12: 84.99 | H12: Always above the subscription per serving — the reason to subscribe.
B14: PRICE POSITION
B15: Ongoing £ per serving, inc VAT | C15: =C9/C10 | D15: =D9/D10 | E15: =E9/E10 | F15: =F9/F10 | G15: =G9/G10
B16: Ongoing £ per serving, NET of VAT | C16: =C15/(1+'01 Inputs'!$G$11) | D16: =D15/(1+'01 Inputs'!$G$11) | E16: =E15/(1+'01 Inputs'!$G$11) | F16: =F15/(1+'01 Inputs'!$G$11) | G16: =G15/(1+'01 Inputs'!$G$11)
B17: Effective monthly cost to the customer | C17: =C9/C11 | D17: =D9/D11 | E17: =E9/E11 | F17: =F9/F11 | G17: =G9/G11 | H17: A-027: half of UK consumers spend UNDER £40/month on subscriptions IN TOTAL. Anything at or above £20/month is 50%+ of the median subscriber's entire budget.
B18: As a share of the £40/month median total subscription budget | C18: =C17/40 | D18: =D17/40 | E18: =E17/40 | F18: =F17/40 | G18: =G17/40 | H18: Source: aquacard 2025 subscription spending study, cited in A-027.
B19: Multiple of the cheapest effervescent vitamin (£0.060/serving) | C19: =C15/0.06 | D19: =D15/0.06 | E19: =E15/0.06 | F19: =F15/0.06 | G19: =G15/0.06 | H19: THE EFFERVESCENT LADDER. Tesco own-label effervescent vitamin C, £1.19 for 20.
B20: vs Berocca Mind £0.666/serving | C20: =C15/0.666-1 | D20: =D15/0.666-1 | E20: =E15/0.666-1 | F20: =F15/0.666-1 | G20: =G15/0.666-1
B21: vs Waterdrop £0.749/serving (taste-and-design precedent) | C21: =C15/0.749-1 | D21: =D15/0.749-1 | E21: =E15/0.749-1 | F21: =F15/0.749-1 | G21: =G15/0.749-1 | H21: Waterdrop sustains £0.749 on ~1.6 mg of declared vitamins, sold purely on taste and design (A-033, A-023). It is the single most relevant precedent for a taste-led V-Drop.
B22: vs Wild Nutrition 45+ £1.013/serving (the user's named reference) | C22: =C15/1.013-1 | D22: =D15/1.013-1 | E22: =E15/1.013-1 | F22: =F15/1.013-1 | G22: =G15/1.013-1
B23: vs AG1 subscription £2.633/serving | C23: =C15/2.633-1 | D23: =D15/2.633-1 | E23: =E15/2.633-1 | F23: =F15/2.633-1 | G23: =G15/2.633-1
B25: ECONOMICS (base-case inputs)
B26: Starter: net revenue (ex VAT) | C26: =(C5*'01 Inputs'!$G$90)/(1+'01 Inputs'!$G$11) | D26: =(D5*'01 Inputs'!$G$90)/(1+'01 Inputs'!$G$11) | E26: =(E5*'01 Inputs'!$G$90)/(1+'01 Inputs'!$G$11) | F26: =(F5*'01 Inputs'!$G$90)/(1+'01 Inputs'!$G$11) | G26: =(G5*'01 Inputs'!$G$90)/(1+'01 Inputs'!$G$11)
B27: Starter: GROSS MARGIN £ | C27: =((C5*'01 Inputs'!$G$90)/(1+'01 Inputs'!$G$11))-(C6*CHOOSE(C8,'01 Inputs'!$G$27,'01 Inputs'!$G$28)+C6*'01 Inputs'!$G$31+'01 Inputs'!$G$32+'01 Inputs'!$G$33+C7*'01 Inputs'!$G$37) | D27: =((D5*'01 Inputs'!$G$90)/(1+'01 Inputs'!$G$11))-(D6*CHOOSE(D8,'01 Inputs'!$G$27,'01 Inputs'!$G$28)+D6*'01 Inputs'!$G$31+'01 Inputs'!$G$32+'01 Inputs'!$G$33+D7*'01 Inputs'!$G$37) | E27: =((E5*'01 Inputs'!$G$90)/(1+'01 Inputs'!$G$11))-(E6*CHOOSE(E8,'01 Inputs'!$G$27,'01 Inputs'!$G$28)+E6*'01 Inputs'!$G$31+'01 Inputs'!$G$32+'01 Inputs'!$G$33+E7*'01 Inputs'!$G$37) | F27: =((F5*'01 Inputs'!$G$90)/(1+'01 Inputs'!$G$11))-(F6*CHOOSE(F8,'01 Inputs'!$G$27,'01 Inputs'!$G$28)+F6*'01 Inputs'!$G$31+'01 Inputs'!$G$32+'01 Inputs'!$G$33+F7*'01 Inputs'!$G$37) | G27: =((G5*'01 Inputs'!$G$90)/(1+'01 Inputs'!$G$11))-(G6*CHOOSE(G8,'01 Inputs'!$G$27,'01 Inputs'!$G$28)+G6*'01 Inputs'!$G$31+'01 Inputs'!$G$32+'01 Inputs'!$G$33+G7*'01 Inputs'!$G$37)
B28: Starter: gross margin % | C28: =C27/C26 | D28: =D27/D26 | E28: =E27/E26 | F28: =F27/F26 | G28: =G27/G26
B29: Starter: CONTRIBUTION £ | C29: =((C5*'01 Inputs'!$G$90)/(1+'01 Inputs'!$G$11))-(C6*CHOOSE(C8,'01 Inputs'!$G$27,'01 Inputs'!$G$28)+C6*'01 Inputs'!$G$31+'01 Inputs'!$G$32+'01 Inputs'!$G$33+C7*'01 Inputs'!$G$37)-('01 Inputs'!$G$39+(IF((C6*'01 Inputs'!$G$14+C6*'01 Inputs'!$G$40+'01 Inputs'!$G$41+C7*'01 Inputs'!$G$42)<=100,'01 Inputs'!$G$43,IF((C6*'01 Inputs'!$G$14+C6*'01 Inputs'!$G$40+'01 Inputs'!$G$41+C7*'01 Inputs'!$G$42)<=250,'01 Inputs'!$G$44,IF((C6*'01 Inputs'!$G$14+C6*'01 Inputs'!$G$40+'01 Inputs'!$G$41+C7*'01 Inputs'!$G$42)<=500,'01 Inputs'!$G$45,IF((C6*'01 Inputs'!$G$14+C6*'01 Inputs'!$G$40+'01 Inputs'!$G$41+C7*'01 Inputs'!$G$42)<=750,'01 Inputs'!$G$46,'01 Inputs'!$G$47))))*'01 Inputs'!$G$48)+((C5*'01 Inputs'!$G$90)*'01 Inputs'!$G$50+'01 Inputs'!$G$51)+'01 Inputs'!$G$53+('01 Inputs'!$G$52*((C6*CHOOSE(C8,'01 Inputs'!$G$27,'01 Inputs'!$G$28)+C6*'01 Inputs'!$G$31+'01 Inputs'!$G$32+'01 Inputs'!$G$33+C7*'01 Inputs'!$G$37)+'01 Inputs'!$G$39+(IF((C6*'01 Inputs'!$G$14+C6*'01 Inputs'!$G$40+'01 Inputs'!$G$41+C7*'01 Inputs'!$G$42)<=100,'01 Inputs'!$G$43,IF((C6*'01 Inputs'!$G$14+C6*'01 Inputs'!$G$40+'01 Inputs'!$G$41+C7*'01 Inputs'!$G$42)<=250,'01 Inputs'!$G$44,IF((C6*'01 Inputs'!$G$14+C6*'01 Inputs'!$G$40+'01 Inputs'!$G$41+C7*'01 Inputs'!$G$42)<=500,'01 Inputs'!$G$45,IF((C6*'01 Inputs'!$G$14+C6*'01 Inputs'!$G$40+'01 Inputs'!$G$41+C7*'01 Inputs'!$G$42)<=750,'01 Inputs'!$G$46,'01 Inputs'!$G$47))))*'01 Inputs'!$G$48)))+('01 Inputs'!$G$54*(((C5*'01 Inputs'!$G$90)/(1+'01 Inputs'!$G$11))+(C6*CHOOSE(C8,'01 Inputs'!$G$27,'01 Inputs'!$G$28)+C6*'01 Inputs'!$G$31+'01 Inputs'!$G$32+'01 Inputs'!$G$33+C7*'01 Inputs'!$G$37)+(IF((C6*'01 Inputs'!$G$14+C6*'01 Inputs'!$G$40+'01 Inputs'!$G$41+C7*'01 Inputs'!$G$42)<=100,'01 Inputs'!$G$43,IF((C6*'01 Inputs'!$G$14+C6*'01 Inputs'!$G$40+'01 Inputs'!$G$41+C7*'01 Inputs'!$G$42)<=250,'01 Inputs'!$G$44,IF((C6*'01 Inputs'!$G$14+C6*'01 Inputs'!$G$40+'01 Inputs'!$G$41+C7*'01 Inputs'!$G$42)<=500,'01 Inputs'!$G$45,IF((C6*'01 Inputs'!$G$14+C6*'01 Inputs'!$G$40+'01 Inputs'!$G$41+C7*'01 Inputs'!$G$42)<=750,'01 Inputs'!$G$46,'01 Inputs'!$G$47))))*'01 Inputs'!$G$48)))) | D29: =((D5*'01 Inputs'!$G$90)/(1+'01 Inputs'!$G$11))-(D6*CHOOSE(D8,'01 Inputs'!$G$27,'01 Inputs'!$G$28)+D6*'01 Inputs'!$G$31+'01 Inputs'!$G$32+'01 Inputs'!$G$33+D7*'01 Inputs'!$G$37)-('01 Inputs'!$G$39+(IF((D6*'01 Inputs'!$G$14+D6*'01 Inputs'!$G$40+'01 Inputs'!$G$41+D7*'01 Inputs'!$G$42)<=100,'01 Inputs'!$G$43,IF((D6*'01 Inputs'!$G$14+D6*'01 Inputs'!$G$40+'01 Inputs'!$G$41+D7*'01 Inputs'!$G$42)<=250,'01 Inputs'!$G$44,IF((D6*'01 Inputs'!$G$14+D6*'01 Inputs'!$G$40+'01 Inputs'!$G$41+D7*'01 Inputs'!$G$42)<=500,'01 Inputs'!$G$45,IF((D6*'01 Inputs'!$G$14+D6*'01 Inputs'!$G$40+'01 Inputs'!$G$41+D7*'01 Inputs'!$G$42)<=750,'01 Inputs'!$G$46,'01 Inputs'!$G$47))))*'01 Inputs'!$G$48)+((D5*'01 Inputs'!$G$90)*'01 Inputs'!$G$50+'01 Inputs'!$G$51)+'01 Inputs'!$G$53+('01 Inputs'!$G$52*((D6*CHOOSE(D8,'01 Inputs'!$G$27,'01 Inputs'!$G$28)+D6*'01 Inputs'!$G$31+'01 Inputs'!$G$32+'01 Inputs'!$G$33+D7*'01 Inputs'!$G$37)+'01 Inputs'!$G$39+(IF((D6*'01 Inputs'!$G$14+D6*'01 Inputs'!$G$40+'01 Inputs'!$G$41+D7*'01 Inputs'!$G$42)<=100,'01 Inputs'!$G$43,IF((D6*'01 Inputs'!$G$14+D6*'01 Inputs'!$G$40+'01 Inputs'!$G$41+D7*'01 Inputs'!$G$42)<=250,'01 Inputs'!$G$44,IF((D6*'01 Inputs'!$G$14+D6*'01 Inputs'!$G$40+'01 Inputs'!$G$41+D7*'01 Inputs'!$G$42)<=500,'01 Inputs'!$G$45,IF((D6*'01 Inputs'!$G$14+D6*'01 Inputs'!$G$40+'01 Inputs'!$G$41+D7*'01 Inputs'!$G$42)<=750,'01 Inputs'!$G$46,'01 Inputs'!$G$47))))*'01 Inputs'!$G$48)))+('01 Inputs'!$G$54*(((D5*'01 Inputs'!$G$90)/(1+'01 Inputs'!$G$11))+(D6*CHOOSE(D8,'01 Inputs'!$G$27,'01 Inputs'!$G$28)+D6*'01 Inputs'!$G$31+'01 Inputs'!$G$32+'01 Inputs'!$G$33+D7*'01 Inputs'!$G$37)+(IF((D6*'01 Inputs'!$G$14+D6*'01 Inputs'!$G$40+'01 Inputs'!$G$41+D7*'01 Inputs'!$G$42)<=100,'01 Inputs'!$G$43,IF((D6*'01 Inputs'!$G$14+D6*'01 Inputs'!$G$40+'01 Inputs'!$G$41+D7*'01 Inputs'!$G$42)<=250,'01 Inputs'!$G$44,IF((D6*'01 Inputs'!$G$14+D6*'01 Inputs'!$G$40+'01 Inputs'!$G$41+D7*'01 Inputs'!$G$42)<=500,'01 Inputs'!$G$45,IF((D6*'01 Inputs'!$G$14+D6*'01 Inputs'!$G$40+'01 Inputs'!$G$41+D7*'01 Inputs'!$G$42)<=750,'01 Inputs'!$G$46,'01 Inputs'!$G$47))))*'01 Inputs'!$G$48)))) | E29: =((E5*'01 Inputs'!$G$90)/(1+'01 Inputs'!$G$11))-(E6*CHOOSE(E8,'01 Inputs'!$G$27,'01 Inputs'!$G$28)+E6*'01 Inputs'!$G$31+'01 Inputs'!$G$32+'01 Inputs'!$G$33+E7*'01 Inputs'!$G$37)-('01 Inputs'!$G$39+(IF((E6*'01 Inputs'!$G$14+E6*'01 Inputs'!$G$40+'01 Inputs'!$G$41+E7*'01 Inputs'!$G$42)<=100,'01 Inputs'!$G$43,IF((E6*'01 Inputs'!$G$14+E6*'01 Inputs'!$G$40+'01 Inputs'!$G$41+E7*'01 Inputs'!$G$42)<=250,'01 Inputs'!$G$44,IF((E6*'01 Inputs'!$G$14+E6*'01 Inputs'!$G$40+'01 Inputs'!$G$41+E7*'01 Inputs'!$G$42)<=500,'01 Inputs'!$G$45,IF((E6*'01 Inputs'!$G$14+E6*'01 Inputs'!$G$40+'01 Inputs'!$G$41+E7*'01 Inputs'!$G$42)<=750,'01 Inputs'!$G$46,'01 Inputs'!$G$47))))*'01 Inputs'!$G$48)+((E5*'01 Inputs'!$G$90)*'01 Inputs'!$G$50+'01 Inputs'!$G$51)+'01 Inputs'!$G$53+('01 Inputs'!$G$52*((E6*CHOOSE(E8,'01 Inputs'!$G$27,'01 Inputs'!$G$28)+E6*'01 Inputs'!$G$31+'01 Inputs'!$G$32+'01 Inputs'!$G$33+E7*'01 Inputs'!$G$37)+'01 Inputs'!$G$39+(IF((E6*'01 Inputs'!$G$14+E6*'01 Inputs'!$G$40+'01 Inputs'!$G$41+E7*'01 Inputs'!$G$42)<=100,'01 Inputs'!$G$43,IF((E6*'01 Inputs'!$G$14+E6*'01 Inputs'!$G$40+'01 Inputs'!$G$41+E7*'01 Inputs'!$G$42)<=250,'01 Inputs'!$G$44,IF((E6*'01 Inputs'!$G$14+E6*'01 Inputs'!$G$40+'01 Inputs'!$G$41+E7*'01 Inputs'!$G$42)<=500,'01 Inputs'!$G$45,IF((E6*'01 Inputs'!$G$14+E6*'01 Inputs'!$G$40+'01 Inputs'!$G$41+E7*'01 Inputs'!$G$42)<=750,'01 Inputs'!$G$46,'01 Inputs'!$G$47))))*'01 Inputs'!$G$48)))+('01 Inputs'!$G$54*(((E5*'01 Inputs'!$G$90)/(1+'01 Inputs'!$G$11))+(E6*CHOOSE(E8,'01 Inputs'!$G$27,'01 Inputs'!$G$28)+E6*'01 Inputs'!$G$31+'01 Inputs'!$G$32+'01 Inputs'!$G$33+E7*'01 Inputs'!$G$37)+(IF((E6*'01 Inputs'!$G$14+E6*'01 Inputs'!$G$40+'01 Inputs'!$G$41+E7*'01 Inputs'!$G$42)<=100,'01 Inputs'!$G$43,IF((E6*'01 Inputs'!$G$14+E6*'01 Inputs'!$G$40+'01 Inputs'!$G$41+E7*'01 Inputs'!$G$42)<=250,'01 Inputs'!$G$44,IF((E6*'01 Inputs'!$G$14+E6*'01 Inputs'!$G$40+'01 Inputs'!$G$41+E7*'01 Inputs'!$G$42)<=500,'01 Inputs'!$G$45,IF((E6*'01 Inputs'!$G$14+E6*'01 Inputs'!$G$40+'01 Inputs'!$G$41+E7*'01 Inputs'!$G$42)<=750,'01 Inputs'!$G$46,'01 Inputs'!$G$47))))*'01 Inputs'!$G$48)))) | F29: =((F5*'01 Inputs'!$G$90)/(1+'01 Inputs'!$G$11))-(F6*CHOOSE(F8,'01 Inputs'!$G$27,'01 Inputs'!$G$28)+F6*'01 Inputs'!$G$31+'01 Inputs'!$G$32+'01 Inputs'!$G$33+F7*'01 Inputs'!$G$37)-('01 Inputs'!$G$39+(IF((F6*'01 Inputs'!$G$14+F6*'01 Inputs'!$G$40+'01 Inputs'!$G$41+F7*'01 Inputs'!$G$42)<=100,'01 Inputs'!$G$43,IF((F6*'01 Inputs'!$G$14+F6*'01 Inputs'!$G$40+'01 Inputs'!$G$41+F7*'01 Inputs'!$G$42)<=250,'01 Inputs'!$G$44,IF((F6*'01 Inputs'!$G$14+F6*'01 Inputs'!$G$40+'01 Inputs'!$G$41+F7*'01 Inputs'!$G$42)<=500,'01 Inputs'!$G$45,IF((F6*'01 Inputs'!$G$14+F6*'01 Inputs'!$G$40+'01 Inputs'!$G$41+F7*'01 Inputs'!$G$42)<=750,'01 Inputs'!$G$46,'01 Inputs'!$G$47))))*'01 Inputs'!$G$48)+((F5*'01 Inputs'!$G$90)*'01 Inputs'!$G$50+'01 Inputs'!$G$51)+'01 Inputs'!$G$53+('01 Inputs'!$G$52*((F6*CHOOSE(F8,'01 Inputs'!$G$27,'01 Inputs'!$G$28)+F6*'01 Inputs'!$G$31+'01 Inputs'!$G$32+'01 Inputs'!$G$33+F7*'01 Inputs'!$G$37)+'01 Inputs'!$G$39+(IF((F6*'01 Inputs'!$G$14+F6*'01 Inputs'!$G$40+'01 Inputs'!$G$41+F7*'01 Inputs'!$G$42)<=100,'01 Inputs'!$G$43,IF((F6*'01 Inputs'!$G$14+F6*'01 Inputs'!$G$40+'01 Inputs'!$G$41+F7*'01 Inputs'!$G$42)<=250,'01 Inputs'!$G$44,IF((F6*'01 Inputs'!$G$14+F6*'01 Inputs'!$G$40+'01 Inputs'!$G$41+F7*'01 Inputs'!$G$42)<=500,'01 Inputs'!$G$45,IF((F6*'01 Inputs'!$G$14+F6*'01 Inputs'!$G$40+'01 Inputs'!$G$41+F7*'01 Inputs'!$G$42)<=750,'01 Inputs'!$G$46,'01 Inputs'!$G$47))))*'01 Inputs'!$G$48)))+('01 Inputs'!$G$54*(((F5*'01 Inputs'!$G$90)/(1+'01 Inputs'!$G$11))+(F6*CHOOSE(F8,'01 Inputs'!$G$27,'01 Inputs'!$G$28)+F6*'01 Inputs'!$G$31+'01 Inputs'!$G$32+'01 Inputs'!$G$33+F7*'01 Inputs'!$G$37)+(IF((F6*'01 Inputs'!$G$14+F6*'01 Inputs'!$G$40+'01 Inputs'!$G$41+F7*'01 Inputs'!$G$42)<=100,'01 Inputs'!$G$43,IF((F6*'01 Inputs'!$G$14+F6*'01 Inputs'!$G$40+'01 Inputs'!$G$41+F7*'01 Inputs'!$G$42)<=250,'01 Inputs'!$G$44,IF((F6*'01 Inputs'!$G$14+F6*'01 Inputs'!$G$40+'01 Inputs'!$G$41+F7*'01 Inputs'!$G$42)<=500,'01 Inputs'!$G$45,IF((F6*'01 Inputs'!$G$14+F6*'01 Inputs'!$G$40+'01 Inputs'!$G$41+F7*'01 Inputs'!$G$42)<=750,'01 Inputs'!$G$46,'01 Inputs'!$G$47))))*'01 Inputs'!$G$48)))) | G29: =((G5*'01 Inputs'!$G$90)/(1+'01 Inputs'!$G$11))-(G6*CHOOSE(G8,'01 Inputs'!$G$27,'01 Inputs'!$G$28)+G6*'01 Inputs'!$G$31+'01 Inputs'!$G$32+'01 Inputs'!$G$33+G7*'01 Inputs'!$G$37)-('01 Inputs'!$G$39+(IF((G6*'01 Inputs'!$G$14+G6*'01 Inputs'!$G$40+'01 Inputs'!$G$41+G7*'01 Inputs'!$G$42)<=100,'01 Inputs'!$G$43,IF((G6*'01 Inputs'!$G$14+G6*'01 Inputs'!$G$40+'01 Inputs'!$G$41+G7*'01 Inputs'!$G$42)<=250,'01 Inputs'!$G$44,IF((G6*'01 Inputs'!$G$14+G6*'01 Inputs'!$G$40+'01 Inputs'!$G$41+G7*'01 Inputs'!$G$42)<=500,'01 Inputs'!$G$45,IF((G6*'01 Inputs'!$G$14+G6*'01 Inputs'!$G$40+'01 Inputs'!$G$41+G7*'01 Inputs'!$G$42)<=750,'01 Inputs'!$G$46,'01 Inputs'!$G$47))))*'01 Inputs'!$G$48)+((G5*'01 Inputs'!$G$90)*'01 Inputs'!$G$50+'01 Inputs'!$G$51)+'01 Inputs'!$G$53+('01 Inputs'!$G$52*((G6*CHOOSE(G8,'01 Inputs'!$G$27,'01 Inputs'!$G$28)+G6*'01 Inputs'!$G$31+'01 Inputs'!$G$32+'01 Inputs'!$G$33+G7*'01 Inputs'!$G$37)+'01 Inputs'!$G$39+(IF((G6*'01 Inputs'!$G$14+G6*'01 Inputs'!$G$40+'01 Inputs'!$G$41+G7*'01 Inputs'!$G$42)<=100,'01 Inputs'!$G$43,IF((G6*'01 Inputs'!$G$14+G6*'01 Inputs'!$G$40+'01 Inputs'!$G$41+G7*'01 Inputs'!$G$42)<=250,'01 Inputs'!$G$44,IF((G6*'01 Inputs'!$G$14+G6*'01 Inputs'!$G$40+'01 Inputs'!$G$41+G7*'01 Inputs'!$G$42)<=500,'01 Inputs'!$G$45,IF((G6*'01 Inputs'!$G$14+G6*'01 Inputs'!$G$40+'01 Inputs'!$G$41+G7*'01 Inputs'!$G$42)<=750,'01 Inputs'!$G$46,'01 Inputs'!$G$47))))*'01 Inputs'!$G$48)))+('01 Inputs'!$G$54*(((G5*'01 Inputs'!$G$90)/(1+'01 Inputs'!$G$11))+(G6*CHOOSE(G8,'01 Inputs'!$G$27,'01 Inputs'!$G$28)+G6*'01 Inputs'!$G$31+'01 Inputs'!$G$32+'01 Inputs'!$G$33+G7*'01 Inputs'!$G$37)+(IF((G6*'01 Inputs'!$G$14+G6*'01 Inputs'!$G$40+'01 Inputs'!$G$41+G7*'01 Inputs'!$G$42)<=100,'01 Inputs'!$G$43,IF((G6*'01 Inputs'!$G$14+G6*'01 Inputs'!$G$40+'01 Inputs'!$G$41+G7*'01 Inputs'!$G$42)<=250,'01 Inputs'!$G$44,IF((G6*'01 Inputs'!$G$14+G6*'01 Inputs'!$G$40+'01 Inputs'!$G$41+G7*'01 Inputs'!$G$42)<=500,'01 Inputs'!$G$45,IF((G6*'01 Inputs'!$G$14+G6*'01 Inputs'!$G$40+'01 Inputs'!$G$41+G7*'01 Inputs'!$G$42)<=750,'01 Inputs'!$G$46,'01 Inputs'!$G$47))))*'01 Inputs'!$G$48))))
B30: Starter: contribution % of net | C30: =C29/C26 | D30: =D29/D26 | E30: =E29/E26 | F30: =F29/F26 | G30: =G29/G26
B31: Ongoing: net revenue (ex VAT) | C31: =(C9*'01 Inputs'!$G$90)/(1+'01 Inputs'!$G$11) | D31: =(D9*'01 Inputs'!$G$90)/(1+'01 Inputs'!$G$11) | E31: =(E9*'01 Inputs'!$G$90)/(1+'01 Inputs'!$G$11) | F31: =(F9*'01 Inputs'!$G$90)/(1+'01 Inputs'!$G$11) | G31: =(G9*'01 Inputs'!$G$90)/(1+'01 Inputs'!$G$11)
B32: Ongoing: GROSS MARGIN £ | C32: =((C9*'01 Inputs'!$G$90)/(1+'01 Inputs'!$G$11))-(C10*CHOOSE(C8,'01 Inputs'!$G$27,'01 Inputs'!$G$28)+C10*'01 Inputs'!$G$31+'01 Inputs'!$G$32+'01 Inputs'!$G$33+0*'01 Inputs'!$G$37) | D32: =((D9*'01 Inputs'!$G$90)/(1+'01 Inputs'!$G$11))-(D10*CHOOSE(D8,'01 Inputs'!$G$27,'01 Inputs'!$G$28)+D10*'01 Inputs'!$G$31+'01 Inputs'!$G$32+'01 Inputs'!$G$33+0*'01 Inputs'!$G$37) | E32: =((E9*'01 Inputs'!$G$90)/(1+'01 Inputs'!$G$11))-(E10*CHOOSE(E8,'01 Inputs'!$G$27,'01 Inputs'!$G$28)+E10*'01 Inputs'!$G$31+'01 Inputs'!$G$32+'01 Inputs'!$G$33+0*'01 Inputs'!$G$37) | F32: =((F9*'01 Inputs'!$G$90)/(1+'01 Inputs'!$G$11))-(F10*CHOOSE(F8,'01 Inputs'!$G$27,'01 Inputs'!$G$28)+F10*'01 Inputs'!$G$31+'01 Inputs'!$G$32+'01 Inputs'!$G$33+0*'01 Inputs'!$G$37) | G32: =((G9*'01 Inputs'!$G$90)/(1+'01 Inputs'!$G$11))-(G10*CHOOSE(G8,'01 Inputs'!$G$27,'01 Inputs'!$G$28)+G10*'01 Inputs'!$G$31+'01 Inputs'!$G$32+'01 Inputs'!$G$33+0*'01 Inputs'!$G$37)
B33: Ongoing: gross margin % | C33: =C32/C31 | D33: =D32/D31 | E33: =E32/E31 | F33: =F32/F31 | G33: =G32/G31
B34: Ongoing: CONTRIBUTION £ | C34: =((C9*'01 Inputs'!$G$90)/(1+'01 Inputs'!$G$11))-(C10*CHOOSE(C8,'01 Inputs'!$G$27,'01 Inputs'!$G$28)+C10*'01 Inputs'!$G$31+'01 Inputs'!$G$32+'01 Inputs'!$G$33+0*'01 Inputs'!$G$37)-('01 Inputs'!$G$39+(IF((C10*'01 Inputs'!$G$14+C10*'01 Inputs'!$G$40+'01 Inputs'!$G$41+0*'01 Inputs'!$G$42)<=100,'01 Inputs'!$G$43,IF((C10*'01 Inputs'!$G$14+C10*'01 Inputs'!$G$40+'01 Inputs'!$G$41+0*'01 Inputs'!$G$42)<=250,'01 Inputs'!$G$44,IF((C10*'01 Inputs'!$G$14+C10*'01 Inputs'!$G$40+'01 Inputs'!$G$41+0*'01 Inputs'!$G$42)<=500,'01 Inputs'!$G$45,IF((C10*'01 Inputs'!$G$14+C10*'01 Inputs'!$G$40+'01 Inputs'!$G$41+0*'01 Inputs'!$G$42)<=750,'01 Inputs'!$G$46,'01 Inputs'!$G$47))))*'01 Inputs'!$G$48)+((C9*'01 Inputs'!$G$90)*'01 Inputs'!$G$50+'01 Inputs'!$G$51)+'01 Inputs'!$G$53+('01 Inputs'!$G$52*((C10*CHOOSE(C8,'01 Inputs'!$G$27,'01 Inputs'!$G$28)+C10*'01 Inputs'!$G$31+'01 Inputs'!$G$32+'01 Inputs'!$G$33+0*'01 Inputs'!$G$37)+'01 Inputs'!$G$39+(IF((C10*'01 Inputs'!$G$14+C10*'01 Inputs'!$G$40+'01 Inputs'!$G$41+0*'01 Inputs'!$G$42)<=100,'01 Inputs'!$G$43,IF((C10*'01 Inputs'!$G$14+C10*'01 Inputs'!$G$40+'01 Inputs'!$G$41+0*'01 Inputs'!$G$42)<=250,'01 Inputs'!$G$44,IF((C10*'01 Inputs'!$G$14+C10*'01 Inputs'!$G$40+'01 Inputs'!$G$41+0*'01 Inputs'!$G$42)<=500,'01 Inputs'!$G$45,IF((C10*'01 Inputs'!$G$14+C10*'01 Inputs'!$G$40+'01 Inputs'!$G$41+0*'01 Inputs'!$G$42)<=750,'01 Inputs'!$G$46,'01 Inputs'!$G$47))))*'01 Inputs'!$G$48)))+('01 Inputs'!$G$54*(((C9*'01 Inputs'!$G$90)/(1+'01 Inputs'!$G$11))+(C10*CHOOSE(C8,'01 Inputs'!$G$27,'01 Inputs'!$G$28)+C10*'01 Inputs'!$G$31+'01 Inputs'!$G$32+'01 Inputs'!$G$33+0*'01 Inputs'!$G$37)+(IF((C10*'01 Inputs'!$G$14+C10*'01 Inputs'!$G$40+'01 Inputs'!$G$41+0*'01 Inputs'!$G$42)<=100,'01 Inputs'!$G$43,IF((C10*'01 Inputs'!$G$14+C10*'01 Inputs'!$G$40+'01 Inputs'!$G$41+0*'01 Inputs'!$G$42)<=250,'01 Inputs'!$G$44,IF((C10*'01 Inputs'!$G$14+C10*'01 Inputs'!$G$40+'01 Inputs'!$G$41+0*'01 Inputs'!$G$42)<=500,'01 Inputs'!$G$45,IF((C10*'01 Inputs'!$G$14+C10*'01 Inputs'!$G$40+'01 Inputs'!$G$41+0*'01 Inputs'!$G$42)<=750,'01 Inputs'!$G$46,'01 Inputs'!$G$47))))*'01 Inputs'!$G$48)))) | D34: =((D9*'01 Inputs'!$G$90)/(1+'01 Inputs'!$G$11))-(D10*CHOOSE(D8,'01 Inputs'!$G$27,'01 Inputs'!$G$28)+D10*'01 Inputs'!$G$31+'01 Inputs'!$G$32+'01 Inputs'!$G$33+0*'01 Inputs'!$G$37)-('01 Inputs'!$G$39+(IF((D10*'01 Inputs'!$G$14+D10*'01 Inputs'!$G$40+'01 Inputs'!$G$41+0*'01 Inputs'!$G$42)<=100,'01 Inputs'!$G$43,IF((D10*'01 Inputs'!$G$14+D10*'01 Inputs'!$G$40+'01 Inputs'!$G$41+0*'01 Inputs'!$G$42)<=250,'01 Inputs'!$G$44,IF((D10*'01 Inputs'!$G$14+D10*'01 Inputs'!$G$40+'01 Inputs'!$G$41+0*'01 Inputs'!$G$42)<=500,'01 Inputs'!$G$45,IF((D10*'01 Inputs'!$G$14+D10*'01 Inputs'!$G$40+'01 Inputs'!$G$41+0*'01 Inputs'!$G$42)<=750,'01 Inputs'!$G$46,'01 Inputs'!$G$47))))*'01 Inputs'!$G$48)+((D9*'01 Inputs'!$G$90)*'01 Inputs'!$G$50+'01 Inputs'!$G$51)+'01 Inputs'!$G$53+('01 Inputs'!$G$52*((D10*CHOOSE(D8,'01 Inputs'!$G$27,'01 Inputs'!$G$28)+D10*'01 Inputs'!$G$31+'01 Inputs'!$G$32+'01 Inputs'!$G$33+0*'01 Inputs'!$G$37)+'01 Inputs'!$G$39+(IF((D10*'01 Inputs'!$G$14+D10*'01 Inputs'!$G$40+'01 Inputs'!$G$41+0*'01 Inputs'!$G$42)<=100,'01 Inputs'!$G$43,IF((D10*'01 Inputs'!$G$14+D10*'01 Inputs'!$G$40+'01 Inputs'!$G$41+0*'01 Inputs'!$G$42)<=250,'01 Inputs'!$G$44,IF((D10*'01 Inputs'!$G$14+D10*'01 Inputs'!$G$40+'01 Inputs'!$G$41+0*'01 Inputs'!$G$42)<=500,'01 Inputs'!$G$45,IF((D10*'01 Inputs'!$G$14+D10*'01 Inputs'!$G$40+'01 Inputs'!$G$41+0*'01 Inputs'!$G$42)<=750,'01 Inputs'!$G$46,'01 Inputs'!$G$47))))*'01 Inputs'!$G$48)))+('01 Inputs'!$G$54*(((D9*'01 Inputs'!$G$90)/(1+'01 Inputs'!$G$11))+(D10*CHOOSE(D8,'01 Inputs'!$G$27,'01 Inputs'!$G$28)+D10*'01 Inputs'!$G$31+'01 Inputs'!$G$32+'01 Inputs'!$G$33+0*'01 Inputs'!$G$37)+(IF((D10*'01 Inputs'!$G$14+D10*'01 Inputs'!$G$40+'01 Inputs'!$G$41+0*'01 Inputs'!$G$42)<=100,'01 Inputs'!$G$43,IF((D10*'01 Inputs'!$G$14+D10*'01 Inputs'!$G$40+'01 Inputs'!$G$41+0*'01 Inputs'!$G$42)<=250,'01 Inputs'!$G$44,IF((D10*'01 Inputs'!$G$14+D10*'01 Inputs'!$G$40+'01 Inputs'!$G$41+0*'01 Inputs'!$G$42)<=500,'01 Inputs'!$G$45,IF((D10*'01 Inputs'!$G$14+D10*'01 Inputs'!$G$40+'01 Inputs'!$G$41+0*'01 Inputs'!$G$42)<=750,'01 Inputs'!$G$46,'01 Inputs'!$G$47))))*'01 Inputs'!$G$48)))) | E34: =((E9*'01 Inputs'!$G$90)/(1+'01 Inputs'!$G$11))-(E10*CHOOSE(E8,'01 Inputs'!$G$27,'01 Inputs'!$G$28)+E10*'01 Inputs'!$G$31+'01 Inputs'!$G$32+'01 Inputs'!$G$33+0*'01 Inputs'!$G$37)-('01 Inputs'!$G$39+(IF((E10*'01 Inputs'!$G$14+E10*'01 Inputs'!$G$40+'01 Inputs'!$G$41+0*'01 Inputs'!$G$42)<=100,'01 Inputs'!$G$43,IF((E10*'01 Inputs'!$G$14+E10*'01 Inputs'!$G$40+'01 Inputs'!$G$41+0*'01 Inputs'!$G$42)<=250,'01 Inputs'!$G$44,IF((E10*'01 Inputs'!$G$14+E10*'01 Inputs'!$G$40+'01 Inputs'!$G$41+0*'01 Inputs'!$G$42)<=500,'01 Inputs'!$G$45,IF((E10*'01 Inputs'!$G$14+E10*'01 Inputs'!$G$40+'01 Inputs'!$G$41+0*'01 Inputs'!$G$42)<=750,'01 Inputs'!$G$46,'01 Inputs'!$G$47))))*'01 Inputs'!$G$48)+((E9*'01 Inputs'!$G$90)*'01 Inputs'!$G$50+'01 Inputs'!$G$51)+'01 Inputs'!$G$53+('01 Inputs'!$G$52*((E10*CHOOSE(E8,'01 Inputs'!$G$27,'01 Inputs'!$G$28)+E10*'01 Inputs'!$G$31+'01 Inputs'!$G$32+'01 Inputs'!$G$33+0*'01 Inputs'!$G$37)+'01 Inputs'!$G$39+(IF((E10*'01 Inputs'!$G$14+E10*'01 Inputs'!$G$40+'01 Inputs'!$G$41+0*'01 Inputs'!$G$42)<=100,'01 Inputs'!$G$43,IF((E10*'01 Inputs'!$G$14+E10*'01 Inputs'!$G$40+'01 Inputs'!$G$41+0*'01 Inputs'!$G$42)<=250,'01 Inputs'!$G$44,IF((E10*'01 Inputs'!$G$14+E10*'01 Inputs'!$G$40+'01 Inputs'!$G$41+0*'01 Inputs'!$G$42)<=500,'01 Inputs'!$G$45,IF((E10*'01 Inputs'!$G$14+E10*'01 Inputs'!$G$40+'01 Inputs'!$G$41+0*'01 Inputs'!$G$42)<=750,'01 Inputs'!$G$46,'01 Inputs'!$G$47))))*'01 Inputs'!$G$48)))+('01 Inputs'!$G$54*(((E9*'01 Inputs'!$G$90)/(1+'01 Inputs'!$G$11))+(E10*CHOOSE(E8,'01 Inputs'!$G$27,'01 Inputs'!$G$28)+E10*'01 Inputs'!$G$31+'01 Inputs'!$G$32+'01 Inputs'!$G$33+0*'01 Inputs'!$G$37)+(IF((E10*'01 Inputs'!$G$14+E10*'01 Inputs'!$G$40+'01 Inputs'!$G$41+0*'01 Inputs'!$G$42)<=100,'01 Inputs'!$G$43,IF((E10*'01 Inputs'!$G$14+E10*'01 Inputs'!$G$40+'01 Inputs'!$G$41+0*'01 Inputs'!$G$42)<=250,'01 Inputs'!$G$44,IF((E10*'01 Inputs'!$G$14+E10*'01 Inputs'!$G$40+'01 Inputs'!$G$41+0*'01 Inputs'!$G$42)<=500,'01 Inputs'!$G$45,IF((E10*'01 Inputs'!$G$14+E10*'01 Inputs'!$G$40+'01 Inputs'!$G$41+0*'01 Inputs'!$G$42)<=750,'01 Inputs'!$G$46,'01 Inputs'!$G$47))))*'01 Inputs'!$G$48)))) | F34: =((F9*'01 Inputs'!$G$90)/(1+'01 Inputs'!$G$11))-(F10*CHOOSE(F8,'01 Inputs'!$G$27,'01 Inputs'!$G$28)+F10*'01 Inputs'!$G$31+'01 Inputs'!$G$32+'01 Inputs'!$G$33+0*'01 Inputs'!$G$37)-('01 Inputs'!$G$39+(IF((F10*'01 Inputs'!$G$14+F10*'01 Inputs'!$G$40+'01 Inputs'!$G$41+0*'01 Inputs'!$G$42)<=100,'01 Inputs'!$G$43,IF((F10*'01 Inputs'!$G$14+F10*'01 Inputs'!$G$40+'01 Inputs'!$G$41+0*'01 Inputs'!$G$42)<=250,'01 Inputs'!$G$44,IF((F10*'01 Inputs'!$G$14+F10*'01 Inputs'!$G$40+'01 Inputs'!$G$41+0*'01 Inputs'!$G$42)<=500,'01 Inputs'!$G$45,IF((F10*'01 Inputs'!$G$14+F10*'01 Inputs'!$G$40+'01 Inputs'!$G$41+0*'01 Inputs'!$G$42)<=750,'01 Inputs'!$G$46,'01 Inputs'!$G$47))))*'01 Inputs'!$G$48)+((F9*'01 Inputs'!$G$90)*'01 Inputs'!$G$50+'01 Inputs'!$G$51)+'01 Inputs'!$G$53+('01 Inputs'!$G$52*((F10*CHOOSE(F8,'01 Inputs'!$G$27,'01 Inputs'!$G$28)+F10*'01 Inputs'!$G$31+'01 Inputs'!$G$32+'01 Inputs'!$G$33+0*'01 Inputs'!$G$37)+'01 Inputs'!$G$39+(IF((F10*'01 Inputs'!$G$14+F10*'01 Inputs'!$G$40+'01 Inputs'!$G$41+0*'01 Inputs'!$G$42)<=100,'01 Inputs'!$G$43,IF((F10*'01 Inputs'!$G$14+F10*'01 Inputs'!$G$40+'01 Inputs'!$G$41+0*'01 Inputs'!$G$42)<=250,'01 Inputs'!$G$44,IF((F10*'01 Inputs'!$G$14+F10*'01 Inputs'!$G$40+'01 Inputs'!$G$41+0*'01 Inputs'!$G$42)<=500,'01 Inputs'!$G$45,IF((F10*'01 Inputs'!$G$14+F10*'01 Inputs'!$G$40+'01 Inputs'!$G$41+0*'01 Inputs'!$G$42)<=750,'01 Inputs'!$G$46,'01 Inputs'!$G$47))))*'01 Inputs'!$G$48)))+('01 Inputs'!$G$54*(((F9*'01 Inputs'!$G$90)/(1+'01 Inputs'!$G$11))+(F10*CHOOSE(F8,'01 Inputs'!$G$27,'01 Inputs'!$G$28)+F10*'01 Inputs'!$G$31+'01 Inputs'!$G$32+'01 Inputs'!$G$33+0*'01 Inputs'!$G$37)+(IF((F10*'01 Inputs'!$G$14+F10*'01 Inputs'!$G$40+'01 Inputs'!$G$41+0*'01 Inputs'!$G$42)<=100,'01 Inputs'!$G$43,IF((F10*'01 Inputs'!$G$14+F10*'01 Inputs'!$G$40+'01 Inputs'!$G$41+0*'01 Inputs'!$G$42)<=250,'01 Inputs'!$G$44,IF((F10*'01 Inputs'!$G$14+F10*'01 Inputs'!$G$40+'01 Inputs'!$G$41+0*'01 Inputs'!$G$42)<=500,'01 Inputs'!$G$45,IF((F10*'01 Inputs'!$G$14+F10*'01 Inputs'!$G$40+'01 Inputs'!$G$41+0*'01 Inputs'!$G$42)<=750,'01 Inputs'!$G$46,'01 Inputs'!$G$47))))*'01 Inputs'!$G$48)))) | G34: =((G9*'01 Inputs'!$G$90)/(1+'01 Inputs'!$G$11))-(G10*CHOOSE(G8,'01 Inputs'!$G$27,'01 Inputs'!$G$28)+G10*'01 Inputs'!$G$31+'01 Inputs'!$G$32+'01 Inputs'!$G$33+0*'01 Inputs'!$G$37)-('01 Inputs'!$G$39+(IF((G10*'01 Inputs'!$G$14+G10*'01 Inputs'!$G$40+'01 Inputs'!$G$41+0*'01 Inputs'!$G$42)<=100,'01 Inputs'!$G$43,IF((G10*'01 Inputs'!$G$14+G10*'01 Inputs'!$G$40+'01 Inputs'!$G$41+0*'01 Inputs'!$G$42)<=250,'01 Inputs'!$G$44,IF((G10*'01 Inputs'!$G$14+G10*'01 Inputs'!$G$40+'01 Inputs'!$G$41+0*'01 Inputs'!$G$42)<=500,'01 Inputs'!$G$45,IF((G10*'01 Inputs'!$G$14+G10*'01 Inputs'!$G$40+'01 Inputs'!$G$41+0*'01 Inputs'!$G$42)<=750,'01 Inputs'!$G$46,'01 Inputs'!$G$47))))*'01 Inputs'!$G$48)+((G9*'01 Inputs'!$G$90)*'01 Inputs'!$G$50+'01 Inputs'!$G$51)+'01 Inputs'!$G$53+('01 Inputs'!$G$52*((G10*CHOOSE(G8,'01 Inputs'!$G$27,'01 Inputs'!$G$28)+G10*'01 Inputs'!$G$31+'01 Inputs'!$G$32+'01 Inputs'!$G$33+0*'01 Inputs'!$G$37)+'01 Inputs'!$G$39+(IF((G10*'01 Inputs'!$G$14+G10*'01 Inputs'!$G$40+'01 Inputs'!$G$41+0*'01 Inputs'!$G$42)<=100,'01 Inputs'!$G$43,IF((G10*'01 Inputs'!$G$14+G10*'01 Inputs'!$G$40+'01 Inputs'!$G$41+0*'01 Inputs'!$G$42)<=250,'01 Inputs'!$G$44,IF((G10*'01 Inputs'!$G$14+G10*'01 Inputs'!$G$40+'01 Inputs'!$G$41+0*'01 Inputs'!$G$42)<=500,'01 Inputs'!$G$45,IF((G10*'01 Inputs'!$G$14+G10*'01 Inputs'!$G$40+'01 Inputs'!$G$41+0*'01 Inputs'!$G$42)<=750,'01 Inputs'!$G$46,'01 Inputs'!$G$47))))*'01 Inputs'!$G$48)))+('01 Inputs'!$G$54*(((G9*'01 Inputs'!$G$90)/(1+'01 Inputs'!$G$11))+(G10*CHOOSE(G8,'01 Inputs'!$G$27,'01 Inputs'!$G$28)+G10*'01 Inputs'!$G$31+'01 Inputs'!$G$32+'01 Inputs'!$G$33+0*'01 Inputs'!$G$37)+(IF((G10*'01 Inputs'!$G$14+G10*'01 Inputs'!$G$40+'01 Inputs'!$G$41+0*'01 Inputs'!$G$42)<=100,'01 Inputs'!$G$43,IF((G10*'01 Inputs'!$G$14+G10*'01 Inputs'!$G$40+'01 Inputs'!$G$41+0*'01 Inputs'!$G$42)<=250,'01 Inputs'!$G$44,IF((G10*'01 Inputs'!$G$14+G10*'01 Inputs'!$G$40+'01 Inputs'!$G$41+0*'01 Inputs'!$G$42)<=500,'01 Inputs'!$G$45,IF((G10*'01 Inputs'!$G$14+G10*'01 Inputs'!$G$40+'01 Inputs'!$G$41+0*'01 Inputs'!$G$42)<=750,'01 Inputs'!$G$46,'01 Inputs'!$G$47))))*'01 Inputs'!$G$48))))
B35: Ongoing: contribution % of net | C35: =C34/C31 | D35: =D34/D31 | E35: =E34/E31 | F35: =F34/F31 | G35: =G34/G31
B36: Ongoing: contribution per serving | C36: =C34/C10 | D36: =D34/D10 | E36: =E34/E10 | F36: =F34/F10 | G36: =G34/G10
B37: Ongoing: contribution per MONTH of subscription | C37: =C34/C11 | D37: =D34/D11 | E37: =E34/E11 | F37: =F34/F11 | G37: =G34/G11 | H37: The right comparator for CAC, because CAC is recovered in calendar time, not in shipments.
B39: ACQUISITION AND RETENTION (base churn and base CAC)
B40: Blended CAC | C40: ='01 Inputs'!$G$67 | D40: ='01 Inputs'!$G$67 | E40: ='01 Inputs'!$G$67 | F40: ='01 Inputs'!$G$67 | G40: ='01 Inputs'!$G$67
B41: Total monthly churn | C41: ='01 Inputs'!$G$72 | D41: ='01 Inputs'!$G$72 | E41: ='01 Inputs'!$G$72 | F41: ='01 Inputs'!$G$72 | G41: ='01 Inputs'!$G$72
B42: First-refill drop | C42: ='01 Inputs'!$G$70 | D42: ='01 Inputs'!$G$70 | E42: ='01 Inputs'!$G$70 | F42: ='01 Inputs'!$G$70 | G42: ='01 Inputs'!$G$70
B43: Churn per CADENCE PERIOD (compounded) | C43: =1-(1-C41)^C11 | D43: =1-(1-D41)^D11 | E43: =1-(1-E41)^E11 | F43: =1-(1-F41)^F11 | G43: =1-(1-G41)^G11 | H43: Quarterly cadence compounds monthly churn over three months BUT removes two cancellation decision points a quarter. A3 is a bet that the second effect beats the first.
B44: Retained periods in 12 months | C44: =(1-C42)*(1-(1-C43)^(12/C11))/C43 | D44: =(1-D42)*(1-(1-D43)^(12/D11))/D43 | E44: =(1-E42)*(1-(1-E43)^(12/E11))/E43 | F44: =(1-F42)*(1-(1-F43)^(12/F11))/F43 | G44: =(1-G42)*(1-(1-G43)^(12/G11))/G43
B45: Retained periods in 24 months | C45: =(1-C42)*(1-(1-C43)^(24/C11))/C43 | D45: =(1-D42)*(1-(1-D43)^(24/D11))/D43 | E45: =(1-E42)*(1-(1-E43)^(24/E11))/E43 | F45: =(1-F42)*(1-(1-F43)^(24/F11))/F43 | G45: =(1-G42)*(1-(1-G43)^(24/G11))/G43
B46: LTV 12 months (CONTRIBUTION basis) | C46: =C29+C44*C34 | D46: =D29+D44*D34 | E46: =E29+E44*E34 | F46: =F29+F44*F34 | G46: =G29+G44*G34
B47: LTV 24 months (CONTRIBUTION basis) | C47: =C29+C45*C34 | D47: =D29+D45*D34 | E47: =E29+E45*E34 | F47: =F29+F45*F34 | G47: =G29+G45*G34
B48: LTV:CAC — 12 months | C48: =C46/C40 | D48: =D46/D40 | E48: =E46/E40 | F48: =F46/F40 | G48: =G46/G40
B49: LTV:CAC — 24 months | C49: =C47/C40 | D49: =D47/D40 | E49: =E47/E40 | F49: =F47/F40 | G49: =G47/G40
B50: CAC payback (MONTHS) | C50: =IF(C29>=C40,0,IF(C29+C34*(1-C42)/C43<=C40,"never",C11*LN(1-(C40-C29)*C43/(C34*(1-C42)))/LN(1-C43))) | D50: =IF(D29>=D40,0,IF(D29+D34*(1-D42)/D43<=D40,"never",D11*LN(1-(D40-D29)*D43/(D34*(1-D42)))/LN(1-D43))) | E50: =IF(E29>=E40,0,IF(E29+E34*(1-E42)/E43<=E40,"never",E11*LN(1-(E40-E29)*E43/(E34*(1-E42)))/LN(1-E43))) | F50: =IF(F29>=F40,0,IF(F29+F34*(1-F42)/F43<=F40,"never",F11*LN(1-(F40-F29)*F43/(F34*(1-F42)))/LN(1-F43))) | G50: =IF(G29>=G40,0,IF(G29+G34*(1-G42)/G43<=G40,"never",G11*LN(1-(G40-G29)*G43/(G34*(1-G42)))/LN(1-G43)))
B51: Year-1 contribution per customer AFTER CAC | C51: =C46-C40 | D51: =D46-D40 | E51: =E46-E40 | F51: =F46-F40 | G51: =G46-G40
B52: MAXIMUM LIFETIME CONTRIBUTION (infinite horizon — the ceiling) | C52: =C29+C34*(1-C42)/C43 | D52: =D29+D34*(1-D42)/D43 | E52: =E29+E34*(1-E42)/E43 | F52: =F29+F34*(1-F42)/F43 | G52: =G29+G34*(1-G42)/G43 | H52: THE MOST DECISIVE NUMBER IN THE WORKBOOK. At a given churn rate a subscriber has a finite expected lifetime, so there is a CEILING on what any customer can ever be worth — no marketing patience, no retention email and no 24-month horizon gets past it. If this row is not comfortably above CAC, the business does not work at any horizon, and the answer is churn or price, never 'wait longer'.
B53: MAX LTV:CAC (infinite horizon) | C53: =C52/C40 | D53: =D52/D40 | E53: =E52/E40 | F53: =F52/F40 | G53: =G52/G40
B55: VERDICT AND RISK
B56: Passes a 3x 12-month LTV:CAC test? | C56: =IF(C48>=3,"YES",IF(C48>=1,"MARGINAL","NO")) | D56: =IF(D48>=3,"YES",IF(D48>=1,"MARGINAL","NO")) | E56: =IF(E48>=3,"YES",IF(E48>=1,"MARGINAL","NO")) | F56: =IF(F48>=3,"YES",IF(F48>=1,"MARGINAL","NO")) | G56: =IF(G48>=3,"YES",IF(G48>=1,"MARGINAL","NO"))
B57: Passes a 12-month payback test? | C57: =IF(ISNUMBER(C50),IF(C50<=12,"YES","NO — "&TEXT(C50,"0.0")&" months"),"NO — never") | D57: =IF(ISNUMBER(D50),IF(D50<=12,"YES","NO — "&TEXT(D50,"0.0")&" months"),"NO — never") | E57: =IF(ISNUMBER(E50),IF(E50<=12,"YES","NO — "&TEXT(E50,"0.0")&" months"),"NO — never") | F57: =IF(ISNUMBER(F50),IF(F50<=12,"YES","NO — "&TEXT(F50,"0.0")&" months"),"NO — never") | G57: =IF(ISNUMBER(G50),IF(G50<=12,"YES","NO — "&TEXT(G50,"0.0")&" months"),"NO — never")
B58: Within the A-027 affordability ceiling (<= £20/month)? | C58: =IF(C17<=20,"YES","NO - "&TEXT(C17,"£0.00")&"/month") | D58: =IF(D17<=20,"YES","NO - "&TEXT(D17,"£0.00")&"/month") | E58: =IF(E17<=20,"YES","NO - "&TEXT(E17,"£0.00")&"/month") | F58: =IF(F17<=20,"YES","NO - "&TEXT(F17,"£0.00")&"/month") | G58: =IF(G17<=20,"YES","NO - "&TEXT(G17,"£0.00")&"/month")
B59: Does the CEILING clear CAC by 3x? | C59: =IF(C53>=3,"YES",IF(C53>=1,"MARGINAL - "&TEXT(C53,"0.00")&"x","NO - "&TEXT(C53,"0.00")&"x")) | D59: =IF(D53>=3,"YES",IF(D53>=1,"MARGINAL - "&TEXT(D53,"0.00")&"x","NO - "&TEXT(D53,"0.00")&"x")) | E59: =IF(E53>=3,"YES",IF(E53>=1,"MARGINAL - "&TEXT(E53,"0.00")&"x","NO - "&TEXT(E53,"0.00")&"x")) | F59: =IF(F53>=3,"YES",IF(F53>=1,"MARGINAL - "&TEXT(F53,"0.00")&"x","NO - "&TEXT(F53,"0.00")&"x")) | G59: =IF(G53>=3,"YES",IF(G53>=1,"MARGINAL - "&TEXT(G53,"0.00")&"x","NO - "&TEXT(G53,"0.00")&"x")) | H59: Applied to the infinite-horizon ceiling, not to a 12-month window. This is the fair version of the 3x test for a subscription business — and it is the one V-Drop still fails at base-case churn.
B60: Principal risk | C60: RISK: bundles unproven hardware (A-025) into the entry price at the exact moment of highest friction, and the CNC tooling amortisation lands on the first, smallest cohort. £19.99/month is 50% of the median UK subscriber's ENTIRE monthly subscription budget (A-027). Upside: highest month-0 cash, so the shortest payback of the monthly options. | D60: RISK: the £22.99 ongoing price is ABOVE the A-027 comfort ceiling and above Waterdrop, Berocca Mind and Wellwoman Max per serving — it needs the taste to actually be better, not just claimed to be. Upside: no hardware capital, no tooling amortisation, lowest entry friction, and the intro discount is a cheaper acquisition subsidy than a £10-£20 case. The case becomes a margin-positive accessory instead of a cost. | E60: RISK: highest cash ask at entry (£34.99 then £54.99 ninety days later) so conversion will be materially lower, and a 90-tablet pack is 315-405 g, which moves it into the 251-500 g postal band. Upside: three months of cash pulled forward, two fewer fulfilment and payment events per quarter, and — the real prize — a third as many cancellation decision points. On these inputs it is the only architecture that comfortably clears both tests. | F60: RISK: fails on arithmetic. At £15.99 for 30 tablets the contribution per month is too thin to recover a health-and-wellness CAC before the customer churns, and there is no premium available to fund the taste system that is supposed to be the differentiator. Included deliberately to show that 'price it cheaper' is not an available answer under a £40-£95 CAC. | G60: RISK: £25.00/month is 62% of the median UK subscriber's ENTIRE monthly subscription budget (A-027), and a £74.99 quarterly charge is a large, visible, memorable debit — exactly the kind the DMCC reminder notices will draw attention to twice a year. It also asks the customer to commit before the taste has been proved to them, which is why the £19.99 first month exists. Upside: it is the only architecture here that combines all four levers at once — no hardware cost at entry, a third as many cancellation decision points, a price that can actually fund branded source forms, and a per-serving price (£0.833) that sits below Wild Nutrition and far below AG1 while clearing the contribution the CAC requires. | H60: OPINION, grounded in the assumptions register.
B63: PRICE FLOOR — the minimum monthly RRP inc VAT that delivers a target CONTRIBUTION margin, by actives grade
B64: Target contribution margin (% of net revenue) | C64: COMMODITY forms: required RRP inc VAT | D64: COMMODITY forms: £ per serving | E64: PATENTED forms: required RRP inc VAT | F64: PATENTED forms: £ per serving | H64: Comment
B65: 0.5 | C65: =IF((1-(1+'01 Inputs'!$G$11)*'01 Inputs'!$G$50-'01 Inputs'!$G$54-$B$65)<=0,"impossible",(('01 Inputs'!$G$15*'01 Inputs'!$G$27+'01 Inputs'!$G$15*'01 Inputs'!$G$31+'01 Inputs'!$G$32+'01 Inputs'!$G$33)*(1+'01 Inputs'!$G$52+'01 Inputs'!$G$54)+'01 Inputs'!$G$39*(1+'01 Inputs'!$G$52)+(IF(('01 Inputs'!$G$15*'01 Inputs'!$G$14+'01 Inputs'!$G$15*'01 Inputs'!$G$40+'01 Inputs'!$G$41)<=100,'01 Inputs'!$G$43,IF(('01 Inputs'!$G$15*'01 Inputs'!$G$14+'01 Inputs'!$G$15*'01 Inputs'!$G$40+'01 Inputs'!$G$41)<=250,'01 Inputs'!$G$44,IF(('01 Inputs'!$G$15*'01 Inputs'!$G$14+'01 Inputs'!$G$15*'01 Inputs'!$G$40+'01 Inputs'!$G$41)<=500,'01 Inputs'!$G$45,IF(('01 Inputs'!$G$15*'01 Inputs'!$G$14+'01 Inputs'!$G$15*'01 Inputs'!$G$40+'01 Inputs'!$G$41)<=750,'01 Inputs'!$G$46,'01 Inputs'!$G$47))))*'01 Inputs'!$G$48)*(1+'01 Inputs'!$G$52+'01 Inputs'!$G$54)+'01 Inputs'!$G$51+'01 Inputs'!$G$53)/(1-(1+'01 Inputs'!$G$11)*'01 Inputs'!$G$50-'01 Inputs'!$G$54-$B$65)*(1+'01 Inputs'!$G$11)/'01 Inputs'!$G$90) | D65: =C65/'01 Inputs'!$G$15 | E65: =IF((1-(1+'01 Inputs'!$G$11)*'01 Inputs'!$G$50-'01 Inputs'!$G$54-$B$65)<=0,"impossible",(('01 Inputs'!$G$15*'01 Inputs'!$G$28+'01 Inputs'!$G$15*'01 Inputs'!$G$31+'01 Inputs'!$G$32+'01 Inputs'!$G$33)*(1+'01 Inputs'!$G$52+'01 Inputs'!$G$54)+'01 Inputs'!$G$39*(1+'01 Inputs'!$G$52)+(IF(('01 Inputs'!$G$15*'01 Inputs'!$G$14+'01 Inputs'!$G$15*'01 Inputs'!$G$40+'01 Inputs'!$G$41)<=100,'01 Inputs'!$G$43,IF(('01 Inputs'!$G$15*'01 Inputs'!$G$14+'01 Inputs'!$G$15*'01 Inputs'!$G$40+'01 Inputs'!$G$41)<=250,'01 Inputs'!$G$44,IF(('01 Inputs'!$G$15*'01 Inputs'!$G$14+'01 Inputs'!$G$15*'01 Inputs'!$G$40+'01 Inputs'!$G$41)<=500,'01 Inputs'!$G$45,IF(('01 Inputs'!$G$15*'01 Inputs'!$G$14+'01 Inputs'!$G$15*'01 Inputs'!$G$40+'01 Inputs'!$G$41)<=750,'01 Inputs'!$G$46,'01 Inputs'!$G$47))))*'01 Inputs'!$G$48)*(1+'01 Inputs'!$G$52+'01 Inputs'!$G$54)+'01 Inputs'!$G$51+'01 Inputs'!$G$53)/(1-(1+'01 Inputs'!$G$11)*'01 Inputs'!$G$50-'01 Inputs'!$G$54-$B$65)*(1+'01 Inputs'!$G$11)/'01 Inputs'!$G$90) | F65: =E65/'01 Inputs'!$G$15
B66: 0.6 | C66: =IF((1-(1+'01 Inputs'!$G$11)*'01 Inputs'!$G$50-'01 Inputs'!$G$54-$B$66)<=0,"impossible",(('01 Inputs'!$G$15*'01 Inputs'!$G$27+'01 Inputs'!$G$15*'01 Inputs'!$G$31+'01 Inputs'!$G$32+'01 Inputs'!$G$33)*(1+'01 Inputs'!$G$52+'01 Inputs'!$G$54)+'01 Inputs'!$G$39*(1+'01 Inputs'!$G$52)+(IF(('01 Inputs'!$G$15*'01 Inputs'!$G$14+'01 Inputs'!$G$15*'01 Inputs'!$G$40+'01 Inputs'!$G$41)<=100,'01 Inputs'!$G$43,IF(('01 Inputs'!$G$15*'01 Inputs'!$G$14+'01 Inputs'!$G$15*'01 Inputs'!$G$40+'01 Inputs'!$G$41)<=250,'01 Inputs'!$G$44,IF(('01 Inputs'!$G$15*'01 Inputs'!$G$14+'01 Inputs'!$G$15*'01 Inputs'!$G$40+'01 Inputs'!$G$41)<=500,'01 Inputs'!$G$45,IF(('01 Inputs'!$G$15*'01 Inputs'!$G$14+'01 Inputs'!$G$15*'01 Inputs'!$G$40+'01 Inputs'!$G$41)<=750,'01 Inputs'!$G$46,'01 Inputs'!$G$47))))*'01 Inputs'!$G$48)*(1+'01 Inputs'!$G$52+'01 Inputs'!$G$54)+'01 Inputs'!$G$51+'01 Inputs'!$G$53)/(1-(1+'01 Inputs'!$G$11)*'01 Inputs'!$G$50-'01 Inputs'!$G$54-$B$66)*(1+'01 Inputs'!$G$11)/'01 Inputs'!$G$90) | D66: =C66/'01 Inputs'!$G$15 | E66: =IF((1-(1+'01 Inputs'!$G$11)*'01 Inputs'!$G$50-'01 Inputs'!$G$54-$B$66)<=0,"impossible",(('01 Inputs'!$G$15*'01 Inputs'!$G$28+'01 Inputs'!$G$15*'01 Inputs'!$G$31+'01 Inputs'!$G$32+'01 Inputs'!$G$33)*(1+'01 Inputs'!$G$52+'01 Inputs'!$G$54)+'01 Inputs'!$G$39*(1+'01 Inputs'!$G$52)+(IF(('01 Inputs'!$G$15*'01 Inputs'!$G$14+'01 Inputs'!$G$15*'01 Inputs'!$G$40+'01 Inputs'!$G$41)<=100,'01 Inputs'!$G$43,IF(('01 Inputs'!$G$15*'01 Inputs'!$G$14+'01 Inputs'!$G$15*'01 Inputs'!$G$40+'01 Inputs'!$G$41)<=250,'01 Inputs'!$G$44,IF(('01 Inputs'!$G$15*'01 Inputs'!$G$14+'01 Inputs'!$G$15*'01 Inputs'!$G$40+'01 Inputs'!$G$41)<=500,'01 Inputs'!$G$45,IF(('01 Inputs'!$G$15*'01 Inputs'!$G$14+'01 Inputs'!$G$15*'01 Inputs'!$G$40+'01 Inputs'!$G$41)<=750,'01 Inputs'!$G$46,'01 Inputs'!$G$47))))*'01 Inputs'!$G$48)*(1+'01 Inputs'!$G$52+'01 Inputs'!$G$54)+'01 Inputs'!$G$51+'01 Inputs'!$G$53)/(1-(1+'01 Inputs'!$G$11)*'01 Inputs'!$G$50-'01 Inputs'!$G$54-$B$66)*(1+'01 Inputs'!$G$11)/'01 Inputs'!$G$90) | F66: =E66/'01 Inputs'!$G$15
B67: 0.65 | C67: =IF((1-(1+'01 Inputs'!$G$11)*'01 Inputs'!$G$50-'01 Inputs'!$G$54-$B$67)<=0,"impossible",(('01 Inputs'!$G$15*'01 Inputs'!$G$27+'01 Inputs'!$G$15*'01 Inputs'!$G$31+'01 Inputs'!$G$32+'01 Inputs'!$G$33)*(1+'01 Inputs'!$G$52+'01 Inputs'!$G$54)+'01 Inputs'!$G$39*(1+'01 Inputs'!$G$52)+(IF(('01 Inputs'!$G$15*'01 Inputs'!$G$14+'01 Inputs'!$G$15*'01 Inputs'!$G$40+'01 Inputs'!$G$41)<=100,'01 Inputs'!$G$43,IF(('01 Inputs'!$G$15*'01 Inputs'!$G$14+'01 Inputs'!$G$15*'01 Inputs'!$G$40+'01 Inputs'!$G$41)<=250,'01 Inputs'!$G$44,IF(('01 Inputs'!$G$15*'01 Inputs'!$G$14+'01 Inputs'!$G$15*'01 Inputs'!$G$40+'01 Inputs'!$G$41)<=500,'01 Inputs'!$G$45,IF(('01 Inputs'!$G$15*'01 Inputs'!$G$14+'01 Inputs'!$G$15*'01 Inputs'!$G$40+'01 Inputs'!$G$41)<=750,'01 Inputs'!$G$46,'01 Inputs'!$G$47))))*'01 Inputs'!$G$48)*(1+'01 Inputs'!$G$52+'01 Inputs'!$G$54)+'01 Inputs'!$G$51+'01 Inputs'!$G$53)/(1-(1+'01 Inputs'!$G$11)*'01 Inputs'!$G$50-'01 Inputs'!$G$54-$B$67)*(1+'01 Inputs'!$G$11)/'01 Inputs'!$G$90) | D67: =C67/'01 Inputs'!$G$15 | E67: =IF((1-(1+'01 Inputs'!$G$11)*'01 Inputs'!$G$50-'01 Inputs'!$G$54-$B$67)<=0,"impossible",(('01 Inputs'!$G$15*'01 Inputs'!$G$28+'01 Inputs'!$G$15*'01 Inputs'!$G$31+'01 Inputs'!$G$32+'01 Inputs'!$G$33)*(1+'01 Inputs'!$G$52+'01 Inputs'!$G$54)+'01 Inputs'!$G$39*(1+'01 Inputs'!$G$52)+(IF(('01 Inputs'!$G$15*'01 Inputs'!$G$14+'01 Inputs'!$G$15*'01 Inputs'!$G$40+'01 Inputs'!$G$41)<=100,'01 Inputs'!$G$43,IF(('01 Inputs'!$G$15*'01 Inputs'!$G$14+'01 Inputs'!$G$15*'01 Inputs'!$G$40+'01 Inputs'!$G$41)<=250,'01 Inputs'!$G$44,IF(('01 Inputs'!$G$15*'01 Inputs'!$G$14+'01 Inputs'!$G$15*'01 Inputs'!$G$40+'01 Inputs'!$G$41)<=500,'01 Inputs'!$G$45,IF(('01 Inputs'!$G$15*'01 Inputs'!$G$14+'01 Inputs'!$G$15*'01 Inputs'!$G$40+'01 Inputs'!$G$41)<=750,'01 Inputs'!$G$46,'01 Inputs'!$G$47))))*'01 Inputs'!$G$48)*(1+'01 Inputs'!$G$52+'01 Inputs'!$G$54)+'01 Inputs'!$G$51+'01 Inputs'!$G$53)/(1-(1+'01 Inputs'!$G$11)*'01 Inputs'!$G$50-'01 Inputs'!$G$54-$B$67)*(1+'01 Inputs'!$G$11)/'01 Inputs'!$G$90) | F67: =E67/'01 Inputs'!$G$15
B68: 0.7 | C68: =IF((1-(1+'01 Inputs'!$G$11)*'01 Inputs'!$G$50-'01 Inputs'!$G$54-$B$68)<=0,"impossible",(('01 Inputs'!$G$15*'01 Inputs'!$G$27+'01 Inputs'!$G$15*'01 Inputs'!$G$31+'01 Inputs'!$G$32+'01 Inputs'!$G$33)*(1+'01 Inputs'!$G$52+'01 Inputs'!$G$54)+'01 Inputs'!$G$39*(1+'01 Inputs'!$G$52)+(IF(('01 Inputs'!$G$15*'01 Inputs'!$G$14+'01 Inputs'!$G$15*'01 Inputs'!$G$40+'01 Inputs'!$G$41)<=100,'01 Inputs'!$G$43,IF(('01 Inputs'!$G$15*'01 Inputs'!$G$14+'01 Inputs'!$G$15*'01 Inputs'!$G$40+'01 Inputs'!$G$41)<=250,'01 Inputs'!$G$44,IF(('01 Inputs'!$G$15*'01 Inputs'!$G$14+'01 Inputs'!$G$15*'01 Inputs'!$G$40+'01 Inputs'!$G$41)<=500,'01 Inputs'!$G$45,IF(('01 Inputs'!$G$15*'01 Inputs'!$G$14+'01 Inputs'!$G$15*'01 Inputs'!$G$40+'01 Inputs'!$G$41)<=750,'01 Inputs'!$G$46,'01 Inputs'!$G$47))))*'01 Inputs'!$G$48)*(1+'01 Inputs'!$G$52+'01 Inputs'!$G$54)+'01 Inputs'!$G$51+'01 Inputs'!$G$53)/(1-(1+'01 Inputs'!$G$11)*'01 Inputs'!$G$50-'01 Inputs'!$G$54-$B$68)*(1+'01 Inputs'!$G$11)/'01 Inputs'!$G$90) | D68: =C68/'01 Inputs'!$G$15 | E68: =IF((1-(1+'01 Inputs'!$G$11)*'01 Inputs'!$G$50-'01 Inputs'!$G$54-$B$68)<=0,"impossible",(('01 Inputs'!$G$15*'01 Inputs'!$G$28+'01 Inputs'!$G$15*'01 Inputs'!$G$31+'01 Inputs'!$G$32+'01 Inputs'!$G$33)*(1+'01 Inputs'!$G$52+'01 Inputs'!$G$54)+'01 Inputs'!$G$39*(1+'01 Inputs'!$G$52)+(IF(('01 Inputs'!$G$15*'01 Inputs'!$G$14+'01 Inputs'!$G$15*'01 Inputs'!$G$40+'01 Inputs'!$G$41)<=100,'01 Inputs'!$G$43,IF(('01 Inputs'!$G$15*'01 Inputs'!$G$14+'01 Inputs'!$G$15*'01 Inputs'!$G$40+'01 Inputs'!$G$41)<=250,'01 Inputs'!$G$44,IF(('01 Inputs'!$G$15*'01 Inputs'!$G$14+'01 Inputs'!$G$15*'01 Inputs'!$G$40+'01 Inputs'!$G$41)<=500,'01 Inputs'!$G$45,IF(('01 Inputs'!$G$15*'01 Inputs'!$G$14+'01 Inputs'!$G$15*'01 Inputs'!$G$40+'01 Inputs'!$G$41)<=750,'01 Inputs'!$G$46,'01 Inputs'!$G$47))))*'01 Inputs'!$G$48)*(1+'01 Inputs'!$G$52+'01 Inputs'!$G$54)+'01 Inputs'!$G$51+'01 Inputs'!$G$53)/(1-(1+'01 Inputs'!$G$11)*'01 Inputs'!$G$50-'01 Inputs'!$G$54-$B$68)*(1+'01 Inputs'!$G$11)/'01 Inputs'!$G$90) | F68: =E68/'01 Inputs'!$G$15
B69: 0.75 | C69: =IF((1-(1+'01 Inputs'!$G$11)*'01 Inputs'!$G$50-'01 Inputs'!$G$54-$B$69)<=0,"impossible",(('01 Inputs'!$G$15*'01 Inputs'!$G$27+'01 Inputs'!$G$15*'01 Inputs'!$G$31+'01 Inputs'!$G$32+'01 Inputs'!$G$33)*(1+'01 Inputs'!$G$52+'01 Inputs'!$G$54)+'01 Inputs'!$G$39*(1+'01 Inputs'!$G$52)+(IF(('01 Inputs'!$G$15*'01 Inputs'!$G$14+'01 Inputs'!$G$15*'01 Inputs'!$G$40+'01 Inputs'!$G$41)<=100,'01 Inputs'!$G$43,IF(('01 Inputs'!$G$15*'01 Inputs'!$G$14+'01 Inputs'!$G$15*'01 Inputs'!$G$40+'01 Inputs'!$G$41)<=250,'01 Inputs'!$G$44,IF(('01 Inputs'!$G$15*'01 Inputs'!$G$14+'01 Inputs'!$G$15*'01 Inputs'!$G$40+'01 Inputs'!$G$41)<=500,'01 Inputs'!$G$45,IF(('01 Inputs'!$G$15*'01 Inputs'!$G$14+'01 Inputs'!$G$15*'01 Inputs'!$G$40+'01 Inputs'!$G$41)<=750,'01 Inputs'!$G$46,'01 Inputs'!$G$47))))*'01 Inputs'!$G$48)*(1+'01 Inputs'!$G$52+'01 Inputs'!$G$54)+'01 Inputs'!$G$51+'01 Inputs'!$G$53)/(1-(1+'01 Inputs'!$G$11)*'01 Inputs'!$G$50-'01 Inputs'!$G$54-$B$69)*(1+'01 Inputs'!$G$11)/'01 Inputs'!$G$90) | D69: =C69/'01 Inputs'!$G$15 | E69: =IF((1-(1+'01 Inputs'!$G$11)*'01 Inputs'!$G$50-'01 Inputs'!$G$54-$B$69)<=0,"impossible",(('01 Inputs'!$G$15*'01 Inputs'!$G$28+'01 Inputs'!$G$15*'01 Inputs'!$G$31+'01 Inputs'!$G$32+'01 Inputs'!$G$33)*(1+'01 Inputs'!$G$52+'01 Inputs'!$G$54)+'01 Inputs'!$G$39*(1+'01 Inputs'!$G$52)+(IF(('01 Inputs'!$G$15*'01 Inputs'!$G$14+'01 Inputs'!$G$15*'01 Inputs'!$G$40+'01 Inputs'!$G$41)<=100,'01 Inputs'!$G$43,IF(('01 Inputs'!$G$15*'01 Inputs'!$G$14+'01 Inputs'!$G$15*'01 Inputs'!$G$40+'01 Inputs'!$G$41)<=250,'01 Inputs'!$G$44,IF(('01 Inputs'!$G$15*'01 Inputs'!$G$14+'01 Inputs'!$G$15*'01 Inputs'!$G$40+'01 Inputs'!$G$41)<=500,'01 Inputs'!$G$45,IF(('01 Inputs'!$G$15*'01 Inputs'!$G$14+'01 Inputs'!$G$15*'01 Inputs'!$G$40+'01 Inputs'!$G$41)<=750,'01 Inputs'!$G$46,'01 Inputs'!$G$47))))*'01 Inputs'!$G$48)*(1+'01 Inputs'!$G$52+'01 Inputs'!$G$54)+'01 Inputs'!$G$51+'01 Inputs'!$G$53)/(1-(1+'01 Inputs'!$G$11)*'01 Inputs'!$G$50-'01 Inputs'!$G$54-$B$69)*(1+'01 Inputs'!$G$11)/'01 Inputs'!$G$90) | F69: =E69/'01 Inputs'!$G$15
H70: Floors are for a 30-tablet monthly pack shipped on Large Letter. They rise with pack size only slowly, because postage and fulfilment are per ORDER, not per serving — which is the arithmetic case for a larger pack or a longer cadence.
B71: HOW TO USE THE FLOOR. Read across to the price your chosen architecture actually charges. If the charged price is well above the floor for a 65-70% contribution margin, the pricing has headroom and the argument is about willingness to pay, not about cost. If it is below, the architecture does not work and no amount of positioning fixes it. Note what the patented-forms column does: it raises the floor, but by far less than the premium it is supposed to unlock — which is the honest commercial case for 'clinical'. The risk is not that branded forms are unaffordable; it is A-043, that the specific branded form may not be a permitted GB source form at all.
B73: WHICH LADDER DOES EACH ARCHITECTURE ASK TO BE JUDGED ON? A1 and A4 sit inside the effervescent band and invite the Berocca/Tesco comparison, which V-Drop loses. A2 and A3 sit at or above Waterdrop and inside the premium daily-vitamin band, which is the comparison a taste-and-ritual proposition can actually win — provided the brand never lets the word 'effervescent' be the headline (A-033: Waterdrop is effervescent and has never once used the word).
